Workbook
Name IT_Sectors: '00 COMMON - Run Setup'!$AA$5
Name OT_Sectors: '00 COMMON - Run Setup'!$AB$5:$AB$7
Name Financial_Services: '00 COMMON - Run Setup'!$Z$8
Name Power_Generation: 'OT PACK - Loaded Registry'!$B$25:$B$30
Name Energy_Assets: 'OT PACK - Loaded Registry'!$B$31:$B$35
Name Manufacturing: 'OT PACK - Loaded Registry'!$B$36:$B$39

Sheet 1 Executive dashboards
A1: 1 Executive dashboards
A3: Read after python -m crq run. Do not enter assessment data here.

Sheet 01 Executive Risk Story

Sheet 02 Risk Formation

Sheet 03 Scenario Analysis

Sheet 04 Business Impact

Sheet 05 Risk Treatment

Sheet 06 Appetite & Insurance
A1: 06 — Appetite & Insurance
A2: Risk-appetite thresholds are organisational policy inputs. Insurance programme terms are risk-financing inputs — not pricing.
A4: RISK APPETITE INPUTS (optional — leave blank if unset)
A5: Parameter | B5: Value
A6: ANNUAL_LOSS_TOLERANCE | C6: Annual aggregate loss tolerance ($)
A7: MAX_ACCEPTABLE_EVENT_PROBABILITY | C7: Max acceptable annual event probability
A8: MAX_ACCEPTABLE_TVAR_95 | C8: Max acceptable TVaR 95 ($)
A9: MAX_ACCEPTABLE_TVAR_99 | C9: Max acceptable TVaR 99 ($)
A10: MAX_ACCEPTABLE_DOWNTIME_DAYS | C10: Max acceptable downtime P95 (days)
A12: INSURANCE PROGRAMME INPUTS (risk-financing — not pricing)
A13: INSURANCE_RETENTION | B13: 0
A14: PRIMARY_LIMIT
A15: AGGREGATE_PROGRAMME_LIMIT
A17: Layer | B17: Attachment | C17: Limit | D17: Coinsurance
A18: Primary | D18: 1
A19: Excess 1 | D19: 1
A20: INSURANCE PROGRAMME INPUTS | D20: 1
A21: Excess 3 | D21: 1

Sheet 07 Uncertainty & Evidence

Sheet 00 Dashboard
A1: IT / OT CYBER RISK QUANTIFICATION | EXECUTIVE DASHBOARD
A2: Common decision view. The selected sector determines the governed calculation engine; dashboard metrics read the normalized output bridge.
A4: Sector | B4: ='00 COMMON - Output Bridge'!B6 | C4: Domain | D4: ='00 COMMON - Output Bridge'!B7 | E4: Pack | F4: ='00 COMMON - Output Bridge'!B9 | G4: Basis | H4: =IF('00 COMMON - Run Setup'!C6="IT",'IT 08 - Reporting Settings'!B16,'00 COMMON - Run Setup'!C9) | I4: Outside-in | J4: ='00 COMMON - Run Setup'!C10 | K4: Asset / scope | L4: ='00 COMMON - Output Bridge'!B8
A7: ANNUAL AVERAGE LOSS | D7: TVaR 95% | G7: TVaR 99% | J7: P(ANY SUCCESSFUL EVENT) | M7: CAMPAIGNS / YEAR
A8: =IF('00 COMMON - Run Setup'!C9="Best Estimate",'00 COMMON - Output Bridge'!B15,'00 COMMON - Output Bridge'!C15) | D8: =IF('00 COMMON - Run Setup'!C9="Best Estimate",'00 COMMON - Output Bridge'!B17,'00 COMMON - Output Bridge'!C17) | G8: =IF('00 COMMON - Run Setup'!C9="Best Estimate",'00 COMMON - Output Bridge'!B19,'00 COMMON - Output Bridge'!C19) | J8: =IF('00 COMMON - Run Setup'!C9="Best Estimate",'00 COMMON - Output Bridge'!B20,'00 COMMON - Output Bridge'!C20) | M8: =IF('00 COMMON - Run Setup'!C9="Best Estimate",'00 COMMON - Output Bridge'!B21,'00 COMMON - Output Bridge'!C21)
A12: AGGREGATE LOSS EXCEEDANCE
A13: Exceedance probability | B13: AEP | C13: OEP
A14: ='00 COMMON - Output Bridge'!A43 | B14: =IF('00 COMMON - Run Setup'!C9="Best Estimate",'00 COMMON - Output Bridge'!B43,'00 COMMON - Output Bridge'!D43) | C14: =IF('00 COMMON - Run Setup'!C9="Best Estimate",'00 COMMON - Output Bridge'!C43,'00 COMMON - Output Bridge'!E43)
A15: ='00 COMMON - Output Bridge'!A44 | B15: =IF('00 COMMON - Run Setup'!C9="Best Estimate",'00 COMMON - Output Bridge'!B44,'00 COMMON - Output Bridge'!D44) | C15: =IF('00 COMMON - Run Setup'!C9="Best Estimate",'00 COMMON - Output Bridge'!C44,'00 COMMON - Output Bridge'!E44)
A16: ='00 COMMON - Output Bridge'!A45 | B16: =IF('00 COMMON - Run Setup'!C9="Best Estimate",'00 COMMON - Output Bridge'!B45,'00 COMMON - Output Bridge'!D45) | C16: =IF('00 COMMON - Run Setup'!C9="Best Estimate",'00 COMMON - Output Bridge'!C45,'00 COMMON - Output Bridge'!E45)
A17: ='00 COMMON - Output Bridge'!A46 | B17: =IF('00 COMMON - Run Setup'!C9="Best Estimate",'00 COMMON - Output Bridge'!B46,'00 COMMON - Output Bridge'!D46) | C17: =IF('00 COMMON - Run Setup'!C9="Best Estimate",'00 COMMON - Output Bridge'!C46,'00 COMMON - Output Bridge'!E46)
A18: ='00 COMMON - Output Bridge'!A47 | B18: =IF('00 COMMON - Run Setup'!C9="Best Estimate",'00 COMMON - Output Bridge'!B47,'00 COMMON - Output Bridge'!D47) | C18: =IF('00 COMMON - Run Setup'!C9="Best Estimate",'00 COMMON - Output Bridge'!C47,'00 COMMON - Output Bridge'!E47)
A19: ='00 COMMON - Output Bridge'!A48 | B19: =IF('00 COMMON - Run Setup'!C9="Best Estimate",'00 COMMON - Output Bridge'!B48,'00 COMMON - Output Bridge'!D48) | C19: =IF('00 COMMON - Run Setup'!C9="Best Estimate",'00 COMMON - Output Bridge'!C48,'00 COMMON - Output Bridge'!E48)
A20: ='00 COMMON - Output Bridge'!A49 | B20: =IF('00 COMMON - Run Setup'!C9="Best Estimate",'00 COMMON - Output Bridge'!B49,'00 COMMON - Output Bridge'!D49) | C20: =IF('00 COMMON - Run Setup'!C9="Best Estimate",'00 COMMON - Output Bridge'!C49,'00 COMMON - Output Bridge'!E49)
A21: ='00 COMMON - Output Bridge'!A50 | B21: =IF('00 COMMON - Run Setup'!C9="Best Estimate",'00 COMMON - Output Bridge'!B50,'00 COMMON - Output Bridge'!D50) | C21: =IF('00 COMMON - Run Setup'!C9="Best Estimate",'00 COMMON - Output Bridge'!C50,'00 COMMON - Output Bridge'!E50)
A22: ='00 COMMON - Output Bridge'!A51 | B22: =IF('00 COMMON - Run Setup'!C9="Best Estimate",'00 COMMON - Output Bridge'!B51,'00 COMMON - Output Bridge'!D51) | C22: =IF('00 COMMON - Run Setup'!C9="Best Estimate",'00 COMMON - Output Bridge'!C51,'00 COMMON - Output Bridge'!E51)
A23: ='00 COMMON - Output Bridge'!A52 | B23: =IF('00 COMMON - Run Setup'!C9="Best Estimate",'00 COMMON - Output Bridge'!B52,'00 COMMON - Output Bridge'!D52) | C23: =IF('00 COMMON - Run Setup'!C9="Best Estimate",'00 COMMON - Output Bridge'!C52,'00 COMMON - Output Bridge'!E52)
A24: ='00 COMMON - Output Bridge'!A53 | B24: =IF('00 COMMON - Run Setup'!C9="Best Estimate",'00 COMMON - Output Bridge'!B53,'00 COMMON - Output Bridge'!D53) | C24: =IF('00 COMMON - Run Setup'!C9="Best Estimate",'00 COMMON - Output Bridge'!C53,'00 COMMON - Output Bridge'!E53)
A29: RISK CONCENTRATION
A30: Threat actor | B30: AAL | I30: Scenario | J30: AAL
A31: ='00 COMMON - Output Bridge'!A27 | B31: ='00 COMMON - Output Bridge'!B27 | I31: ='00 COMMON - Output Bridge'!A34 | J31: ='00 COMMON - Output Bridge'!B34
A32: ='00 COMMON - Output Bridge'!A28 | B32: ='00 COMMON - Output Bridge'!B28 | I32: ='00 COMMON - Output Bridge'!A35 | J32: ='00 COMMON - Output Bridge'!B35
A33: ='00 COMMON - Output Bridge'!A29 | B33: ='00 COMMON - Output Bridge'!B29 | I33: ='00 COMMON - Output Bridge'!A36 | J33: ='00 COMMON - Output Bridge'!B36
A34: ='00 COMMON - Output Bridge'!A30 | B34: ='00 COMMON - Output Bridge'!B30 | I34: ='00 COMMON - Output Bridge'!A37 | J34: ='00 COMMON - Output Bridge'!B37
I35: ='00 COMMON - Output Bridge'!A38 | J35: ='00 COMMON - Output Bridge'!B38
A46: OUTSIDE-IN CONDITIONING STATUS
A47: Scan applied? | B47: ='00 COMMON - Run Setup'!C10 | C47: Normalized file | D47: ='00 COMMON - Run Setup'!C11 | G47: Finding count | H47: ='00 COMMON - Outside-In'!B10 | I47: Quantitative adjustments | J47: ='00 COMMON - Outside-In'!B11 | K47: Baseline retained? | L47: =IF('00 COMMON - Run Setup'!C10="No","Yes","See rationale register")
A49: Interpretation | B49: No scan is a valid model state. When a scan is used, the final result must remain explainable through 00 OI Adjustment Rationale; no opaque scan-score multiplier is permitted.

Sheet 00 Risk Drivers
A1: IT / OT CYBER RISK QUANTIFICATION | RISK DRIVERS
A2: OT view: drill from actor/scenario into the five composite stages. For an IT run, the common runner should populate the normalized route/stage bridge using the IT route model rather than forcing OT stages.
A4: Threat actor | B4: Nation State | C4: Scenario | D4: Operational Disruption | E4: Detailed view | F4: Current engine output
A7: SELECTED ACTOR × SCENARIO
A8: Attempts / yr | B8: =IF('00 COMMON - Run Setup'!C6="OT",SUMIFS('OT CALC - Threat Frequency'!L16:L30,'OT CALC - Threat Frequency'!A16:A30,B4,'OT CALC - Threat Frequency'!B16:B30,D4),"") | C8: P(success) | D8: =IFERROR(IF('00 COMMON - Run Setup'!C6="OT",SUMIFS('OT CALC - Threat Frequency'!M16:M30,'OT CALC - Threat Frequency'!A16:A30,B4,'OT CALC - Threat Frequency'!B16:B30,D4),""),"") | E8: Successful events / yr | F8: =IF('00 COMMON - Run Setup'!C6="OT",SUMIFS('OT CALC - Threat Frequency'!N16:N30,'OT CALC - Threat Frequency'!A16:A30,B4,'OT CALC - Threat Frequency'!B16:B30,D4),"") | G8: AAL contribution | H8: =IF('00 COMMON - Run Setup'!C6="OT",INDEX('OT CALC - Actor-Scenario Matrix'!B16:F18,MATCH(B4,'OT CALC - Actor-Scenario Matrix'!A16:A18,0),MATCH(D4,'OT CALC - Actor-Scenario Matrix'!B15:F15,0)),"")
A12: COMPOSITE ATTACK-PATH STAGES
A13: Stage | B13: Required? | C13: Relevant TTPs | D13: Reference prior | E13: Actual barrier | F13: Through probability | G13: Interpretation
A14: S1 | B14: =IF('00 COMMON - Run Setup'!C6="OT",IF(COUNTIFS('OT CALC - Attack Path'!A16:A200,$B$4,'OT CALC - Attack Path'!B16:B200,$D$4,'OT CALC - Attack Path'!C16:C200,A14,'OT CALC - Attack Path'!D16:D200,"Yes")>0,"Yes","No"),"") | C14: =IF('00 COMMON - Run Setup'!C6="OT",SUMIFS('OT CALC - Attack Path'!E16:E200,'OT CALC - Attack Path'!A16:A200,$B$4,'OT CALC - Attack Path'!B16:B200,$D$4,'OT CALC - Attack Path'!C16:C200,A14),"") | D14: =IF('00 COMMON - Run Setup'!C6="OT",SUMIFS('OT CALC - Attack Path'!H16:H200,'OT CALC - Attack Path'!A16:A200,$B$4,'OT CALC - Attack Path'!B16:B200,$D$4,'OT CALC - Attack Path'!C16:C200,A14),"") | E14: =IF('00 COMMON - Run Setup'!C6="OT",SUMIFS('OT CALC - Attack Path'!J16:J200,'OT CALC - Attack Path'!A16:A200,$B$4,'OT CALC - Attack Path'!B16:B200,$D$4,'OT CALC - Attack Path'!C16:C200,A14),"") | F14: =IF('00 COMMON - Run Setup'!C6="OT",SUMIFS('OT CALC - Attack Path'!L16:L200,'OT CALC - Attack Path'!A16:A200,$B$4,'OT CALC - Attack Path'!B16:B200,$D$4,'OT CALC - Attack Path'!C16:C200,A14),"") | G14: Initial access
A15: S2 | B15: =IF('00 COMMON - Run Setup'!C6="OT",IF(COUNTIFS('OT CALC - Attack Path'!A16:A200,$B$4,'OT CALC - Attack Path'!B16:B200,$D$4,'OT CALC - Attack Path'!C16:C200,A15,'OT CALC - Attack Path'!D16:D200,"Yes")>0,"Yes","No"),"") | C15: =IF('00 COMMON - Run Setup'!C6="OT",SUMIFS('OT CALC - Attack Path'!E16:E200,'OT CALC - Attack Path'!A16:A200,$B$4,'OT CALC - Attack Path'!B16:B200,$D$4,'OT CALC - Attack Path'!C16:C200,A15),"") | D15: =IF('00 COMMON - Run Setup'!C6="OT",SUMIFS('OT CALC - Attack Path'!H16:H200,'OT CALC - Attack Path'!A16:A200,$B$4,'OT CALC - Attack Path'!B16:B200,$D$4,'OT CALC - Attack Path'!C16:C200,A15),"") | E15: =IF('00 COMMON - Run Setup'!C6="OT",SUMIFS('OT CALC - Attack Path'!J16:J200,'OT CALC - Attack Path'!A16:A200,$B$4,'OT CALC - Attack Path'!B16:B200,$D$4,'OT CALC - Attack Path'!C16:C200,A15),"") | F15: =IF('00 COMMON - Run Setup'!C6="OT",SUMIFS('OT CALC - Attack Path'!L16:L200,'OT CALC - Attack Path'!A16:A200,$B$4,'OT CALC - Attack Path'!B16:B200,$D$4,'OT CALC - Attack Path'!C16:C200,A15),"") | G15: Establish presence
A16: S3 | B16: =IF('00 COMMON - Run Setup'!C6="OT",IF(COUNTIFS('OT CALC - Attack Path'!A16:A200,$B$4,'OT CALC - Attack Path'!B16:B200,$D$4,'OT CALC - Attack Path'!C16:C200,A16,'OT CALC - Attack Path'!D16:D200,"Yes")>0,"Yes","No"),"") | C16: =IF('00 COMMON - Run Setup'!C6="OT",SUMIFS('OT CALC - Attack Path'!E16:E200,'OT CALC - Attack Path'!A16:A200,$B$4,'OT CALC - Attack Path'!B16:B200,$D$4,'OT CALC - Attack Path'!C16:C200,A16),"") | D16: =IF('00 COMMON - Run Setup'!C6="OT",SUMIFS('OT CALC - Attack Path'!H16:H200,'OT CALC - Attack Path'!A16:A200,$B$4,'OT CALC - Attack Path'!B16:B200,$D$4,'OT CALC - Attack Path'!C16:C200,A16),"") | E16: =IF('00 COMMON - Run Setup'!C6="OT",SUMIFS('OT CALC - Attack Path'!J16:J200,'OT CALC - Attack Path'!A16:A200,$B$4,'OT CALC - Attack Path'!B16:B200,$D$4,'OT CALC - Attack Path'!C16:C200,A16),"") | F16: =IF('00 COMMON - Run Setup'!C6="OT",SUMIFS('OT CALC - Attack Path'!L16:L200,'OT CALC - Attack Path'!A16:A200,$B$4,'OT CALC - Attack Path'!B16:B200,$D$4,'OT CALC - Attack Path'!C16:C200,A16),"") | G16: Move into OT
A17: S4 | B17: =IF('00 COMMON - Run Setup'!C6="OT",IF(COUNTIFS('OT CALC - Attack Path'!A16:A200,$B$4,'OT CALC - Attack Path'!B16:B200,$D$4,'OT CALC - Attack Path'!C16:C200,A17,'OT CALC - Attack Path'!D16:D200,"Yes")>0,"Yes","No"),"") | C17: =IF('00 COMMON - Run Setup'!C6="OT",SUMIFS('OT CALC - Attack Path'!E16:E200,'OT CALC - Attack Path'!A16:A200,$B$4,'OT CALC - Attack Path'!B16:B200,$D$4,'OT CALC - Attack Path'!C16:C200,A17),"") | D17: =IF('00 COMMON - Run Setup'!C6="OT",SUMIFS('OT CALC - Attack Path'!H16:H200,'OT CALC - Attack Path'!A16:A200,$B$4,'OT CALC - Attack Path'!B16:B200,$D$4,'OT CALC - Attack Path'!C16:C200,A17),"") | E17: =IF('00 COMMON - Run Setup'!C6="OT",SUMIFS('OT CALC - Attack Path'!J16:J200,'OT CALC - Attack Path'!A16:A200,$B$4,'OT CALC - Attack Path'!B16:B200,$D$4,'OT CALC - Attack Path'!C16:C200,A17),"") | F17: =IF('00 COMMON - Run Setup'!C6="OT",SUMIFS('OT CALC - Attack Path'!L16:L200,'OT CALC - Attack Path'!A16:A200,$B$4,'OT CALC - Attack Path'!B16:B200,$D$4,'OT CALC - Attack Path'!C16:C200,A17),"") | G17: Understand the process
A18: S5 | B18: =IF('00 COMMON - Run Setup'!C6="OT",IF(COUNTIFS('OT CALC - Attack Path'!A16:A200,$B$4,'OT CALC - Attack Path'!B16:B200,$D$4,'OT CALC - Attack Path'!C16:C200,A18,'OT CALC - Attack Path'!D16:D200,"Yes")>0,"Yes","No"),"") | C18: =IF('00 COMMON - Run Setup'!C6="OT",SUMIFS('OT CALC - Attack Path'!E16:E200,'OT CALC - Attack Path'!A16:A200,$B$4,'OT CALC - Attack Path'!B16:B200,$D$4,'OT CALC - Attack Path'!C16:C200,A18),"") | D18: =IF('00 COMMON - Run Setup'!C6="OT",SUMIFS('OT CALC - Attack Path'!H16:H200,'OT CALC - Attack Path'!A16:A200,$B$4,'OT CALC - Attack Path'!B16:B200,$D$4,'OT CALC - Attack Path'!C16:C200,A18),"") | E18: =IF('00 COMMON - Run Setup'!C6="OT",SUMIFS('OT CALC - Attack Path'!J16:J200,'OT CALC - Attack Path'!A16:A200,$B$4,'OT CALC - Attack Path'!B16:B200,$D$4,'OT CALC - Attack Path'!C16:C200,A18),"") | F18: =IF('00 COMMON - Run Setup'!C6="OT",SUMIFS('OT CALC - Attack Path'!L16:L200,'OT CALC - Attack Path'!A16:A200,$B$4,'OT CALC - Attack Path'!B16:B200,$D$4,'OT CALC - Attack Path'!C16:C200,A18),"") | G18: Achieve adverse outcome
A21: OUTSIDE-IN EVIDENCE LINK
A22: When applied, outside-in evidence should appear as a traceable change to an existing exposure/frequency input, a route-feasibility gate, or a relevant stage/barrier. Use 00 Outside-In for the observed evidence and 00 OI Adjustment Rationale for the baseline-to-conditioned bridge. Do not insert a scan score directly into AAL.

Sheet 00 Loss Analysis
A1: IT / OT CYBER RISK QUANTIFICATION | LOSS ANALYSIS
A2: Event-level consequence view. Outside-in evidence does not alter these financial impact assumptions solely because an external exposure is observed.
A4: Threat actor | B4: Nation State | C4: Scenario | D4: Operational Disruption | E4: Loss view | F4: P50 / P99
A7: SELECTED EVENT CONSEQUENCE
A8: Metric | B8: P50 | C8: P99 | D8: Meaning
A9: Downtime (days) | B9: =IF('00 COMMON - Run Setup'!C6="OT",SUMIFS('OT CALC - Consequence'!C16:C30,'OT CALC - Consequence'!A16:A30,$B$4,'OT CALC - Consequence'!B16:B30,$D$4),"") | C9: =IF('00 COMMON - Run Setup'!C6="OT",SUMIFS('OT CALC - Consequence'!D16:D30,'OT CALC - Consequence'!A16:A30,$B$4,'OT CALC - Consequence'!B16:B30,$D$4),"") | D9: Scenario/facility recovery duration
A10: Capacity affected | B10: =IF('00 COMMON - Run Setup'!C6="OT",SUMIFS('OT CALC - Consequence'!E16:E30,'OT CALC - Consequence'!A16:A30,$B$4,'OT CALC - Consequence'!B16:B30,$D$4),"") | C10: =IF('00 COMMON - Run Setup'!C6="OT",SUMIFS('OT CALC - Consequence'!F16:F30,'OT CALC - Consequence'!A16:A30,$B$4,'OT CALC - Consequence'!B16:B30,$D$4),"") | D10: Share of scoped capacity affected
A11: Total event loss | B11: =IF('00 COMMON - Run Setup'!C6="OT",SUMIFS('OT CALC - Consequence'!M16:M30,'OT CALC - Consequence'!A16:A30,$B$4,'OT CALC - Consequence'!B16:B30,$D$4),"") | C11: =IF('00 COMMON - Run Setup'!C6="OT",SUMIFS('OT CALC - Consequence'!N16:N30,'OT CALC - Consequence'!A16:A30,$B$4,'OT CALC - Consequence'!B16:B30,$D$4),"") | D11: Modelled BI + non-BI consequence
A14: BI / NON-BI DECOMPOSITION
A15: Component | B15: P50 | C15: P99
A16: Modelled BI | B16: =IF('00 COMMON - Run Setup'!C6="OT",SUMIFS('OT CALC - Consequence'!I16:I30,'OT CALC - Consequence'!A16:A30,$B$4,'OT CALC - Consequence'!B16:B30,$D$4),"") | C16: =IF('00 COMMON - Run Setup'!C6="OT",SUMIFS('OT CALC - Consequence'!J16:J30,'OT CALC - Consequence'!A16:A30,$B$4,'OT CALC - Consequence'!B16:B30,$D$4),"")
A17: Non-BI consequence | B17: =IF('00 COMMON - Run Setup'!C6="OT",SUMIFS('OT CALC - Consequence'!K16:K30,'OT CALC - Consequence'!A16:A30,$B$4,'OT CALC - Consequence'!B16:B30,$D$4),"") | C17: =IF('00 COMMON - Run Setup'!C6="OT",SUMIFS('OT CALC - Consequence'!L16:L30,'OT CALC - Consequence'!A16:A30,$B$4,'OT CALC - Consequence'!B16:B30,$D$4),"")
A32: OUTSIDE-IN BOUNDARY — Scan evidence can change likelihood because it provides evidence about external opportunity, exposed services, exploitable vulnerabilities or route feasibility. It does not independently evidence revenue-at-risk, restoration time, capacity affected, physical damage, safety, environmental loss or other consequence drivers.

Sheet 00 What-If
A1: IT / OT CYBER RISK QUANTIFICATION | CONTROL WHAT-IF
A2: Decision view of modelled control improvement. Engine-generated what-if values remain the system of record.
A4: Basis | B4: ='00 COMMON - Run Setup'!C9 | C4: Source | D4: 20 Control What-If
A7: CONTROL IMPROVEMENT RESULTS
A8: Control ID | B8: Control | C8: Channel | D8: Current maturity | E8: What-if maturity | F8: AAL reduction | G8: Reduction % | I8: Outside-in findings should not become a second what-if framework. Where a scan identifies a real exposure or exploitable weakness, the evidence-conditioned baseline is recorded first. Control what-if analysis then asks what happens if the relevant control is improved from that evidenced current state.
A9: ='OT CALC - Control What-If'!A16 | B9: ='OT CALC - Control What-If'!B16 | C9: ='OT CALC - Control What-If'!C16 | D9: ='OT CALC - Control What-If'!D16 | E9: ='OT CALC - Control What-If'!E16 | F9: =IF($B$4="Best Estimate",'OT CALC - Control What-If'!H16,'OT CALC - Control What-If'!L16) | G9: =IF($B$4="Best Estimate",'OT CALC - Control What-If'!I16,'OT CALC - Control What-If'!M16)
A10: ='OT CALC - Control What-If'!A17 | B10: ='OT CALC - Control What-If'!B17 | C10: ='OT CALC - Control What-If'!C17 | D10: ='OT CALC - Control What-If'!D17 | E10: ='OT CALC - Control What-If'!E17 | F10: =IF($B$4="Best Estimate",'OT CALC - Control What-If'!H17,'OT CALC - Control What-If'!L17) | G10: =IF($B$4="Best Estimate",'OT CALC - Control What-If'!I17,'OT CALC - Control What-If'!M17)
A11: ='OT CALC - Control What-If'!A18 | B11: ='OT CALC - Control What-If'!B18 | C11: ='OT CALC - Control What-If'!C18 | D11: ='OT CALC - Control What-If'!D18 | E11: ='OT CALC - Control What-If'!E18 | F11: =IF($B$4="Best Estimate",'OT CALC - Control What-If'!H18,'OT CALC - Control What-If'!L18) | G11: =IF($B$4="Best Estimate",'OT CALC - Control What-If'!I18,'OT CALC - Control What-If'!M18)
A12: ='OT CALC - Control What-If'!A19 | B12: ='OT CALC - Control What-If'!B19 | C12: ='OT CALC - Control What-If'!C19 | D12: ='OT CALC - Control What-If'!D19 | E12: ='OT CALC - Control What-If'!E19 | F12: =IF($B$4="Best Estimate",'OT CALC - Control What-If'!H19,'OT CALC - Control What-If'!L19) | G12: =IF($B$4="Best Estimate",'OT CALC - Control What-If'!I19,'OT CALC - Control What-If'!M19)
A13: ='OT CALC - Control What-If'!A20 | B13: ='OT CALC - Control What-If'!B20 | C13: ='OT CALC - Control What-If'!C20 | D13: ='OT CALC - Control What-If'!D20 | E13: ='OT CALC - Control What-If'!E20 | F13: =IF($B$4="Best Estimate",'OT CALC - Control What-If'!H20,'OT CALC - Control What-If'!L20) | G13: =IF($B$4="Best Estimate",'OT CALC - Control What-If'!I20,'OT CALC - Control What-If'!M20)
A14: ='OT CALC - Control What-If'!A21 | B14: ='OT CALC - Control What-If'!B21 | C14: ='OT CALC - Control What-If'!C21 | D14: ='OT CALC - Control What-If'!D21 | E14: ='OT CALC - Control What-If'!E21 | F14: =IF($B$4="Best Estimate",'OT CALC - Control What-If'!H21,'OT CALC - Control What-If'!L21) | G14: =IF($B$4="Best Estimate",'OT CALC - Control What-If'!I21,'OT CALC - Control What-If'!M21)
A15: ='OT CALC - Control What-If'!A22 | B15: ='OT CALC - Control What-If'!B22 | C15: ='OT CALC - Control What-If'!C22 | D15: ='OT CALC - Control What-If'!D22 | E15: ='OT CALC - Control What-If'!E22 | F15: =IF($B$4="Best Estimate",'OT CALC - Control What-If'!H22,'OT CALC - Control What-If'!L22) | G15: =IF($B$4="Best Estimate",'OT CALC - Control What-If'!I22,'OT CALC - Control What-If'!M22)
A16: ='OT CALC - Control What-If'!A23 | B16: ='OT CALC - Control What-If'!B23 | C16: ='OT CALC - Control What-If'!C23 | D16: ='OT CALC - Control What-If'!D23 | E16: ='OT CALC - Control What-If'!E23 | F16: =IF($B$4="Best Estimate",'OT CALC - Control What-If'!H23,'OT CALC - Control What-If'!L23) | G16: =IF($B$4="Best Estimate",'OT CALC - Control What-If'!I23,'OT CALC - Control What-If'!M23)
A17: ='OT CALC - Control What-If'!A24 | B17: ='OT CALC - Control What-If'!B24 | C17: ='OT CALC - Control What-If'!C24 | D17: ='OT CALC - Control What-If'!D24 | E17: ='OT CALC - Control What-If'!E24 | F17: =IF($B$4="Best Estimate",'OT CALC - Control What-If'!H24,'OT CALC - Control What-If'!L24) | G17: =IF($B$4="Best Estimate",'OT CALC - Control What-If'!I24,'OT CALC - Control What-If'!M24)
A18: ='OT CALC - Control What-If'!A25 | B18: ='OT CALC - Control What-If'!B25 | C18: ='OT CALC - Control What-If'!C25 | D18: ='OT CALC - Control What-If'!D25 | E18: ='OT CALC - Control What-If'!E25 | F18: =IF($B$4="Best Estimate",'OT CALC - Control What-If'!H25,'OT CALC - Control What-If'!L25) | G18: =IF($B$4="Best Estimate",'OT CALC - Control What-If'!I25,'OT CALC - Control What-If'!M25)
A19: ='OT CALC - Control What-If'!A26 | B19: ='OT CALC - Control What-If'!B26 | C19: ='OT CALC - Control What-If'!C26 | D19: ='OT CALC - Control What-If'!D26 | E19: ='OT CALC - Control What-If'!E26 | F19: =IF($B$4="Best Estimate",'OT CALC - Control What-If'!H26,'OT CALC - Control What-If'!L26) | G19: =IF($B$4="Best Estimate",'OT CALC - Control What-If'!I26,'OT CALC - Control What-If'!M26)
A20: ='OT CALC - Control What-If'!A27 | B20: ='OT CALC - Control What-If'!B27 | C20: ='OT CALC - Control What-If'!C27 | D20: ='OT CALC - Control What-If'!D27 | E20: ='OT CALC - Control What-If'!E27 | F20: =IF($B$4="Best Estimate",'OT CALC - Control What-If'!H27,'OT CALC - Control What-If'!L27) | G20: =IF($B$4="Best Estimate",'OT CALC - Control What-If'!I27,'OT CALC - Control What-If'!M27)
... A23: ='OT CALC - Control What-If'!A30 | B23: ='OT CALC - Control What-If'!B30 | C23: ='OT CALC - Control What-If'!C30 | D23: ='OT CALC - Control What-If'!D30 | E23: ='OT CALC - Control What-If'!E30 | F23: =IF($B$4="Best Estimate",'OT CALC - Control What-If'!H30,'OT CALC - Control What-If'!L30) | G23: =IF($B$4="Best Estimate",'OT CALC - Control What-If'!I30,'OT CALC - Control What-If'!M30)

Sheet 00 Risk Transfer
A1: IT / OT CYBER RISK QUANTIFICATION | RISK TRANSFER
A2: Indicative financing diagnostics using modelled annual tail risk. This is not a policy-pricing engine and does not simulate coverage terms or recoveries.
A4: Basis | B4: =IF('00 COMMON - Run Setup'!C6="IT",'IT 08 - Reporting Settings'!B16,'00 COMMON - Run Setup'!C9) | C4: Illustrative retention | D4: =IF('00 COMMON - Run Setup'!C6="IT",'IT 08 - Reporting Settings'!B18,0) | E4: Selected tail basis | F4: =IF('00 COMMON - Run Setup'!C6="IT",'IT 08 - Reporting Settings'!B17,"TVaR 99%")
A8: TAIL RISK DIAGNOSTIC
A9: Metric | B9: Value | C9: Interpretation
A10: =F4 | B10: =IF(F4="TVaR 95%",IF($B$4="Best Estimate",'00 COMMON - Output Bridge'!B17,'00 COMMON - Output Bridge'!C17),IF($B$4="Best Estimate",'00 COMMON - Output Bridge'!B19,'00 COMMON - Output Bridge'!C19)) | C10: Mean of the worst 1% of annual aggregate-loss outcomes.
A11: Tail above illustrative retention | B11: =MAX(B10-$D$4,0) | C11: TVaR99 minus retention, floored at zero. Indicative only.
A12: P(any successful event) | B12: =IF($B$4="Best Estimate",'00 COMMON - Output Bridge'!B20,'00 COMMON - Output Bridge'!C20) | C12: Positive-loss year share from the selected model view.
A15: RETURN-PERIOD LOSS DIAGNOSTIC
A16: Return period | B16: Exceedance probability | C16: AEP loss | D16: Loss above retention
A17: 2 | B17: ='00 COMMON - Output Bridge'!A43 | C17: =IF($B$4="Best Estimate",'00 COMMON - Output Bridge'!B43,'00 COMMON - Output Bridge'!D43) | D17: =MAX(C17-$D$4,0)
A18: 5 | B18: ='00 COMMON - Output Bridge'!A44 | C18: =IF($B$4="Best Estimate",'00 COMMON - Output Bridge'!B44,'00 COMMON - Output Bridge'!D44) | D18: =MAX(C18-$D$4,0)
A19: 10 | B19: ='00 COMMON - Output Bridge'!A45 | C19: =IF($B$4="Best Estimate",'00 COMMON - Output Bridge'!B45,'00 COMMON - Output Bridge'!D45) | D19: =MAX(C19-$D$4,0)
A20: 20 | B20: ='00 COMMON - Output Bridge'!A46 | C20: =IF($B$4="Best Estimate",'00 COMMON - Output Bridge'!B46,'00 COMMON - Output Bridge'!D46) | D20: =MAX(C20-$D$4,0)
A21: 25 | B21: ='00 COMMON - Output Bridge'!A47 | C21: =IF($B$4="Best Estimate",'00 COMMON - Output Bridge'!B47,'00 COMMON - Output Bridge'!D47) | D21: =MAX(C21-$D$4,0)
A22: 50 | B22: ='00 COMMON - Output Bridge'!A48 | C22: =IF($B$4="Best Estimate",'00 COMMON - Output Bridge'!B48,'00 COMMON - Output Bridge'!D48) | D22: =MAX(C22-$D$4,0)
A23: 100 | B23: ='00 COMMON - Output Bridge'!A49 | C23: =IF($B$4="Best Estimate",'00 COMMON - Output Bridge'!B49,'00 COMMON - Output Bridge'!D49) | D23: =MAX(C23-$D$4,0)
A24: 200 | B24: ='00 COMMON - Output Bridge'!A50 | C24: =IF($B$4="Best Estimate",'00 COMMON - Output Bridge'!B50,'00 COMMON - Output Bridge'!D50) | D24: =MAX(C24-$D$4,0)
A25: 250 | B25: ='00 COMMON - Output Bridge'!A51 | C25: =IF($B$4="Best Estimate",'00 COMMON - Output Bridge'!B51,'00 COMMON - Output Bridge'!D51) | D25: =MAX(C25-$D$4,0)
A26: 500 | B26: ='00 COMMON - Output Bridge'!A52 | C26: =IF($B$4="Best Estimate",'00 COMMON - Output Bridge'!B52,'00 COMMON - Output Bridge'!D52) | D26: =MAX(C26-$D$4,0)

Sheet 2 User-input navigation
A1: 2 User-input navigation
A2: Editable assessment inputs. Complete only the selected IT or OT domain; outside-in evidence remains optional.
A3: =IF('00 COMMON - Run Setup'!C6="IT","Complete the IT input section only",IF('00 COMMON - Run Setup'!C6="OT","Complete the OT input section only","Set Model domain first"))
A4: Common every run: 00 COMMON - Run Setup; 00 COMMON - Outside-In (optional).
A5: IT only: IT 03, optional IT 04, IT 05, IT 06 overrides, IT 07 adjustments, IT 08 reporting.
A6: OT only: OT 03, OT 04, OT 05, OT 06 adjustments.
A7: Governed packs and core methodology are Advanced / Read Only / Not required to complete an assessment.
A8: 04 Control Assessment | B8: Assessment input / configuration | C8: =HYPERLINK("#'OT 04 - Control Assessment'!A1","Open")
A9: 05 Impact and BIA | B9: Assessment input / configuration | C9: =HYPERLINK("#'OT 05 - Impact & BIA'!A1","Open")
A10: IT 03 Organisation Inputs | B10: Assessment input / configuration | C10: =HYPERLINK("#'IT 03 - Organisation Inputs'!A1","Open")
A11: IT 05 Control Assessment | B11: Assessment input / configuration | C11: =HYPERLINK("#'IT 05 - Control Assessment'!A1","Open")
A12: IT 06 Impact and BIA | B12: Assessment input / configuration | C12: =HYPERLINK("#'IT 06 - Impact & BIA Overrides'!A1","Open")

Sheet 00 COMMON - Run Setup
A1: GUIDED IT / OT CYBER RISK QUANTIFICATION — RUN SETUP
A2: Single assessment front end. Sector selection routes to the governed IT or OT methodology; outside-in evidence is optional and must never be treated as a standalone risk score.
A4: ASSESSMENT & MODEL ROUTING
A5: Input | B5: Purpose | C5: Selection | Z5: IT | AA5: Financial Services | AB5: Power Generation
A6: Model domain | B6: Explicit user selection. Filters the Sector list. | C6: OT | Z6: OT | AA6: Financial_Services | AB6: Energy Assets
A7: Sector | B7: Filtered by Model domain. Resolves the external sector pack. | C7: Power Generation | AB7: Manufacturing
A8: Asset type / scope | B8: Filtered by Sector: Organisation for IT; facility archetype for OT. | C8: CCGT | D8: =IF(C6="IT",IF(C8="Organisation","","IT requires Asset type = Organisation"),"") | Z8: Organisation
A9: Basis | B9: Best Estimate or Prudent dashboard view. | C9: Prudent
A10: Apply outside-in scan? | B10: Optional evidence layer. No scan = baseline model remains fully valid. | C10: No
A11: Outside-in file | B11: Expected relative path for approved normalized scan results. | C11: ="evidence/outside_in/"&IF(C6="OT",'OT 03 - Facility Inputs'!C16,'IT 03 - Organisation Inputs'!C16)&"_outside_in.csv"
A12: Resolved engine | B12: Common runner dispatches to the governed domain engine. | C12: =IF(C6="IT","it_crq v1.1.1","ot_crq v1.7.1")
A13: Unit of analysis | B13: Organisation for IT; one facility for OT. | C13: =IF(C6="IT","Organisation","Facility")
A14: Resolved pack | B14: Engine-resolved pack identifier. | C14: =IF(C6="OT",'OT 03 - Facility Inputs'!C32,'IT 03 - Organisation Inputs'!C34)
A17: DOMAIN ROUTING CONTRACT
A18: Sector | B18: Domain | C18: Unit | D18: Underlying methodology | E18: Engine | F18: Template / pack | G18: Outside-in allowed? | H18: Routing note
A19: Financial Services | B19: IT | C19: Organisation | D19: IT-CRQ v1.1.1 | E19: it_crq | F19: Guided_IT_CRQ_Model_v1_1_1_Dashboard.xlsx / FS-v1.1.1 | G19: Yes | H19: Enterprise ATT&CK; 4 actors; IT scenario/route model.
A20: Power Generation | B20: OT | C20: Facility | D20: OT-CRQ v1.7 + PG pack | E20: ot_crq | F20: PG-v1.6 | G20: Yes | H20: ATT&CK for ICS; 3 actors; five-stage OT composite path.
A21: Energy Assets | B21: OT | C21: Facility | D21: OT-CRQ v1.7 + EA pack | E21: ot_crq | F21: EA-v1.0 | G21: Yes | H21: Same OT method; Energy calibration pack.
A22: Manufacturing | B22: OT | C22: Facility | D22: OT-CRQ v1.7 + MF pack | E22: ot_crq | F22: MF-v1.0 | G22: Yes | H22: Same OT method; Manufacturing calibration pack.
A25: RUN WORKFLOW
A26: Step | B26: Operator action | C26: Engine behaviour | D26: Audit result
A27: 1 | B27: Select sector and scope above. | C27: Router resolves IT vs OT and governed pack. | D27: Domain/pack recorded in result workbook.
A28: 2 | B28: Complete the relevant IT or OT assessment inputs. | C28: Only the selected domain methodology is executed. | D28: Unselected domain is not blended into the result.
A29: 3 | B29: If a scan exists, set Apply outside-in = Yes and place normalized file at the shown path. | C29: Engine validates schema, attribution and approved mapping rules. | D29: 00 Outside-In stores the normalized evidence snapshot.
A30: 4 | B30: Run the common launcher. | C30: Launcher dispatches to it_crq or ot_crq. | D30: Baseline assumptions and scan-conditioned amendments are preserved separately.
A31: 5 | B31: Review dashboards and validation. | C31: Dashboard reads the common output bridge. | D31: 00 OI Adjustment Rationale explains every quantitative amendment.
A32: 6 | B32: Archive workbook + scan + engine version. | C32: No scan is a valid run state. | D32: Reproducible assessment package.
A35: EXECUTION CONTRACT — one combined workbook is the operator-facing assessment file. The common Python launcher routes by sector. IT runs use the supplied v1.1.1 code against the IT staging sheets; OT runs remain on the governed OT methodology. The unselected domain is not blended into the calculation.
A42: FINANCIAL SERVICES — IT INPUT SYNC CONTRACT
A43: Combined workbook sheet | B43: IT template destination | C43: Values to sync | D43: Direction | E43: When | F43: Purpose
A44: IT 03 Organisation Inputs | B44: 03 Organisation Inputs | C44: User input cells / keys | D44: Master → IT template | E44: Before IT run | F44: Organisation scale and model settings
A45: IT 05 Control Assessment | B45: 05 Control Assessment | C45: Actual maturity / coverage / evidence | D45: Master → IT template | E45: Before IT run | F45: Control barriers
A46: IT 06 Impact and BIA | B46: 06 Impact and BIA | C46: Organisation overrides | D46: Master → IT template | E46: Before IT run | F46: Financial consequence
A47: IT 07 Frequency Assumptions | B47: 07 Frequency Assumptions | C47: User input frequency multipliers | D47: Master → IT template | E47: Before IT run | F47: Campaign frequency
A48: IT 08 Tail Risk Settings | B48: 08 Tail Risk Settings | C48: Reporting / retention inputs | D48: Master → IT template | E48: Before IT run | F48: Reporting configuration
A49: 00 Output Bridge | B49: IT result workbook | C49: Normalized metrics / curves / decompositions | D49: IT result → Master | E49: After IT run | F49: Common dashboards
A50: Required workflow
A51: =IF(C6="IT","Complete the IT input section only",IF(C6="OT","Complete the OT input section only","Select IT or OT"))
A52: Parameter | B52: Description | C52: Value
A53: Selected domain | B53: =C6
A54: Selected sector | B54: =C7
A55: Unit of analysis | B55: =C13
A56: MAX_ACCEPTABLE_TVAR_99 | B56: Max acceptable TVaR 99 ($)
A57: MAX_ACCEPTABLE_DOWNTIME_DAYS | B57: Max acceptable downtime P95 (days)

Sheet 00 COMMON - Outside-In
A1: OPTIONAL OUTSIDE-IN EVIDENCE
A2: Engine-populated normalized scan evidence. The model must run with this sheet empty when no scan is available. Positive evidence may condition existing likelihood inputs; absence of a finding does not automatically earn risk credit.
A4: SCAN STATUS & GOVERNANCE
A5: Field | B5: Value | D5: INCLUSION RULES • Finding must map to an in-scope organisation/facility asset or route. • Direct exposure can change exposure/frequency or route feasibility. • KEV/high-EPSS/CVE evidence can inform the relevant access/stage barrier; EPSS is not P(success). • Do not change financial severity, downtime, physical damage or safety consequence solely from outside-in data. • Uncertain ownership or facility attribution is retained as evidence but receives no automatic quantitative adjustment. • A clean scan does not, by itself, reduce baseline risk.
A6: Apply outside-in? | B6: ='00 COMMON - Run Setup'!C10
A7: Expected file | B7: ='00 COMMON - Run Setup'!C11
A8: Scan supplied? | B8: No
A9: Schema status | B9: NOT LOADED
A10: Finding count | B10: 0
A11: Quantitative adjustments | B11: 0
A12: Scan / observation date
A14: NORMALIZED FINDING SNAPSHOT — ENGINE OUTPUT
A15: Finding ID | B15: Observed asset / endpoint | C15: Finding type | D15: Technology / service | E15: CVE | F15: KEV? | G15: EPSS | H15: Internet exposed? | I15: Organisation attribution | J15: Facility attribution | K15: Attribution confidence | L15: IT/OT relevance | M15: ATT&CK / route mapping | N15: Model stage | O15: Proposed treatment | P15: Evidence strength | Q15: Source / scanner | R15: Observation date

Sheet 3 Assumption Ownership
A1: 3 Assumption Ownership
A2: Governed calibration, scenario/TTP mappings, sector packs and frequency/tail assumptions.
A3: Group | B3: Domain | C3: Sector | D3: Assumption layer | E3: Sheet or file | F3: Purpose | G3: Owner | H3: Editable during assessment? | I3: Authoritative location | J3: Required evidence | K3: Calibration status
A4: 1 Common setup | B4: Common | C4: All | D4: Assessment setup | E4: 00 COMMON - Run Setup | F4: Domain, sector, pack, basis, outside-in | G4: Assessment Team | H4: Yes | I4: 00 COMMON - Run Setup | J4: Assessment ID / sector selection | K4: n/a
A5: 1 Common setup | B5: Common | C5: All | D5: Optional evidence | E5: 00 COMMON - Outside-In | F5: Approved outside-in findings | G5: Assessment Team | H5: Optional | I5: 00 COMMON - Outside-In | J5: Approved CSV | K5: n/a
A6: 2 IT assessment | B6: IT | C6: Financial Services | D6: Assessment input | E6: IT 03 - Organisation Inputs | F6: Organisation scale and run inputs | G6: Assessment Team | H6: Yes | I6: IT 03 - Organisation Inputs | J6: Client evidence | K6: n/a
A7: 2 IT assessment | B7: IT | C7: Financial Services | D7: Optional override | E7: IT 04 - Exposure Adjustments | F7: Exposure-model recommendations | G7: Assessment Team | H7: Optional | I7: IT 04 - Exposure Adjustments | J7: Exposure model | K7: n/a
A8: 2 IT assessment | B8: IT | C8: Financial Services | D8: Assessment input | E8: IT 05 - Control Assessment | F8: Actual IT control maturity | G8: Assessment Team | H8: Yes | I8: IT 05 - Control Assessment | J8: Control evidence | K8: n/a
A9: 2 IT assessment | B9: IT | C9: Financial Services | D9: Optional override | E9: IT 06 - Impact & BIA Overrides | F9: Org-specific BIA overrides | G9: Assessment Team | H9: Optional | I9: IT 06; blank keeps pack | J9: Org BIA | K9: n/a
A10: 2 IT assessment | B10: IT | C10: Financial Services | D10: Optional override | E10: IT 07 - Assessment Adjustments | F10: Org frequency/threat overlays | G10: Assessment Team | H10: Optional | I10: IT 07; pack owns reference λ | J10: Threat intel | K10: n/a
A11: 2 IT assessment | B11: IT | C11: Financial Services | D11: Assessment input | E11: IT 08 - Reporting Settings | F11: Basis, retention, tail metric | G11: Assessment Team | H11: Yes | I11: IT 08 - Reporting Settings | J11: Reporting policy | K11: n/a
A12: 3 Core IT | B12: IT | C12: All IT | D12: Core methodology | E12: IT CORE / IT CALC sheets | F12: IT calculation method | G12: Core IT Model Owner | H12: No | I12: src/it_crq + IT CORE sheets | J12: n/a | K12: Governed
A13: 4 FS pack | B13: IT | C13: Financial Services | D13: Sector pack | E13: sector_packs/IT/IT_CRQ_Sector_Pack_Financial_Services_v1_1_1.xlsx | F13: FS reference calibration | G13: Sector Pack Owner | H13: No | I13: External FS pack | J13: Pack evidence register | K13: Working priors
A14: 5 OT assessment | B14: OT | C14: Selected OT sector | D14: Assessment input | E14: OT 03 - Facility Inputs | F14: Facility identity and architecture | G14: Assessment Team | H14: Yes | I14: OT 03 - Facility Inputs | J14: Facility evidence | K14: n/a
... A22: 10 Outputs | B22: Common | C22: All | D22: Calculated | E22: 00 dashboards / Engine Results | F22: AAL, LEC, validation | G22: Python engine | H22: No | I22: 00 COMMON - Engine Results | J22: n/a | K22: Run-specific

Sheet FILL IT assessment only
A1: FILL IT assessment only
A3: =IF('00 COMMON - Run Setup'!C6="IT","FILL the cyan IT tabs. Ignore FILL OT.","Not used for this run.")

Sheet IT 03 - Organisation Inputs
A1: 03 — Organisation and Run Inputs
A2: Select the sector, organisation scale and whether upstream IT Exposure Adjustment Model recommendations are applied.
A3: =IF('00 COMMON - Run Setup'!C6="IT","FILL this sheet — IT assessment.","Not used for this run. Complete the OT assessment section only.")
A4: Enter organisation identity and scale here. Python uses these Value cells for the IT calculation. Sector is taken from Run Setup. Currency and Use exposure model are dropdowns.
A15: Input | B15: Question | C15: Value | D15: Type | E15: How used | F15: Basis / evidence
A16: ASSESSMENT_ID | B16: Assessment reference | C16: IT-CRQ-001 | D16: Text | E16: Reporting and traceability | F16: Client
A17: ORGANISATION | B17: Organisation | C17: Example Financial Institution | D17: Text | E17: Organisation-level unit of analysis | F17: Client
A18: COUNTRY_REGION | B18: Country / region | C18: UAE / GCC | D18: Text | E18: Reporting context; explicit multiplier is on 07 | F18: Client
A19: SECTOR | B19: Sector | C19: ='00 COMMON - Run Setup'!C7 | D19: Dropdown | E19: Resolves the separate sector-pack workbook | F19: 09 Sector Pack Registry
A20: CURRENCY | B20: Reporting currency | C20: USD | D20: Dropdown | E20: Financial result labels | F20: Client
A21: ANNUAL_REVENUE_AT_RISK | B21: Annual revenue at risk | C21: 1000000000 | D21: Currency/year | E21: Business interruption and revenue-scaled drivers | F21: Client Finance
A22: ANNUAL_PAYMENT_VALUE | B22: Annual payment / transaction value | C22: 5000000000 | D22: Currency/year | E22: Funds-at-risk model for integrity and fraud scenarios | F22: Client Finance
A23: BI_LOSS_FACTOR | B23: Business-interruption loss factor | C23: 1 | D23: Percentage | E23: Share of revenue at risk treated as avoidable loss | F23: Client Finance
A24: EMPLOYEES | B24: Employees | C24: 10000 | D24: Count | E24: Organisation context | F24: Client
A25: CUSTOMERS | B25: Customers / accounts | C25: 2000000 | D25: Count | E25: Potential notification and monitoring scale | F25: Client
A26: SENSITIVE_RECORDS | B26: Sensitive records | C26: 5000000 | D26: Count | E26: Data-compromise scaling | F26: Client
A27: CRITICAL_ENDPOINTS | B27: Critical endpoints | C27: 5000 | D27: Count | E27: Recovery-cost scaling | F27: Client
A28: CRITICAL_SERVERS | B28: Critical servers / workloads | C28: 500 | D28: Count | E28: Recovery-cost scaling | F28: Client
A29: USE_EXPOSURE_MODEL | B29: Use IT Exposure Adjustment Model inputs? | C29: No | D29: Yes / No dropdown | E29: Controls whether sheet 04 recommendations are applied | F29: User decision
A30: SIMULATION_YEARS | B30: Monte Carlo organisation-years | C30: 500000 | D30: Count | E30: Annual-loss simulation size | F30: Model setting
A31: RANDOM_SEED | B31: Random seed | C31: 20260821 | D31: Integer | E31: Reproducible simulation | F31: Model setting
A33: RESOLVED SECTOR PACK
A34: PACK_ID | B34: Resolved pack ID | C34: FS-v1.1.1 | D34: Engine output | E34: Traceability | F34: Separate sector-pack workbook
A35: PACK_VERSION | B35: Resolved pack version | C35: 1.1.1 | D35: Engine output | E35: Compatibility | F35: Separate sector-pack workbook
A36: PACK_STATUS | B36: Pack calibration status | C36: Development — working priors; calibration required | D36: Engine output | E36: Governance | F36: Separate sector-pack workbook
A37: MODEL_STATUS | B37: Last validation status | C37: PASS | D37: Engine output | E37: Model governance | F37: 22 Validation Tests
A40: COMBINED-MODEL NOTE — These IT sheets are the user-input staging area for Financial Services. The common runner must copy the staged values into the governed IT v1.1.1 template, execute it_crq, then write the normalized results back to 00 Output Bridge. The IT calculation methodology itself is not replaced by OT logic.

Sheet IT 04 - Exposure Adjustments
A1: 04 — IT Exposure Adjustment Inputs
A2: Optional upstream recommendations. The CRQ workbook does not ingest raw asset or vulnerability records.
A3: =IF('00 COMMON - Run Setup'!C6="IT","FILL this sheet — IT assessment.","Not used for this run. Complete the OT assessment section only.")
A4: Optional. Leave this sheet at Yes / Unknown / 1.0 unless you set USE_EXPOSURE_MODEL = Yes on IT 03 and have a governed exposure-model recommendation. Organisation applicable? can still mark a route as out of scope.
A15: Route ID | B15: Attack route | C15: Organisation applicable? | D15: Evidence-model feasible? | E15: Opportunity factor | F15: S1 factor | G15: S2 factor | H15: S3 factor | I15: S4 factor | J15: S5 factor | K15: Impact factor | L15: Confidence | M15: Recommendation ID | N15: Evidence date | O15: Rationale | P15: Used opportunity | Q15: Used S1 | R15: Used S2 | S15: Used S3 | T15: Used S4 | U15: Used S5 | V15: Used impact
A16: R_ID | B16: Identity and credential compromise | C16: Yes | D16: Unknown | E16: 1 | F16: 1 | G16: 1 | H16: 1 | I16: 1 | J16: 1 | K16: 1 | L16: Not assessed | O16: No exposure-model recommendation loaded. | P16: 1 | Q16: 1 | R16: 1 | S16: 1 | T16: 1 | U16: 1 | V16: 1
A17: R_USER | B17: User endpoint and social engineering | C17: Yes | D17: Unknown | E17: 1 | F17: 1 | G17: 1 | H17: 1 | I17: 1 | J17: 1 | K17: 1 | L17: Not assessed | O17: No exposure-model recommendation loaded. | P17: 1 | Q17: 1 | R17: 1 | S17: 1 | T17: 1 | U17: 1 | V17: 1
A18: R_EXP | B18: Public-facing application exploitation | C18: Yes | D18: Unknown | E18: 1 | F18: 1 | G18: 1 | H18: 1 | I18: 1 | J18: 1 | K18: 1 | L18: Not assessed | O18: No exposure-model recommendation loaded. | P18: 1 | Q18: 1 | R18: 1 | S18: 1 | T18: 1 | U18: 1 | V18: 1
A19: R_TP | B19: Third-party or software supply chain | C19: Yes | D19: Unknown | E19: 1 | F19: 1 | G19: 1 | H19: 1 | I19: 1 | J19: 1 | K19: 1 | L19: Not assessed | O19: No exposure-model recommendation loaded. | P19: 1 | Q19: 1 | R19: 1 | S19: 1 | T19: 1 | U19: 1 | V19: 1
A20: R_DDOS | B20: Direct availability or DDoS | C20: Yes | D20: Unknown | E20: 1 | F20: 1 | G20: 1 | H20: 1 | I20: 1 | J20: 1 | K20: 1 | L20: Not assessed | O20: No exposure-model recommendation loaded. | P20: 1 | Q20: 1 | R20: 1 | S20: 1 | T20: 1 | U20: 1 | V20: 1
A21: R_INS | B21: Insider or trusted access | C21: Yes | D21: Unknown | E21: 1 | F21: 1 | G21: 1 | H21: 1 | I21: 1 | J21: 1 | K21: 1 | L21: Not assessed | O21: No exposure-model recommendation loaded. | P21: 1 | Q21: 1 | R21: 1 | S21: 1 | T21: 1 | U21: 1 | V21: 1

Sheet IT 05 - Control Assessment
A1: 05 — Control Assessment
A2: NIST CSF 2.0-aligned control families with Enterprise ATT&CK mitigation mappings and reference-relative efficacy.
A3: =IF('00 COMMON - Run Setup'!C6="IT","FILL this sheet — IT assessment.","Not used for this run. Complete the OT assessment section only.")
A15: Control ID | B15: Control family | C15: NIST CSF 2.0 | D15: MITRE mitigations | E15: Actual maturity | F15: Actual coverage | G15: Reference maturity | H15: Reference coverage | I15: Evidence / rationale | J15: Resolved status
A16: C01 | B16: Asset and vulnerability management | C16: ID.AM; ID.RA | D16: M1016; M1051 | E16: Developing | F16: 0.75 | G16: Developing | H16: 0.75 | I16: User assessment required | J16: Working prior
A17: C02 | B17: Identity, authentication and MFA | C17: PR.AA | D17: M1032; M1036 | E17: Developing | F17: 0.75 | G17: Developing | H17: 0.75 | I17: User assessment required | J17: Working prior
A18: C03 | B18: Privileged access management | C18: PR.AA | D18: M1026; M1018 | E18: Developing | F18: 0.75 | G18: Developing | H18: 0.75 | I18: User assessment required | J18: Working prior
A19: C04 | B19: Email, web security and awareness | C19: PR.AT; PR.DS | D19: M1017; M1021 | E19: Developing | F19: 0.75 | G19: Developing | H19: 0.75 | I19: User assessment required | J19: Working prior
A20: C05 | B20: Endpoint protection and execution control | C20: PR.PS; DE.CM | D20: M1040; M1049 | E20: Developing | F20: 0.75 | G20: Developing | H20: 0.75 | I20: User assessment required | J20: Working prior
A21: C06 | B21: Secure configuration and patching | C21: PR.PS | D21: M1042; M1051 | E21: Developing | F21: 0.75 | G21: Developing | H21: 0.75 | I21: User assessment required | J21: Working prior
A22: C07 | B22: Network security and segmentation | C22: PR.IR; PR.PS | D22: M1030; M1037 | E22: Developing | F22: 0.75 | G22: Developing | H22: 0.75 | I22: User assessment required | J22: Working prior
A23: C08 | B23: Cloud and SaaS security | C23: PR.AA; PR.PS; DE.CM | D23: M1047; M1032 | E23: Developing | F23: 0.75 | G23: Developing | H23: 0.75 | I23: User assessment required | J23: Working prior
A24: C09 | B24: Application and API security | C24: ID.RA; PR.PS | D24: M1050; M1051 | E24: Developing | F24: 0.75 | G24: Developing | H24: 0.75 | I24: User assessment required | J24: Working prior
A25: C10 | B25: Logging, detection and threat response | C25: DE.CM; DE.AE; RS.AN | D25: M1047 | E25: Developing | F25: 0.75 | G25: Developing | H25: 0.75 | I25: User assessment required | J25: Working prior
A26: C11 | B26: Data protection and DLP | C26: PR.DS | D26: M1041; M1057 | E26: Developing | F26: 0.75 | G26: Developing | H26: 0.75 | I26: User assessment required | J26: Working prior
A27: C12 | B27: Third-party and supply-chain security | C27: GV.SC; ID.RA | D27: M1045; M1051 | E27: Developing | F27: 0.75 | G27: Developing | H27: 0.75 | I27: User assessment required | J27: Working prior
... A30: C15 | B30: Payment and fraud controls | C30: PR.AA; DE.AE; RS.MI | D30: M1018; M1047 | E30: Developing | F30: 0.75 | G30: Developing | H30: 0.75 | I30: User assessment required | J30: Working prior

Sheet IT 06 - Impact & BIA Overrides
A1: 06 — Impact and Business Impact Analysis
A2: Pack-driven P50/P99 assumptions. Python prepares this long table and preserves overrides.
A3: =IF('00 COMMON - Run Setup'!C6="IT","FILL this sheet — IT assessment.","Not used for this run. Complete the OT assessment section only.")
A4: Organisation-scale figures below are live links to IT 03 — do not type them here. On this sheet, fill Override P50/P99 only where you have organisation-specific BIA evidence. Leave overrides blank to keep the Financial Services pack baseline.
A5: ORGANISATION-SCALE INPUTS
A6: Metric | B6: Value | C6: Source
A7: Annual revenue at risk | B7: ='IT 03 - Organisation Inputs'!C21 | C7: IT 03 - Organisation Inputs (live)
A8: Annual payment value | B8: ='IT 03 - Organisation Inputs'!C22 | C8: IT 03 - Organisation Inputs (live)
A9: BI loss factor | B9: ='IT 03 - Organisation Inputs'!C23 | C9: IT 03 - Organisation Inputs (live)
A10: Customers | B10: ='IT 03 - Organisation Inputs'!C25 | C10: IT 03 - Organisation Inputs (live)
A11: Sensitive records | B11: ='IT 03 - Organisation Inputs'!C26 | C11: IT 03 - Organisation Inputs (live)
A12: Critical endpoints | B12: ='IT 03 - Organisation Inputs'!C27 | C12: IT 03 - Organisation Inputs (live)
A13: Critical servers | B13: ='IT 03 - Organisation Inputs'!C28 | C13: IT 03 - Organisation Inputs (live)
A15: PACK ASSUMPTIONS AND ORGANISATION OVERRIDES
A16: Assumption type | B16: Scenario ID | C16: Scenario | D16: Parameter ID | E16: Description | F16: Unit | G16: Pack P50 | H16: Pack P99 | I16: Override P50 | J16: Override P99 | K16: Used P50 | L16: Used P99 | M16: Evidence grade | N16: Source ID
A17: RATE | D17: NOTIFICATION_PER_RECORD | E17: Notification cost per affected record | F17: USD/record | G17: 0.5 | H17: 1 | K17: 0.5 | L17: 1 | M17: D | N17: SRC-07
A18: RATE | D18: CREDIT_MONITORING_PER_RECORD | E18: Credit monitoring per participating record | F18: USD/record | G18: 8 | H18: 20 | K18: 8 | L18: 20 | M18: D | N18: SRC-07
A19: RATE | D19: FORENSIC_DAILY | E19: Daily forensic investigation team | F19: USD/day | G19: 2000 | H19: 4000 | K19: 2000 | L19: 4000 | M19: D | N19: SRC-07
A20: RATE | D20: EXTERNAL_CYBER_DAILY | E20: Daily external cyber response team | F20: USD/day | G20: 3000 | H20: 5000 | K20: 3000 | L20: 5000 | M20: D | N20: SRC-07
A21: RATE | D21: RESTORATION_DAILY | E21: Daily data restoration team | F21: USD/day | G21: 2000 | H21: 4000 | K21: 2000 | L21: 4000 | M21: D | N21: SRC-07
A22: RATE | D22: LEGAL_DAILY | E22: Daily external legal team | F22: USD/day | G22: 5000 | H22: 10000 | K22: 5000 | L22: 10000 | M22: D | N22: SRC-07
A23: RATE | D23: ENDPOINT_REPAIR | E23: Endpoint repair/replacement unit cost | F23: USD/endpoint | G23: 200 | H23: 500 | K23: 200 | L23: 500 | M23: D | N23: SRC-07
A24: RATE | D24: SERVER_REPAIR | E24: Server repair/replacement unit cost | F24: USD/server | G24: 5000 | H24: 8000 | K24: 5000 | L24: 8000 | M24: D | N24: SRC-07
A25: PARAM | B25: SC_DISR | C25: Critical business-service disruption | D25: AFFECTED_ENDPOINT_SHARE | E25: AFFECTED_ENDPOINT_SHARE | F25: share | G25: 0.1 | H25: 0.5 | K25: 0.1 | L25: 0.5 | M25: D | N25: SRC-10
A26: PARAM | B26: SC_DISR | C26: Critical business-service disruption | D26: AFFECTED_RECORD_SHARE | E26: AFFECTED_RECORD_SHARE | F26: share | G26: 0 | H26: 0.05 | K26: 0 | L26: 0.05 | M26: D | N26: SRC-10
A27: PARAM | B27: SC_DISR | C27: Critical business-service disruption | D27: AFFECTED_SERVER_SHARE | E27: AFFECTED_SERVER_SHARE | F27: share | G27: 0.1 | H27: 0.6 | K27: 0.1 | L27: 0.6 | M27: D | N27: SRC-10
A28: PARAM | B28: SC_DISR | C28: Critical business-service disruption | D28: AFFECTED_SERVICE_SHARE | E28: AFFECTED_SERVICE_SHARE | F28: share | G28: 0.3 | H28: 0.85 | K28: 0.3 | L28: 0.85 | M28: D | N28: SRC-10
A29: PARAM | B29: SC_DISR | C29: Critical business-service disruption | D29: CHURN_REVENUE_SHARE | E29: CHURN_REVENUE_SHARE | F29: share | G29: 0.001 | H29: 0.01 | K29: 0.001 | L29: 0.01 | M29: D | N29: SRC-10
A30: PARAM | B30: SC_DISR | C30: Critical business-service disruption | D30: CYBER_DAYS | E30: CYBER_DAYS | F30: days | G30: 10 | H30: 90 | K30: 10 | L30: 90 | M30: D | N30: SRC-10
A31: PARAM | B31: SC_DISR | C31: Critical business-service disruption | D31: DIVERTED_SHARE | E31: DIVERTED_SHARE | F31: share | G31: 0 | H31: 0 | K31: 0 | L31: 0 | M31: D | N31: SRC-10
A32: PARAM | B32: SC_DISR | C32: Critical business-service disruption | D32: DOWNTIME_DAYS | E32: DOWNTIME_DAYS | F32: days | G32: 3 | H32: 30 | K32: 3 | L32: 30 | M32: D | N32: SRC-10
A33: PARAM | B33: SC_DISR | C33: Critical business-service disruption | D33: EXTORTION_DIRECT | E33: EXTORTION_DIRECT | F33: USD | G33: 1000000 | H33: 20000000 | K33: 1000000 | L33: 20000000 | M33: D | N33: SRC-10
A34: PARAM | B34: SC_DISR | C34: Critical business-service disruption | D34: FRAUD_RECOVERY_RATE | E34: FRAUD_RECOVERY_RATE | F34: share | G34: 0 | H34: 0 | K34: 0 | L34: 0 | M34: D | N34: SRC-10
A35: PARAM | B35: SC_DISR | C35: Critical business-service disruption | D35: IR_DAYS | E35: IR_DAYS | F35: days | G35: 10 | H35: 60 | K35: 10 | L35: 60 | M35: D | N35: SRC-10
A36: PARAM | B36: SC_DISR | C36: Critical business-service disruption | D36: LEGAL_DAYS | E36: LEGAL_DAYS | F36: days | G36: 5 | H36: 45 | K36: 5 | L36: 45 | M36: D | N36: SRC-10
... A92: PARAM | B92: SC_FRAUD | C92: Cyber-enabled theft or fraud | D92: RESTORE_DAYS | E92: RESTORE_DAYS | F92: days | G92: 5 | H92: 60 | K92: 5 | L92: 60 | M92: D | N92: SRC-10

Sheet IT 07 - Assessment Adjustments
A1: 07 — Frequency Assumptions
A2: Best-estimate campaign frequency remains separate from conditional attack-path success and prudence.
A3: =IF('00 COMMON - Run Setup'!C6="IT","FILL this sheet — IT assessment.","Not used for this run. Complete the OT assessment section only.")
A4: Organisation-level overlays only. Pack-owned campaign rate, actor weights and route priors are read-only.
A15: Parameter | B15: Value | C15: Unit | D15: How used | E15: Status | F15: Source / rationale
A16: ORGANISATION_EXPOSURE_MULT | B16: 1 | C16: multiplier | D16: Scales reference material campaign rate before actor/scenario/route allocation | E16: User input | F16: Organisation context; avoid duplicating sheet 04 route factors
A17: GEOGRAPHY_THREAT_MULT | B17: 1 | C17: multiplier | D17: Scales campaign rate for geography-specific threat context | E17: User input | F17: Use 1.00 unless evidence supports adjustment
A18: PRUDENCE_FREQUENCY_FACTOR | B18: 1.25 | C18: multiplier | D18: Applied only to prudent frequency view | E18: User input | F18: Separate named prudence margin
A19: NATION_STATE_ACTIVITY | B19: 1 | C19: multiplier | D19: Actor-specific activity adjustment | E19: User input | F19: Client threat intelligence
A20: CYBERCRIMINAL_ACTIVITY | B20: 1 | C20: multiplier | D20: Actor-specific activity adjustment | E20: User input | F20: Client threat intelligence
A21: MALICIOUS_INSIDER_ACTIVITY | B21: 1 | C21: multiplier | D21: Actor-specific activity adjustment | E21: User input | F21: Client threat intelligence
A22: HACKTIVIST_ACTIVITY | B22: 1 | C22: multiplier | D22: Actor-specific activity adjustment | E22: User input | F22: Client threat intelligence
A25: RESOLVED PACK FREQUENCY
A26: REFERENCE_CAMPAIGNS_PER_YEAR | B26: 1 | C26: campaigns/org-year | D26: Loaded from selected sector pack | E26: Engine output | F26: Development working prior
A27: PACK_WEIGHTED_ACTIVITY | B27: 1 | C27: multiplier | D27: Σ(actor weight × actor activity) | E27: Engine output | F27: Calculation
A28: BEST_ESTIMATE_LAMBDA | B28: 1 | C28: campaigns/org-year | D28: Reference × organisation × geography × weighted activity | E28: Engine output | F28: Calculation
A29: PRUDENT_LAMBDA | B29: 1.25 | C29: campaigns/org-year | D29: Best estimate × prudence factor | E29: Engine output | F29: Calculation
A30: ACTIVE_ROUTE_OPPORTUNITY | B30: 1 | C30: multiplier | D30: Resulting route-level exposure effect | E30: Engine output | F30: Calculation

Sheet IT 08 - Reporting Settings
A1: 08 — Tail-Risk and Reporting Settings
A2: User-selected tail metric and insurance retention; both best-estimate and prudent views remain available.
A3: =IF('00 COMMON - Run Setup'!C6="IT","FILL this sheet — IT assessment.","Not used for this run. Complete the OT assessment section only.")
A4: Set reporting basis (Best Estimate vs Prudent), TVaR 95 vs TVaR 99, and illustrative insurance retention here. 00 Risk Transfer, the executive dashboard Basis, and the IT engine all read these three cells.
A15: Parameter | B15: Value | C15: Type | D15: How used | E15: Status | F15: Notes
A16: REPORTING_VIEW | B16: Prudent | C16: Dropdown | D16: Detailed-sheet presentation | E16: User input | F16: Executive summary always shows both views
A17: TVAR_SELECTION | B17: TVaR 99% | C17: Dropdown | D17: Selected tail metric | E17: User input | F17: Does not alter the simulated distribution
A18: INSURANCE_RETENTION | B18: 0 | C18: Currency | D18: Tail loss above retention | E18: User input | F18: Indicative risk-transfer view only
A19: LEC_RETURN_PERIODS | B19: 2,5,10,20,25,50,100,200,250,500 | C19: Text | D19: AEP/OEP curve points | E19: Model setting | F19: Fixed engine-supported list

Sheet FILL OT assessment only
A1: FILL OT assessment only
A3: =IF('00 COMMON - Run Setup'!C6="OT","FILL the purple OT tabs. Ignore FILL IT.","Not used for this run.")

Sheet OT 03 - Facility Inputs
A1: 03 — Facility Inputs
A2: Purpose: Capture the facility-level unit of analysis, selected sector/asset pack, and architecture/access-route characteristics that affect exposure and TTP feasibility.
A3: =IF('00 COMMON - Run Setup'!C6="OT","FILL this sheet — OT assessment.","Not used for this run. Complete the IT assessment section only.")
A4: SHEET TYPE: USER INPUT
A5: Inputs / upstream sources
A6: Client architecture, engineering, operating model and facility information.
A7: Calculation / decision logic
A8: Facility inputs feed three mechanisms: (1) pack resolution on 28, (2) feasibility gates on 12, and (3) facility exposure on 06. Financial severity changes only through explicit BIA inputs on 05.
A9: Key assumptions / defaults
A10: The unit of analysis is one facility. Asset type must belong to the selected sector. TTPs with no explicit sector or facility gate default to applicable/feasible and remain visible for review.
A11: Outputs / downstream use
A12: Used by 06 Frequency Assumptions, 12 Facility Feasibility, 14 TTP Relevance Calc, 28–29 sector-pack sheets and the Python engine.
A13: Workbook convention: yellow cells / blue font are editable inputs or calibration assumptions; engine-output cells are not manually editable.
A15: Input | B15: Question | C15: Value | D15: Type | E15: How the model uses it | F15: Basis / evidence
A16: ASSESSMENT_ID | B16: Assessment reference | C16: PlantA | D16: Text | E16: Reporting / traceability | F16: Client
A17: ORGANISATION | B17: Organisation | C17: Example Energy Co | D17: Text | E17: Reporting | F17: Client
A18: FACILITY | B18: Facility / site | C18: Example Power Station | D18: Text | E18: Unit of analysis | F18: Client
A19: COUNTRY_REGION | B19: Country / region | C19: UAE / GCC | D19: Dropdown | E19: Actor geography multiplier | F19: Client
A20: SECTOR | B20: Sector | C20: =IF('00 COMMON - Run Setup'!C6="OT",'00 COMMON - Run Setup'!C6,"") | D20: Dropdown | E20: Actor sector multiplier + pack selection | F20: Client
A21: PLANT_TYPE | B21: Plant / asset type | C21: =IF('00 COMMON - Run Setup'!C6="OT",'00 COMMON - Run Setup'!C8,"") | D21: Dropdown (filtered by Sector) | E21: Asset-pack context and frequency overlay. List is filtered by Sector. | F21: Client
A22: CRITICAL_PROCESS | B22: Critical process / service | C22: Power generation and dispatch | D22: Text | E22: Scenario narrative / BIA scope | F22: Client
A23: IT_OT_CONNECTIVITY | B23: Enterprise IT connected to OT? | C23: Yes | D23: Dropdown | E23: Exposure multiplier + remote/IT-OT feasibility | F23: Architecture
A24: REMOTE_ACCESS | B24: Vendor / engineer remote access? | C24: Controlled | D24: Dropdown | E24: Exposure multiplier + remote TTP feasibility | F24: Architecture
A25: INTERNET_OT | B25: Critical OT service internet-accessible? | C25: No | D25: Dropdown | E25: Exposure multiplier + internet TTP feasibility | F25: Architecture
A26: TRANSIENT_ASSETS | B26: Transient / contractor devices permitted? | C26: Controlled | D26: Dropdown | E26: Exposure multiplier + removable-media feasibility | F26: Architecture
A27: SUPPLY_CHAIN_ROUTE | B27: Trusted update / firmware route? | C27: Yes | D27: Dropdown | E27: Supply-chain TTP feasibility only; frequency multiplier is neutral. | F27: Architecture
A28: WIRELESS_OT | B28: Wireless connectivity in OT? | C28: No | D28: Dropdown | E28: Wireless TTP feasibility only; frequency multiplier is neutral. | F28: Architecture
A29: SAFETY_SYSTEM | B29: Safety / protection relationship | C29: Segregated | D29: Dropdown | E29: Safety scenario gate | F29: Engineering
A31: RESOLVED SECTOR PACK
A32: SECTOR_PACK_ID | B32: Resolved pack identifier | C32: =IFERROR(VLOOKUP(C20,'OT PACK - Loaded Registry'!$A$16:$H$18,2,FALSE),"UNRESOLVED") | D32: Formula | E32: Traceability / engine pack selection | F32: 28 Sector Pack Registry
A33: SECTOR_PACK_STATUS | B33: Pack calibration status | C33: =IFERROR(VLOOKUP(C20,'OT PACK - Loaded Registry'!$A$16:$H$18,4,FALSE),"UNRESOLVED") | D33: Formula | E33: Governance / production-use label | F33: 28 Sector Pack Registry
A34: ASSET_TYPE_VALID | B34: Asset type belongs to selected sector? | C34: =IF(COUNTIFS('OT PACK - Loaded Registry'!$A$25:$A$39,C20,'OT PACK - Loaded Registry'!$B$25:$B$39,C21)=1,"Yes","No") | D34: Formula | E34: Fail-closed selection check | F34: 28 Sector Pack Registry
A35: SECTOR_FREQUENCY_TREATMENT | B35: Selected pack frequency treatment | C35: =IFERROR(VLOOKUP(C20,'OT PACK - Loaded Registry'!$A$16:$H$18,5,FALSE),"UNRESOLVED") | D35: Formula | E35: Shows how sector pack modifies frequency context | F35: 28 Sector Pack Registry
A36: SECTOR_BIA_TREATMENT | B36: Selected pack BIA treatment | C36: =IFERROR(VLOOKUP(C20,'OT PACK - Loaded Registry'!$A$16:$H$18,6,FALSE),"UNRESOLVED") | D36: Formula | E36: Shows sector-specific BIA guidance / extensions | F36: 28 Sector Pack Registry
A37: SECTOR_TTP_TREATMENT | B37: Selected pack TTP treatment | C37: =IFERROR(VLOOKUP(C20,'OT PACK - Loaded Registry'!$A$16:$H$18,7,FALSE),"UNRESOLVED") | D37: Formula | E37: Shows sector-specific TTP governance | F37: 28 Sector Pack Registry

Sheet OT 04 - Control Assessment
A1: 04 — Control Assessment
A2: Purpose: Assess implementation quality and coverage for the controls used by the OT attack/consequence model.
A3: =IF('00 COMMON - Run Setup'!C6="OT","FILL this sheet — OT assessment.","Not used for this run. Complete the IT assessment section only.")
A4: SHEET TYPE: USER INPUT
A5: Inputs / upstream sources
A6: Control inventory plus assessor evidence. Maturity factors and default coverage are linked to 07 Control Assumptions.
A7: Calculation / decision logic
A8: Maturity Factor = lookup(Maturity). Not Assessed → Developing. Coverage Used = user coverage if supplied, otherwise DEFAULT_COVERAGE. Implementation Factor = Maturity Factor × Coverage Used. Actual TTP-control efficacy is calculated on 13 TTP-Control Map.
A9: Key assumptions / defaults
A10: Maturity factors: 0 / 0.25 / 0.50 / 0.75 / 0.95. Default coverage = 75%. Maturity deliberately excludes coverage language to avoid double counting.
A11: Outputs / downstream use
A12: Feeds 13 TTP-Control Map and all downstream attack-path / consequence control adjustments.
A13: Workbook convention: yellow cells / blue font are editable inputs or calibration assumptions; engine-output cells are not manually editable.
A15: Control ID | B15: Control | C15: Channel | D15: Maturity | E15: Coverage (user) | F15: Tested? | G15: Test result | H15: Evidence reference | I15: Maturity factor | J15: Coverage used | K15: Implementation factor | L15: How used
A16: M0801 | B16: Access Management | C16: Prevent / Resist | D16: Managed | F16: No | G16: n/a | I16: =IF(D16="Not Assessed",INDEX('OT CORE - Control Method'!$B$16:$B$20,MATCH("Developing",'OT CORE - Control Method'!$A$16:$A$20,0)),INDEX('OT CORE - Control Method'!$B$16:$B$20,MATCH(D16,'OT CORE - Control Method'!$A$16:$A$20,0))) | J16: =IF(E16="",INDEX('OT CORE - Control Method'!$B$26:$B$34,MATCH("DEFAULT_COVERAGE",'OT CORE - Control Method'!$A$26:$A$34,0)),E16) | K16: =I16*J16 | L16: Maturity represents implementation/operating quality. Coverage represents the in-scope population covered. Evidence supports the maturity judgement. Numerical TTP-control efficacy is calculated on 13 TTP-Control Map.
A17: M0936 | B17: Account Use Policies | C17: Prevent / Resist | D17: Managed | F17: No | G17: n/a | I17: =IF(D17="Not Assessed",INDEX('OT CORE - Control Method'!$B$16:$B$20,MATCH("Developing",'OT CORE - Control Method'!$A$16:$A$20,0)),INDEX('OT CORE - Control Method'!$B$16:$B$20,MATCH(D17,'OT CORE - Control Method'!$A$16:$A$20,0))) | J17: =IF(E17="",INDEX('OT CORE - Control Method'!$B$26:$B$34,MATCH("DEFAULT_COVERAGE",'OT CORE - Control Method'!$A$26:$A$34,0)),E17) | K17: =I17*J17 | L17: Maturity represents implementation/operating quality. Coverage represents the in-scope population covered. Evidence supports the maturity judgement. Numerical TTP-control efficacy is calculated on 13 TTP-Control Map.
A18: M0915 | B18: Active Directory Configuration | C18: Prevent / Resist | D18: Managed | F18: No | G18: n/a | I18: =IF(D18="Not Assessed",INDEX('OT CORE - Control Method'!$B$16:$B$20,MATCH("Developing",'OT CORE - Control Method'!$A$16:$A$20,0)),INDEX('OT CORE - Control Method'!$B$16:$B$20,MATCH(D18,'OT CORE - Control Method'!$A$16:$A$20,0))) | J18: =IF(E18="",INDEX('OT CORE - Control Method'!$B$26:$B$34,MATCH("DEFAULT_COVERAGE",'OT CORE - Control Method'!$A$26:$A$34,0)),E18) | K18: =I18*J18 | L18: Maturity represents implementation/operating quality. Coverage represents the in-scope population covered. Evidence supports the maturity judgement. Numerical TTP-control efficacy is calculated on 13 TTP-Control Map.
A19: M0949 | B19: Antivirus/Antimalware | C19: Prevent / Resist | D19: Managed | F19: No | G19: n/a | I19: =IF(D19="Not Assessed",INDEX('OT CORE - Control Method'!$B$16:$B$20,MATCH("Developing",'OT CORE - Control Method'!$A$16:$A$20,0)),INDEX('OT CORE - Control Method'!$B$16:$B$20,MATCH(D19,'OT CORE - Control Method'!$A$16:$A$20,0))) | J19: =IF(E19="",INDEX('OT CORE - Control Method'!$B$26:$B$34,MATCH("DEFAULT_COVERAGE",'OT CORE - Control Method'!$A$26:$A$34,0)),E19) | K19: =I19*J19 | L19: Maturity represents implementation/operating quality. Coverage represents the in-scope population covered. Evidence supports the maturity judgement. Numerical TTP-control efficacy is calculated on 13 TTP-Control Map.
A20: M0913 | B20: Application Developer Guidance | C20: Prevent / Resist | D20: Managed | F20: No | G20: n/a | I20: =IF(D20="Not Assessed",INDEX('OT CORE - Control Method'!$B$16:$B$20,MATCH("Developing",'OT CORE - Control Method'!$A$16:$A$20,0)),INDEX('OT CORE - Control Method'!$B$16:$B$20,MATCH(D20,'OT CORE - Control Method'!$A$16:$A$20,0))) | J20: =IF(E20="",INDEX('OT CORE - Control Method'!$B$26:$B$34,MATCH("DEFAULT_COVERAGE",'OT CORE - Control Method'!$A$26:$A$34,0)),E20) | K20: =I20*J20 | L20: Maturity represents implementation/operating quality. Coverage represents the in-scope population covered. Evidence supports the maturity judgement. Numerical TTP-control efficacy is calculated on 13 TTP-Control Map.
A21: M0948 | B21: Application Isolation and Sandboxing | C21: Prevent / Resist | D21: Managed | F21: No | G21: n/a | I21: =IF(D21="Not Assessed",INDEX('OT CORE - Control Method'!$B$16:$B$20,MATCH("Developing",'OT CORE - Control Method'!$A$16:$A$20,0)),INDEX('OT CORE - Control Method'!$B$16:$B$20,MATCH(D21,'OT CORE - Control Method'!$A$16:$A$20,0))) | J21: =IF(E21="",INDEX('OT CORE - Control Method'!$B$26:$B$34,MATCH("DEFAULT_COVERAGE",'OT CORE - Control Method'!$A$26:$A$34,0)),E21) | K21: =I21*J21 | L21: Maturity represents implementation/operating quality. Coverage represents the in-scope population covered. Evidence supports the maturity judgement. Numerical TTP-control efficacy is calculated on 13 TTP-Control Map.
A22: M0947 | B22: Audit | C22: Detect / Contain | D22: Managed | F22: No | G22: n/a | I22: =IF(D22="Not Assessed",INDEX('OT CORE - Control Method'!$B$16:$B$20,MATCH("Developing",'OT CORE - Control Method'!$A$16:$A$20,0)),INDEX('OT CORE - Control Method'!$B$16:$B$20,MATCH(D22,'OT CORE - Control Method'!$A$16:$A$20,0))) | J22: =IF(E22="",INDEX('OT CORE - Control Method'!$B$26:$B$34,MATCH("DEFAULT_COVERAGE",'OT CORE - Control Method'!$A$26:$A$34,0)),E22) | K22: =I22*J22 | L22: Maturity represents implementation/operating quality. Coverage represents the in-scope population covered. Evidence supports the maturity judgement. Numerical TTP-control efficacy is calculated on 13 TTP-Control Map.
A23: M0800 | B23: Authorization Enforcement | C23: Prevent / Resist | D23: Managed | F23: No | G23: n/a | I23: =IF(D23="Not Assessed",INDEX('OT CORE - Control Method'!$B$16:$B$20,MATCH("Developing",'OT CORE - Control Method'!$A$16:$A$20,0)),INDEX('OT CORE - Control Method'!$B$16:$B$20,MATCH(D23,'OT CORE - Control Method'!$A$16:$A$20,0))) | J23: =IF(E23="",INDEX('OT CORE - Control Method'!$B$26:$B$34,MATCH("DEFAULT_COVERAGE",'OT CORE - Control Method'!$A$26:$A$34,0)),E23) | K23: =I23*J23 | L23: Maturity represents implementation/operating quality. Coverage represents the in-scope population covered. Evidence supports the maturity judgement. Numerical TTP-control efficacy is calculated on 13 TTP-Control Map.
A24: M0946 | B24: Boot Integrity | C24: Prevent / Resist | D24: Managed | F24: No | G24: n/a | I24: =IF(D24="Not Assessed",INDEX('OT CORE - Control Method'!$B$16:$B$20,MATCH("Developing",'OT CORE - Control Method'!$A$16:$A$20,0)),INDEX('OT CORE - Control Method'!$B$16:$B$20,MATCH(D24,'OT CORE - Control Method'!$A$16:$A$20,0))) | J24: =IF(E24="",INDEX('OT CORE - Control Method'!$B$26:$B$34,MATCH("DEFAULT_COVERAGE",'OT CORE - Control Method'!$A$26:$A$34,0)),E24) | K24: =I24*J24 | L24: Maturity represents implementation/operating quality. Coverage represents the in-scope population covered. Evidence supports the maturity judgement. Numerical TTP-control efficacy is calculated on 13 TTP-Control Map.
A25: M0945 | B25: Code Signing | C25: Prevent / Resist | D25: Managed | F25: No | G25: n/a | I25: =IF(D25="Not Assessed",INDEX('OT CORE - Control Method'!$B$16:$B$20,MATCH("Developing",'OT CORE - Control Method'!$A$16:$A$20,0)),INDEX('OT CORE - Control Method'!$B$16:$B$20,MATCH(D25,'OT CORE - Control Method'!$A$16:$A$20,0))) | J25: =IF(E25="",INDEX('OT CORE - Control Method'!$B$26:$B$34,MATCH("DEFAULT_COVERAGE",'OT CORE - Control Method'!$A$26:$A$34,0)),E25) | K25: =I25*J25 | L25: Maturity represents implementation/operating quality. Coverage represents the in-scope population covered. Evidence supports the maturity judgement. Numerical TTP-control efficacy is calculated on 13 TTP-Control Map.
A26: M0802 | B26: Communication Authenticity | C26: Prevent / Resist | D26: Managed | F26: No | G26: n/a | I26: =IF(D26="Not Assessed",INDEX('OT CORE - Control Method'!$B$16:$B$20,MATCH("Developing",'OT CORE - Control Method'!$A$16:$A$20,0)),INDEX('OT CORE - Control Method'!$B$16:$B$20,MATCH(D26,'OT CORE - Control Method'!$A$16:$A$20,0))) | J26: =IF(E26="",INDEX('OT CORE - Control Method'!$B$26:$B$34,MATCH("DEFAULT_COVERAGE",'OT CORE - Control Method'!$A$26:$A$34,0)),E26) | K26: =I26*J26 | L26: Maturity represents implementation/operating quality. Coverage represents the in-scope population covered. Evidence supports the maturity judgement. Numerical TTP-control efficacy is calculated on 13 TTP-Control Map.
A27: M0953 | B27: Data Backup | C27: Recover / Restore | D27: Managed | F27: No | G27: n/a | I27: =IF(D27="Not Assessed",INDEX('OT CORE - Control Method'!$B$16:$B$20,MATCH("Developing",'OT CORE - Control Method'!$A$16:$A$20,0)),INDEX('OT CORE - Control Method'!$B$16:$B$20,MATCH(D27,'OT CORE - Control Method'!$A$16:$A$20,0))) | J27: =IF(E27="",INDEX('OT CORE - Control Method'!$B$26:$B$34,MATCH("DEFAULT_COVERAGE",'OT CORE - Control Method'!$A$26:$A$34,0)),E27) | K27: =I27*J27 | L27: Maturity represents implementation/operating quality. Coverage represents the in-scope population covered. Evidence supports the maturity judgement. Numerical TTP-control efficacy is calculated on 13 TTP-Control Map.
... A67: M0815 | B67: Watchdog Timers | C67: Safety / Resilience | D67: Managed | F67: No | G67: n/a | I67: =IF(D67="Not Assessed",INDEX('OT CORE - Control Method'!$B$16:$B$20,MATCH("Developing",'OT CORE - Control Method'!$A$16:$A$20,0)),INDEX('OT CORE - Control Method'!$B$16:$B$20,MATCH(D67,'OT CORE - Control Method'!$A$16:$A$20,0))) | J67: =IF(E67="",INDEX('OT CORE - Control Method'!$B$26:$B$34,MATCH("DEFAULT_COVERAGE",'OT CORE - Control Method'!$A$26:$A$34,0)),E67) | K67: =I67*J67 | L67: Maturity represents implementation/operating quality. Coverage represents the in-scope population covered. Evidence supports the maturity judgement. Numerical TTP-control efficacy is calculated on 13 TTP-Control Map.
A71: CONTROL ASSESSMENT FIELD GUIDE
A73: Field | B73: Who assesses it? | C73: Numerical effect? | D73: Interpretation / model use
A74: Maturity | B74: Assessor | C74: Yes | D74: Implementation and operating quality. This is the model's implementation-quality assessment.
A75: Coverage (user) | B75: Assessor | C75: Yes | D75: Share of the relevant in-scope environment covered. Blank uses 75%.
A76: Tested? | B76: Assessor/evidence | C76: No direct multiplier | D76: Supports the maturity judgement and audit trail.
A77: Test result | B77: Assessor/evidence | C77: No direct multiplier | D77: Supports the maturity judgement and audit trail.
A78: Evidence reference | B78: Assessor/evidence | C78: No direct multiplier | D78: Links the judgement to evidence.
A79: Maturity factor | B79: Formula-linked | C79: Yes | D79: Lookup from 07 Control Assumptions; Not Assessed defaults to Developing = 0.50.
A80: Implementation factor | B80: Formula-linked | C80: Yes | D80: Maturity Factor × Coverage Used. It is not itself total cyber-risk reduction.

Sheet OT 05 - Impact & BIA
A1: 05 — OT IMPACT DRIVER MATRIX, BIA & CALIBRATION
A2: Purpose: Build conditional facility impact from the common 18-driver OT BIA, scenario applicability, facility revenue, asset counts, unit rates and P50/P99 operating assumptions across all sector packs.
A3: =IF('00 COMMON - Run Setup'!C6="OT","FILL this sheet — OT assessment.","Not used for this run. Complete the IT assessment section only.")
A4: Enter facility-specific values or overrides only where facility evidence supports departure from the selected OT sector-pack baseline. Pack-owned rows are read-only.
A6: Inputs / upstream sources: Finance and BIA revenue; Operations/Engineering downtime and capacity; asset register; IR/OEM/Legal/HSE rates; incident and claims evidence.
A8: Calculation logic: applicable drivers are calculated from the visible equations. P50 is the conditional median; P99 is the configured conditional stress percentile. BI = revenue ÷ 365 × BI factor × downtime × capacity.
A10: Key assumption: the common 18-driver BIA remains the engine structure across all three sectors. Sector packs on 30–32 now provide scenario downtime/capacity starting points and sector-specific calibration evidence. Current cells remain the Power Generation reference values until a compatible engine / pack loader applies the selected pack or the user replaces them with facility BIA evidence.
A12: Outputs / downstream use: scenario/actor conditional loss in 17, annual AAL and tail risk in 02 and 18–25, and control what-if severity benefits in 20.
A15: Parameter | B15: Question | C15: Value | D15: Unit | E15: Basis / source | F15: How used
A16: ANNUAL_REVENUE_AT_RISK | B16: Annual facility revenue at risk | C16: 1000000000 | D16: USD/year | E16: Demo placeholder — replace with Finance/BIA | F16: BI and revenue-scaled drivers.
A17: BI_LOSS_FACTOR | B17: BI factor (% of disrupted revenue) | C17: 1 | D17: share | E17: Default 100%; reduce only with avoided-cost evidence | F17: Converts gross revenue disruption to modelled BI.
A18: EMPLOYEES | B18: Facility employees / contractors in scope | C18: 1000 | D18: count | E18: Demo placeholder — optional scaling input | F18: Recorded for calibration context; not used by a default driver.
A19: CRITICAL_OT_ENDPOINTS | B19: Critical OT endpoints/controllers in scope | C19: 500 | D19: count | E19: Demo placeholder — replace with asset register | F19: Scales controller/endpoint replacement cost.
A20: CRITICAL_OT_SERVERS | B20: Critical OT servers/engineering systems in scope | C20: 50 | D20: count | E20: Demo placeholder — replace with asset register | F20: Scales OT server/engineering-system replacement cost.
A22: Derived metric | B22: Formula-linked value | C22: Unit | D22: Formula / interpretation
A23: Gross revenue per calendar day | B23: =C16/365 | C23: USD/day | D23: Annual Revenue at Risk ÷ 365
A24: BI value per calendar day | B24: =C16*C17/365 | C24: USD/day | D24: Annual Revenue at Risk × BI Factor ÷ 365
A26: EDITABLE OT IMPACT-DRIVER APPLICABILITY MATRIX
A27: Cost category | B27: Driver ID | C27: Cost driver | D27: Actor applicability | E27: Control sensitivity | F27: Operational disruption | G27: Loss of control / visibility | H27: Process manipulation | I27: Safety system compromise | J27: Destructive / integrity attack | K27: Calculation / equation | L27: Calibration guidance
A28: Incident response costs
A29: Incident response costs | B29: IR-01 | C29: OT and digital forensic investigation | D29: All | E29: Fixed | F29: TRUE | G29: TRUE | H29: TRUE | I29: TRUE | J29: TRUE | K29: Daily forensic team cost × days required | L29: Use retained incident-response rates and expected OT evidence-preservation duration.
A30: Incident response costs | B30: IR-02 | C30: External cyber incident response | D30: All | E30: Fixed | F30: TRUE | G30: TRUE | H30: TRUE | I30: TRUE | J30: TRUE | K30: Daily external response team cost × days required | L30: Calibrate to panel/retainer rates, travel and surge staffing.
A31: Incident response costs | B31: IR-03 | C31: Crisis communications | D31: All | E31: Fixed | F31: TRUE | G31: TRUE | H31: TRUE | I31: TRUE | J31: TRUE | K31: Daily crisis communications cost × days required | L31: Include external communications support only; exclude legal cost captured elsewhere.
A32: Recovery and restoration costs
A33: Recovery and restoration costs | B33: RC-01 | C33: OT restoration and recommissioning | D33: All | E33: Recover | F33: TRUE | G33: TRUE | H33: TRUE | I33: TRUE | J33: TRUE | K33: Daily restoration team cost × days required | L33: Include controls validation, loop checks, recommissioning and restart support.
A34: Recovery and restoration costs | B34: RC-02 | C34: OEM and specialist engineering support | D34: All | E34: Recover | F34: TRUE | G34: TRUE | H34: TRUE | I34: TRUE | J34: TRUE | K34: Daily OEM/specialist cost × days required | L34: Use framework rates and realistic mobilisation duration for key OEMs.
A35: Recovery and restoration costs | B35: RC-03 | C35: Configuration/data restoration and integrity validation | D35: All | E35: Recover | F35: TRUE | G35: TRUE | H35: TRUE | I35: TRUE | J35: TRUE | K35: Daily validation team cost × days required | L35: Include golden-image restore, configuration comparison and integrity assurance.
A36: Business interruption and continuity
A37: Business interruption and continuity | B37: BI-01 | C37: Business interruption | D37: All | E37: Duration | F37: TRUE | G37: TRUE | H37: TRUE | I37: TRUE | J37: TRUE | K37: Annual revenue ÷ 365 × BI factor × downtime × capacity affected | L37: 100% BI factor is the default. Reduce only when Finance can evidence avoided/non-continuing costs.
A38: Business interruption and continuity | B38: OP-01 | C38: Manual operations / increased cost of working | D38: All | E38: Recover | F38: TRUE | G38: TRUE | H38: TRUE | I38: TRUE | J38: TRUE | K38: Daily incremental operating cost × scenario downtime | L38: Include only incremental labour, temporary plant and workarounds not already in BI.
A39: Business interruption and continuity | B39: OP-02 | C39: Alternative supply / availability and contract penalties | D39: All | E39: Recover | F39: TRUE | G39: TRUE | H39: TRUE | I39: TRUE | J39: TRUE | K39: Daily alternative-supply/penalty cost × scenario downtime | L39: Use only amounts borne by the facility and not already captured in revenue at risk.
A40: Direct loss / extortion
A41: Direct loss / extortion | B41: EX-01 | C41: Extortion / ransom | D41: Cybercriminal | E41: Fixed | F41: TRUE | G41: FALSE | H41: FALSE | I41: FALSE | J41: TRUE | K41: Direct conditional amount | L41: Applied only to Cybercriminal events; enter zero if policy or governance excludes payment.
A42: Legal and regulatory costs
A43: Legal and regulatory costs | B43: LG-01 | C43: Legal and regulatory response | D43: All | E43: Fixed | F43: TRUE | G43: TRUE | H43: TRUE | I43: TRUE | J43: TRUE | K43: Daily external legal/regulatory cost × days required | L43: Include external counsel and regulatory response; exclude fines captured below.
A44: Legal and regulatory costs | B44: LG-02 | C44: Regulatory fines and penalties | D44: All | E44: Fixed | F44: FALSE | G44: FALSE | H44: TRUE | I44: TRUE | J44: TRUE | K44: Annual revenue × conditional penalty share | L44: Use the expected paid amount, not a statutory maximum; set FALSE where not relevant.
A45: Safety and environmental costs
A46: Safety and environmental costs | B46: SF-01 | C46: Safety and emergency response | D46: All | E46: Safety | F46: FALSE | G46: FALSE | H46: TRUE | I46: TRUE | J46: TRUE | K46: Direct conditional amount | L46: Include emergency response, medical and investigation cost; exclude physical repair.
A47: Safety and environmental costs | B47: EN-01 | C47: Environmental remediation | D47: All | E47: Safety | F47: FALSE | G47: FALSE | H47: TRUE | I47: TRUE | J47: TRUE | K47: Direct conditional amount | L47: Include cleanup and remediation only where the scenario can cause a release.
A48: Physical damage costs
A49: Physical damage costs | B49: PD-01 | C49: OT endpoint / controller replacement | D49: All | E49: Recover | F49: TRUE | G49: TRUE | H49: TRUE | I49: TRUE | J49: TRUE | K49: Critical OT endpoints × affected share × replacement unit cost | L49: Count only critical controllers/HMIs/OT workstations in the scoped facility.
A50: Physical damage costs | B50: PD-02 | C50: OT server / engineering-system replacement | D50: All | E50: Recover | F50: TRUE | G50: TRUE | H50: TRUE | I50: TRUE | J50: TRUE | K50: Critical OT servers × affected share × replacement unit cost | L50: Include configured replacement and specialist rebuild, not ordinary desktop hardware.
A51: Physical damage costs | B51: PD-03 | C51: Major equipment / physical damage | D51: All | E51: Safety | F51: FALSE | G51: FALSE | H51: TRUE | I51: TRUE | J51: TRUE | K51: Direct conditional amount | L51: Use engineering loss scenarios; do not duplicate controller/server replacement.
A52: Indirect losses
A53: Indirect losses | B53: IN-01 | C53: Post-event security uplift | D53: All | E53: Fixed | F53: TRUE | G53: TRUE | H53: TRUE | I53: TRUE | J53: TRUE | K53: Annual revenue × conditional uplift share | L53: Optional incremental programme cost after an event; set FALSE if budgeted elsewhere.
A56: SCENARIO DOWNTIME & CAPACITY CALIBRATION
A57: Scenario | B57: P50 downtime (days) | C57: P99 downtime (days) | D57: P50 capacity affected | E57: P99 capacity affected | F57: Calibration status | G57: Calibration note
A58: Operational Disruption | B58: 5 | C58: 45 | D58: 0.75 | E58: 1 | F58: Working prior — calibrate | G58: Material outage/reduced generation; use BIA, dispatch and claims evidence.
A59: Loss of Control or Visibility | B59: 3 | C59: 30 | D59: 0.5 | E59: 1 | F59: Working prior — calibrate | G59: Loss of trusted view/control may force conservative operation or shutdown.
A60: Process Manipulation | B60: 7 | C60: 60 | D60: 0.75 | E60: 1 | F60: Working prior — calibrate | G60: Unsafe or off-spec process changes may require inspection and recommissioning.
A61: Safety System Compromise | B61: 14 | C61: 120 | D61: 0.8 | E61: 1 | F61: Working prior — calibrate | G61: Protection/SIS restoration and assurance can extend outage duration.
A62: Destructive or Integrity Attack | B62: 30 | C62: 180 | D62: 1 | E62: 1 | F62: Working prior — calibrate | G62: Rebuild, replacement and integrity assurance create the longest tail.
A65: DRIVER RATE, QUANTITY & SHARE ASSUMPTIONS
A66: Driver ID | B66: Cost driver | C66: Base rate / unit cost | D66: Stress rate / unit cost | E66: Base quantity / share | F66: Stress quantity / share | G66: Rate / quantity unit | H66: Scaling input | I66: Calculation type | J66: Reference P50 (Operational) | K66: Reference P99 (Operational) | L66: Basis / calibration status
A67: IR-01 | B67: OT and digital forensic investigation | C67: 20000 | D67: 45000 | E67: 30 | F67: 90 | G67: USD/day × days | I67: DAILY_X_DAYS | J67: =IF($F$29="TRUE",$C$67*$E$67,0) | K67: =IF($F$29="TRUE",$D$67*$F$67,0) | L67: Working prior; replace with IR retainer, panel and claims data.
A68: IR-02 | B68: External cyber incident response | C68: 25000 | D68: 50000 | E68: 30 | F68: 120 | G68: USD/day × days | I68: DAILY_X_DAYS | J68: =IF($F$30="TRUE",$C$68*$E$68,0) | K68: =IF($F$30="TRUE",$D$68*$F$68,0) | L68: Working prior; replace with response supplier evidence.
A69: IR-03 | B69: Crisis communications | C69: 10000 | D69: 25000 | E69: 15 | F69: 60 | G69: USD/day × days | I69: DAILY_X_DAYS | J69: =IF($F$31="TRUE",$C$69*$E$69,0) | K69: =IF($F$31="TRUE",$D$69*$F$69,0) | L69: Working prior; calibrate with communications and panel rates.
A70: RC-01 | B70: OT restoration and recommissioning | C70: 30000 | D70: 75000 | E70: 30 | F70: 180 | G70: USD/day × days | I70: DAILY_X_DAYS | J70: =IF($F$33="TRUE",$C$70*$E$70,0) | K70: =IF($F$33="TRUE",$D$70*$F$70,0) | L70: Working prior; replace with Engineering/O&M work-pack estimates.
A71: RC-02 | B71: OEM and specialist engineering support | C71: 25000 | D71: 75000 | E71: 30 | F71: 180 | G71: USD/day × days | I71: DAILY_X_DAYS | J71: =IF($F$34="TRUE",$C$71*$E$71,0) | K71: =IF($F$34="TRUE",$D$71*$F$71,0) | L71: Working prior; replace with OEM/framework agreements.
A72: RC-03 | B72: Configuration/data restoration and integrity validation | C72: 15000 | D72: 40000 | E72: 20 | F72: 120 | G72: USD/day × days | I72: DAILY_X_DAYS | J72: =IF($F$35="TRUE",$C$72*$E$72,0) | K72: =IF($F$35="TRUE",$D$72*$F$72,0) | L72: Working prior; calibrate from recovery plans and exercises.
A73: BI-01 | B73: Business interruption | G73: USD | H73: ANNUAL_REVENUE_AT_RISK | I73: BI_SCENARIO | J73: =IF($F$37="TRUE",$C$16/365*$C$17*$B$58*$D$58,0) | K73: =IF($F$37="TRUE",$C$16/365*$C$17*$C$58*$E$58,0) | L73: Agreed revenue-based convention; scenario duration/capacity below.
A74: OP-01 | B74: Manual operations / increased cost of working | C74: 50000 | D74: 200000 | G74: USD/day × scenario days | I74: DAILY_X_SCENARIO_DAYS | J74: =IF($F$38="TRUE",$C$74*$B$58,0) | K74: =IF($F$38="TRUE",$D$74*$C$58,0) | L74: Working prior; replace with continuity and operations estimates.
A75: OP-02 | B75: Alternative supply / availability and contract penalties | C75: 150000 | D75: 750000 | G75: USD/day × scenario days | I75: DAILY_X_SCENARIO_DAYS | J75: =IF($F$39="TRUE",$C$75*$B$58,0) | K75: =IF($F$39="TRUE",$D$75*$C$58,0) | L75: Working prior; calibrate with Commercial contracts, continuity arrangements and penalty terms.
A76: EX-01 | B76: Extortion / ransom | C76: 2000000 | D76: 25000000 | G76: USD | I76: DIRECT | J76: =IF($F$41="TRUE",$C$76,0) | K76: =IF($F$41="TRUE",$D$76,0) | L76: Working prior; replace with approved incident/claims/market evidence.
A77: LG-01 | B77: Legal and regulatory response | C77: 10000 | D77: 30000 | E77: 30 | F77: 180 | G77: USD/day × days | I77: DAILY_X_DAYS | J77: =IF($F$43="TRUE",$C$77*$E$77,0) | K77: =IF($F$43="TRUE",$D$77*$F$77,0) | L77: Working prior; replace with Legal panel and response estimates.
A78: LG-02 | B78: Regulatory fines and penalties | E78: 0.0005 | F78: 0.01 | G78: share of annual revenue | H78: ANNUAL_REVENUE_AT_RISK | I78: REVENUE_X_SHARE | J78: =IF($F$44="TRUE",$C$16*$E$78,0) | K78: =IF($F$44="TRUE",$C$16*$F$78,0) | L78: Working prior; Legal must calibrate jurisdiction and enforcement context.
A79: SF-01 | B79: Safety and emergency response | C79: 1000000 | D79: 25000000 | G79: USD | I79: DIRECT | J79: =IF($F$46="TRUE",$C$79,0) | K79: =IF($F$46="TRUE",$D$79,0) | L79: Working prior; replace with HSE scenario and claims evidence.
A80: EN-01 | B80: Environmental remediation | C80: 1000000 | D80: 50000000 | G80: USD | I80: DIRECT | J80: =IF($F$47="TRUE",$C$80,0) | K80: =IF($F$47="TRUE",$D$80,0) | L80: Working prior; replace with HSE/environmental loss scenarios.
A81: PD-01 | B81: OT endpoint / controller replacement | C81: 15000 | D81: 40000 | E81: 0.1 | F81: 0.5 | G81: USD/unit × affected share | H81: CRITICAL_OT_ENDPOINTS | I81: ASSET_X_SHARE_X_UNIT | J81: =IF($F$49="TRUE",$C$19*$E$81*$C$81,0) | K81: =IF($F$49="TRUE",$C$19*$F$81*$D$81,0) | L81: Working prior; calibrate from asset register and replacement estimates.
A82: PD-02 | B82: OT server / engineering-system replacement | C82: 50000 | D82: 150000 | E82: 0.1 | F82: 0.5 | G82: USD/unit × affected share | H82: CRITICAL_OT_SERVERS | I82: ASSET_X_SHARE_X_UNIT | J82: =IF($F$50="TRUE",$C$20*$E$82*$C$82,0) | K82: =IF($F$50="TRUE",$C$20*$F$82*$D$82,0) | L82: Working prior; calibrate from asset register/OEM estimates.
A83: PD-03 | B83: Major equipment / physical damage | C83: 2000000 | D83: 150000000 | G83: USD | I83: DIRECT | J83: =IF($F$51="TRUE",$C$83,0) | K83: =IF($F$51="TRUE",$D$83,0) | L83: Working prior; replace with Engineering/property loss scenarios.
A84: IN-01 | B84: Post-event security uplift | E84: 0.001 | F84: 0.0075 | G84: share of annual revenue | H84: ANNUAL_REVENUE_AT_RISK | I84: REVENUE_X_SHARE | J84: =IF($F$53="TRUE",$C$16*$E$84,0) | K84: =IF($F$53="TRUE",$C$16*$F$84,0) | L84: Working prior; calibrate with Cyber/Engineering remediation plans.
A87: FORMULA-LINKED CONDITIONAL DRIVER COST BY SCENARIO
A88: Scenario | B88: Driver ID | C88: Cost driver | D88: P50 conditional cost | E88: P99 conditional cost | F88: Unit | G88: Actor applicability | H88: Control sensitivity | I88: Visible calculation / calibration note
A89: Operational Disruption | B89: IR-01 | C89: OT and digital forensic investigation | D89: =IF($F$29="TRUE",$C$67*$E$67,0) | E89: =IF($F$29="TRUE",$D$67*$F$67,0) | F89: USD | G89: All | H89: Fixed | I89: Daily forensic team cost × days required. Working prior; replace with IR retainer, panel and claims data.
A90: Operational Disruption | B90: IR-02 | C90: External cyber incident response | D90: =IF($F$30="TRUE",$C$68*$E$68,0) | E90: =IF($F$30="TRUE",$D$68*$F$68,0) | F90: USD | G90: All | H90: Fixed | I90: Daily external response team cost × days required. Working prior; replace with response supplier evidence.
A91: Operational Disruption | B91: IR-03 | C91: Crisis communications | D91: =IF($F$31="TRUE",$C$69*$E$69,0) | E91: =IF($F$31="TRUE",$D$69*$F$69,0) | F91: USD | G91: All | H91: Fixed | I91: Daily crisis communications cost × days required. Working prior; calibrate with communications and panel rates.
A92: Operational Disruption | B92: RC-01 | C92: OT restoration and recommissioning | D92: =IF($F$33="TRUE",$C$70*$E$70,0) | E92: =IF($F$33="TRUE",$D$70*$F$70,0) | F92: USD | G92: All | H92: Recover | I92: Daily restoration team cost × days required. Working prior; replace with Engineering/O&M work-pack estimates.
A93: Operational Disruption | B93: RC-02 | C93: OEM and specialist engineering support | D93: =IF($F$34="TRUE",$C$71*$E$71,0) | E93: =IF($F$34="TRUE",$D$71*$F$71,0) | F93: USD | G93: All | H93: Recover | I93: Daily OEM/specialist cost × days required. Working prior; replace with OEM/framework agreements.
A94: Operational Disruption | B94: RC-03 | C94: Configuration/data restoration and integrity validation | D94: =IF($F$35="TRUE",$C$72*$E$72,0) | E94: =IF($F$35="TRUE",$D$72*$F$72,0) | F94: USD | G94: All | H94: Recover | I94: Daily validation team cost × days required. Working prior; calibrate from recovery plans and exercises.
A95: Operational Disruption | B95: BI-01 | C95: Business interruption | D95: =IF($F$37="TRUE",$C$16/365*$C$17*$B$58*$D$58,0) | E95: =IF($F$37="TRUE",$C$16/365*$C$17*$C$58*$E$58,0) | F95: USD | G95: All | H95: Duration | I95: Annual revenue ÷ 365 × BI factor × downtime × capacity affected. Agreed revenue-based convention; scenario duration/capacity below.
A96: Operational Disruption | B96: OP-01 | C96: Manual operations / increased cost of working | D96: =IF($F$38="TRUE",$C$74*$B$58,0) | E96: =IF($F$38="TRUE",$D$74*$C$58,0) | F96: USD | G96: All | H96: Recover | I96: Daily incremental operating cost × scenario downtime. Working prior; replace with continuity and operations estimates.
A97: Operational Disruption | B97: OP-02 | C97: Alternative supply / availability and contract penalties | D97: =IF($F$39="TRUE",$C$75*$B$58,0) | E97: =IF($F$39="TRUE",$D$75*$C$58,0) | F97: USD | G97: All | H97: Recover | I97: Daily incremental replacement/penalty cost × scenario downtime. Working prior; calibrate with Commercial contracts, continuity arrangements and penalty terms.
A98: Operational Disruption | B98: EX-01 | C98: Extortion / ransom | D98: =IF($F$41="TRUE",$C$76,0) | E98: =IF($F$41="TRUE",$D$76,0) | F98: USD | G98: Cybercriminal | H98: Fixed | I98: Direct conditional amount. Working prior; replace with approved incident/claims/market evidence.
A99: Operational Disruption | B99: LG-01 | C99: Legal and regulatory response | D99: =IF($F$43="TRUE",$C$77*$E$77,0) | E99: =IF($F$43="TRUE",$D$77*$F$77,0) | F99: USD | G99: All | H99: Fixed | I99: Daily external legal/regulatory cost × days required. Working prior; replace with Legal panel and response estimates.
A100: Operational Disruption | B100: LG-02 | C100: Regulatory fines and penalties | D100: =IF($F$44="TRUE",$C$16*$E$78,0) | E100: =IF($F$44="TRUE",$C$16*$F$78,0) | F100: USD | G100: All | H100: Fixed | I100: Annual revenue × conditional penalty share. Working prior; Legal must calibrate jurisdiction and enforcement context.
A101: Operational Disruption | B101: SF-01 | C101: Safety and emergency response | D101: =IF($F$46="TRUE",$C$79,0) | E101: =IF($F$46="TRUE",$D$79,0) | F101: USD | G101: All | H101: Safety | I101: Direct conditional amount. Working prior; replace with HSE scenario and claims evidence.
A102: Operational Disruption | B102: EN-01 | C102: Environmental remediation | D102: =IF($F$47="TRUE",$C$80,0) | E102: =IF($F$47="TRUE",$D$80,0) | F102: USD | G102: All | H102: Safety | I102: Direct conditional amount. Working prior; replace with HSE/environmental loss scenarios.
A103: Operational Disruption | B103: PD-01 | C103: OT endpoint / controller replacement | D103: =IF($F$49="TRUE",$C$19*$E$81*$C$81,0) | E103: =IF($F$49="TRUE",$C$19*$F$81*$D$81,0) | F103: USD | G103: All | H103: Recover | I103: Critical OT endpoints × affected share × replacement unit cost. Working prior; calibrate from asset register and replacement estimates.
A104: Operational Disruption | B104: PD-02 | C104: OT server / engineering-system replacement | D104: =IF($F$50="TRUE",$C$20*$E$82*$C$82,0) | E104: =IF($F$50="TRUE",$C$20*$F$82*$D$82,0) | F104: USD | G104: All | H104: Recover | I104: Critical OT servers × affected share × replacement unit cost. Working prior; calibrate from asset register/OEM estimates.
A105: Operational Disruption | B105: PD-03 | C105: Major equipment / physical damage | D105: =IF($F$51="TRUE",$C$83,0) | E105: =IF($F$51="TRUE",$D$83,0) | F105: USD | G105: All | H105: Safety | I105: Direct conditional amount. Working prior; replace with Engineering/property loss scenarios.
A106: Operational Disruption | B106: IN-01 | C106: Post-event security uplift | D106: =IF($F$53="TRUE",$C$16*$E$84,0) | E106: =IF($F$53="TRUE",$C$16*$F$84,0) | F106: USD | G106: All | H106: Fixed | I106: Annual revenue × conditional uplift share. Working prior; calibrate with Cyber/Engineering remediation plans.
A107: Loss of Control or Visibility | B107: IR-01 | C107: OT and digital forensic investigation | D107: =IF($G$29="TRUE",$C$67*$E$67,0) | E107: =IF($G$29="TRUE",$D$67*$F$67,0) | F107: USD | G107: All | H107: Fixed | I107: Daily forensic team cost × days required. Working prior; replace with IR retainer, panel and claims data.
A108: Loss of Control or Visibility | B108: IR-02 | C108: External cyber incident response | D108: =IF($G$30="TRUE",$C$68*$E$68,0) | E108: =IF($G$30="TRUE",$D$68*$F$68,0) | F108: USD | G108: All | H108: Fixed | I108: Daily external response team cost × days required. Working prior; replace with response supplier evidence.
A109: Loss of Control or Visibility | B109: IR-03 | C109: Crisis communications | D109: =IF($G$31="TRUE",$C$69*$E$69,0) | E109: =IF($G$31="TRUE",$D$69*$F$69,0) | F109: USD | G109: All | H109: Fixed | I109: Daily crisis communications cost × days required. Working prior; calibrate with communications and panel rates.
A110: Loss of Control or Visibility | B110: RC-01 | C110: OT restoration and recommissioning | D110: =IF($G$33="TRUE",$C$70*$E$70,0) | E110: =IF($G$33="TRUE",$D$70*$F$70,0) | F110: USD | G110: All | H110: Recover | I110: Daily restoration team cost × days required. Working prior; replace with Engineering/O&M work-pack estimates.
A111: Loss of Control or Visibility | B111: RC-02 | C111: OEM and specialist engineering support | D111: =IF($G$34="TRUE",$C$71*$E$71,0) | E111: =IF($G$34="TRUE",$D$71*$F$71,0) | F111: USD | G111: All | H111: Recover | I111: Daily OEM/specialist cost × days required. Working prior; replace with OEM/framework agreements.
A112: Loss of Control or Visibility | B112: RC-03 | C112: Configuration/data restoration and integrity validation | D112: =IF($G$35="TRUE",$C$72*$E$72,0) | E112: =IF($G$35="TRUE",$D$72*$F$72,0) | F112: USD | G112: All | H112: Recover | I112: Daily validation team cost × days required. Working prior; calibrate from recovery plans and exercises.
A113: Loss of Control or Visibility | B113: BI-01 | C113: Business interruption | D113: =IF($G$37="TRUE",$C$16/365*$C$17*$B$59*$D$59,0) | E113: =IF($G$37="TRUE",$C$16/365*$C$17*$C$59*$E$59,0) | F113: USD | G113: All | H113: Duration | I113: Annual revenue ÷ 365 × BI factor × downtime × capacity affected. Agreed revenue-based convention; scenario duration/capacity below.
A114: Loss of Control or Visibility | B114: OP-01 | C114: Manual operations / increased cost of working | D114: =IF($G$38="TRUE",$C$74*$B$59,0) | E114: =IF($G$38="TRUE",$D$74*$C$59,0) | F114: USD | G114: All | H114: Recover | I114: Daily incremental operating cost × scenario downtime. Working prior; replace with continuity and operations estimates.
...

Sheet OT 06 - Assessment Adjustments
A1: 06 — Frequency, Threat & Simulation Assumptions
A2: Purpose: Provide the likelihood calibration layer: reference campaign arrival, explicit prudence, actor mix, scenario propensity, actor capability, facility exposure, sector/asset and geography modifiers.
A3: =IF('00 COMMON - Run Setup'!C6="OT","FILL this sheet — OT assessment.","Not used for this run. Complete the IT assessment section only.")
A4: Assessment adjustments only. Effective λ = Core reference × sector-pack actor multiplier × asset-type overlay × facility exposure × geography × client actor activity × prudence. Do not edit pack multipliers here.
A5: Inputs / upstream sources
A6: Internal incidents/threat intelligence, sector/region evidence, red-team/BAS evidence and expert elicitation. Current values are working priors unless stated otherwise.
A7: Calculation / decision logic
A8: Best-estimate λ = 0.55 reference campaigns/facility-year × Facility Exposure × Σ(Actor Share × Threat Activity × Sector × Asset Type × Geography). Asset Type is governed on 28 and must be applied exactly once by the compatible engine.
A9: Key assumptions / defaults
A10: The 0.55 rate remains the Power Generation reference working prior. V1.8 adds evidence-informed, explicitly governed sector actor multipliers for Energy Assets and Manufacturing. These are structured relative priors — not empirical facility-year rates — because public threat datasets lack a compatible denominator. Prudence remains a separate frequency-only overlay.
A11: Outputs / downstream use
A12: Feeds 15 Attack Path Calc, 16 Threat and Loss Frequency and the Monte Carlo engine.
A13: Workbook convention: yellow cells / blue font are editable inputs or calibration assumptions; engine-output cells are not manually editable.
A15: Parameter | B15: Parameter type | C15: Low | D15: Base | E15: High | F15: Unit | G15: Basis / evidence | H15: How used
A16: REFERENCE_CAMPAIGNS_PER_YEAR | B16: Calibration parameter | D16: 0.55 | F16: campaigns/facility-year | G16: Centrally governed working prior; external sources observe outcomes, not attempted material campaigns | H16: Best-estimate arrival-rate anchor before facility and actor-intensity modifiers.
A17: PRUDENCE_FACTOR | B17: User override | D17: 1.5 | F17: multiplier | G17: Agreed risk-appetite overlay; default 1.50×; no upper cap | H17: Applied only to best-estimate λ to produce the Prudent view.
A18: REPORTING_VIEW | B18: Reporting selector | D18: Both | F18: selection | G18: User selection | H18: Best Estimate, Prudent or Both. When Both is selected, detailed sheets use Prudent and comparison sheets show both.
A19: SIMULATIONS | B19: Computational setting | D19: 500000 | F19: facility-years | G19: Required model setting | H19: Simulation years per view and per control what-if. Required value is 500,000.
A20: RANDOM_SEED | B20: Computational setting | D20: 20260813 | F20: seed | G20: Reproducibility setting | H20: Fixed seed enables common-random-number comparisons within each view.
A25: Threat actor | B25: Campaign share | C25: Threat activity multiplier (advanced) | D25: S1 | E25: S2 | F25: S3 | G25: S4 | H25: S5 capability | I25: Calibration status | J25: How used
A27: Nation State | B27: 0.2 | C27: 1 | D27: 0.8 | E27: 0.85 | F27: 0.7 | G27: 0.75 | H27: 0.85 | I27: Benchmark-informed actor allocation prior | J27: Share allocates campaigns; threat activity remains 1.00 unless a dated intelligence overlay is approved. S1–S4 and S5 are structured expert priors.
A28: Cybercriminal | B28: 0.75 | C28: 1 | D28: 0.8 | E28: 0.8 | F28: 0.65 | G28: 0.65 | H28: 0.65 | I28: Benchmark-informed actor allocation prior | J28: Cybercriminal dominance is directionally supported by OT ransomware evidence; deep-OT capability remains expert judgement.
A29: Malicious Insider | B29: 0.05 | C29: 1 | D29: Not used | E29: 0.9 | F29: 0.8 | G29: 0.75 | H29: 0.75 | I29: Structured expert prior | J29: The malicious-insider share is not supported by a direct OT denominator. S1 is bypassed and therefore not used.
A33: Threat actor | B33: Operational Disruption | C33: Loss of Control or Visibility | D33: Process Manipulation | E33: Safety System Compromise | F33: Destructive or Integrity Attack | G33: Row sum
A35: Nation State | B35: 0.25 | C35: 0.15 | D35: 0.25 | E35: 0.15 | F35: 0.2 | G35: =SUM(B35:F35)
A36: Cybercriminal | B36: 0.7 | C36: 0.1 | D36: 0.05 | E36: 0.02 | F36: 0.13 | G36: =SUM(B36:F36)
A37: Malicious Insider | B37: 0.3 | C37: 0.15 | D37: 0.2 | E37: 0.1 | F37: 0.25 | G37: =SUM(B37:F37)
A41: Scenario | B41: Relative outcome achievability multiplier | C41: Parameter type | D41: Basis | E41: How used
A43: Operational Disruption | B43: 0.95 | C43: Structured expert prior | D43: Ordering directionally supported; exact magnitude not empirically estimated | E43: Multiplies actor S5 capability; centrally governed.
A44: Loss of Control or Visibility | B44: 0.85 | C44: Structured expert prior | D44: Ordering directionally supported; exact magnitude not empirically estimated | E44: Multiplies actor S5 capability; centrally governed.
A45: Process Manipulation | B45: 0.7 | C45: Structured expert prior | D45: Ordering directionally supported; exact magnitude not empirically estimated | E45: Multiplies actor S5 capability; centrally governed.
A46: Safety System Compromise | B46: 0.55 | C46: Structured expert prior | D46: Ordering directionally supported; exact magnitude not empirically estimated | E46: Multiplies actor S5 capability; centrally governed.
A47: Destructive or Integrity Attack | B47: 0.6 | C47: Structured expert prior | D47: Ordering directionally supported; exact magnitude not empirically estimated | E47: Multiplies actor S5 capability; centrally governed.
A51: Facility input | B51: Value option | C51: Multiplier | D51: Parameter type | E51: Status | F51: Rationale / how used
A53: IT_OT_CONNECTIVITY | B53: Yes | C53: 1.1 | D53: Calibration parameter | E53: Working prior | F53: Connected enterprise IT increases reachable attack surface.
A54: IT_OT_CONNECTIVITY | B54: No | C54: 0.9 | D54: Calibration parameter | E54: Working prior | F54: Reduced external attack surface.
A55: REMOTE_ACCESS | B55: None | C55: 0.85 | D55: Calibration parameter | E55: Working prior | F55: No remote-access route.
A56: REMOTE_ACCESS | B56: Controlled | C56: 1 | D56: Calibration parameter | E56: Reference | F56: Reference state.
A57: REMOTE_ACCESS | B57: Uncontrolled | C57: 1.25 | D57: Calibration parameter | E57: Working prior | F57: Weak/uncontrolled remote access increases opportunity.
A58: INTERNET_OT | B58: No | C58: 1 | D58: Calibration parameter | E58: Reference | F58: Reference state.
A59: INTERNET_OT | B59: Yes | C59: 1.3 | D59: Calibration parameter | E59: Working prior | F59: Internet exposure increases opportunity.
A60: TRANSIENT_ASSETS | B60: None | C60: 0.9 | D60: Calibration parameter | E60: Working prior | F60: Removes a common route.
A61: TRANSIENT_ASSETS | B61: Controlled | C61: 1 | D61: Calibration parameter | E61: Reference | F61: Reference state.
A62: TRANSIENT_ASSETS | B62: Unrestricted | C62: 1.2 | D62: Calibration parameter | E62: Working prior | F62: Increases removable/transient-device exposure.
A63: SUPPLY_CHAIN_ROUTE | B63: No | C63: 1 | D63: Model structure | E63: Neutral | F63: Supply-chain route affects TTP feasibility only; control quality is captured elsewhere.
A64: SUPPLY_CHAIN_ROUTE | B64: Yes | C64: 1 | D64: Model structure | E64: Neutral | F64: Supply-chain route affects TTP feasibility only; control quality is captured elsewhere.
... A66: WIRELESS_OT | B66: Yes | C66: 1 | D66: Model structure | E66: Neutral | F66: Wireless affects TTP feasibility only; secure presence does not automatically increase arrival frequency.
A71: Sector | B71: Nation State | C71: Cybercriminal | D71: Malicious Insider | E71: Basis / how used | F71: Calibration status | G71: Pack ID
A73: Power Generation | B73: 1 | C73: 1 | D73: 1 | E73: Reference sector; retained from validated V1.6/1.7 structure. | F73: Reference model working prior | G73: PG-v1.6
A74: Energy Assets | B74: 1.15 | C74: 1 | D74: 1 | E74: Nation-state uplift is an evidence-informed structured prior reflecting strategic energy targeting; no direct facility-year denominator is available. | F74: Working structured prior — controlled calibration | G74: EA-v1.0
A75: Manufacturing | B75: 0.85 | C75: 1.25 | D75: 1 | E75: Cybercriminal uplift reflects sustained ransomware concentration in manufacturing; raw victim shares are not used directly because sector denominators are unavailable. | F75: Working structured prior — controlled calibration | G75: MF-v1.0
A80: Country / region | B80: Nation State | C80: Cybercriminal | D80: Malicious Insider | E80: Basis / how used
A82: UAE / GCC | B82: 1 | C82: 1 | D82: 1 | E82: Canonical UAE/GCC row; neutral defaults pending evidence-led regional calibration.
A83: UK / Europe | B83: 1 | C83: 1 | D83: 1 | E83: Explicit row; neutral defaults pending evidence-led regional calibration.
A84: North America | B84: 1 | C84: 1 | D84: 1 | E84: Explicit row; neutral defaults pending evidence-led regional calibration.
A85: Other | B85: 1 | C85: 1 | D85: 1 | E85: Applied only when the user explicitly selects Other; never a silent fallback.

Sheet 4 Results and audit trail
A1: 4 Results and audit trail
A2: Python-populated calculations, decompositions, loss-exceedance data and domain-specific technical results.
A3: Results and audit trail. Calculated output — do not edit.
A4: Workbook tab | B4: Purpose | C4: Open
A5: 00 Output Bridge | B5: Model calculation / result | C5: =HYPERLINK("#'00 COMMON - Output Bridge'!A1","Open")
A6: 02 Executive Summary | B6: Model calculation / result | C6: =HYPERLINK("#'OT 02 - Executive Summary'!A1","Open")
A7: 14 TTP Relevance Calc | B7: Model calculation / result | C7: =HYPERLINK("#'OT CALC - TTP Relevance'!A1","Open")
A8: 15 Attack Path Calc | B8: Model calculation / result | C8: =HYPERLINK("#'OT CALC - Attack Path'!A1","Open")
A9: 16 Threat and Loss Frequency | B9: Model calculation / result | C9: =HYPERLINK("#'OT CALC - Threat Frequency'!A1","Open")
A10: 17 Consequence Calc | B10: Model calculation / result | C10: =HYPERLINK("#'OT CALC - Consequence'!A1","Open")
A11: 18 Actor-Scenario Matrix | B11: Model calculation / result | C11: =HYPERLINK("#'OT CALC - Actor-Scenario Matrix'!A1","Open")
A12: 19 Tail Risk Metrics | B12: Model calculation / result | C12: =HYPERLINK("#'OT CALC - Tail Risk Metrics'!A1","Open")
A13: 20 Control What-If | B13: Model calculation / result | C13: =HYPERLINK("#'OT CALC - Control What-If'!A1","Open")
A14: 21 Aggregate LECs | B14: Model calculation / result | C14: =HYPERLINK("#'OT CALC - Aggregate LECs'!A1","Open")
A15: 22 Scenario LECs | B15: Model calculation / result | C15: =HYPERLINK("#'OT CALC - Scenario LECs'!A1","Open")
A16: 23 Actor LECs | B16: Model calculation / result | C16: =HYPERLINK("#'OT CALC - Actor LECs'!A1","Open")
A17: 24 Actor-Scenario LEC Data | B17: Model calculation / result | C17: =HYPERLINK("#'OT CALC - Actor-Scenario LEC'!A1","Open")
A18: 25 Risk Charts | B18: Model calculation / result | C18: =HYPERLINK("#'OT CALC - Risk Charts'!A1","Open")
A19: IT 02 Executive Summary | B19: Model calculation / result | C19: =HYPERLINK("#'IT 02 - Executive Summary'!A1","Open")
A20: IT 10 TTP Relevance Calc | B20: Model calculation / result | C20: =HYPERLINK("#'IT CALC - TTP Relevance'!A1","Open")
A21: IT 11 Attack Path Calc | B21: Model calculation / result | C21: =HYPERLINK("#'IT CALC - Attack Path'!A1","Open")
A22: IT 12 Frequency and Success | B22: Model calculation / result | C22: =HYPERLINK("#'IT CALC - Frequency and Success'!A1","Open")
A23: IT 13 Consequence Calc | B23: Model calculation / result | C23: =HYPERLINK("#'IT CALC - Consequence'!A1","Open")
A24: IT 14 Actor Scenario Matrix | B24: Model calculation / result | C24: =HYPERLINK("#'IT CALC - Actor Scenario Matrix'!A1","Open")
A25: IT 15 Tail Risk Metrics | B25: Model calculation / result | C25: =HYPERLINK("#'IT CALC - Tail Risk Metrics'!A1","Open")
A26: IT 16 Control What-If | B26: Model calculation / result | C26: =HYPERLINK("#'IT CALC - Control What-If'!A1","Open")
A27: IT 17 Aggregate LECs | B27: Model calculation / result | C27: =HYPERLINK("#'IT CALC - Aggregate LECs'!A1","Open")
A28: IT 18 Scenario LECs | B28: Model calculation / result | C28: =HYPERLINK("#'IT CALC - Scenario LECs'!A1","Open")
A29: IT 19 Actor LECs | B29: Model calculation / result | C29: =HYPERLINK("#'IT CALC - Actor LECs'!A1","Open")
A30: IT 20 Risk Charts | B30: Model calculation / result | C30: =HYPERLINK("#'IT CALC - Risk Charts'!A1","Open")

Sheet 00 COMMON - Output Bridge
A1: COMMON OUTPUT BRIDGE — ENGINE / DASHBOARD CONTRACT
A2: Normalized interface used by the common dashboards. Formulas resolve directly to the selected IT or OT result tables.
A4: RUN IDENTITY
A5: Field | B5: Value
A6: Selected sector | B6: ='00 COMMON - Run Setup'!C6
A7: Model domain | B7: ='00 COMMON - Run Setup'!C7
A8: Asset type / scope | B8: ='00 COMMON - Run Setup'!C8
A9: Pack ID | B9: =IF(B7="IT",'IT 03 - Organisation Inputs'!C34,'OT 03 - Facility Inputs'!C32)
A10: Reporting basis | B10: ='00 COMMON - Run Setup'!C9
A13: NORMALIZED RISK METRICS
A14: Metric | B14: Best Estimate | C14: Prudent
A15: AAL | B15: =IF($B$7="IT",'IT 02 - Executive Summary'!B7,'OT 02 - Executive Summary'!L17) | C15: =IF($B$7="IT",'IT 02 - Executive Summary'!C7,'OT 02 - Executive Summary'!B17)
A16: VaR 95% | B16: =IF($B$7="IT",'IT 02 - Executive Summary'!B8,'OT 02 - Executive Summary'!L18) | C16: =IF($B$7="IT",'IT 02 - Executive Summary'!C8,'OT 02 - Executive Summary'!B18)
A17: TVaR 95% | B17: =IF($B$7="IT",'IT 02 - Executive Summary'!B9,'OT 02 - Executive Summary'!L19) | C17: =IF($B$7="IT",'IT 02 - Executive Summary'!C9,'OT 02 - Executive Summary'!B19)
A18: VaR 99% | B18: =IF($B$7="IT",'IT 02 - Executive Summary'!B10,'OT 02 - Executive Summary'!L20) | C18: =IF($B$7="IT",'IT 02 - Executive Summary'!C10,'OT 02 - Executive Summary'!B20)
A19: TVaR 99% | B19: =IF($B$7="IT",'IT 02 - Executive Summary'!B11,'OT 02 - Executive Summary'!L21) | C19: =IF($B$7="IT",'IT 02 - Executive Summary'!C11,'OT 02 - Executive Summary'!B21)
A20: P(any successful event) | B20: =IF($B$7="IT",'IT 02 - Executive Summary'!B18,'OT 02 - Executive Summary'!L28) | C20: =IF($B$7="IT",'IT 02 - Executive Summary'!C18,'OT 02 - Executive Summary'!B28)
A21: Campaign frequency / yr | B21: =IF($B$7="IT",'IT 02 - Executive Summary'!B20,'OT 02 - Executive Summary'!L37*'OT 02 - Executive Summary'!L38*'OT 02 - Executive Summary'!L39) | C21: =IF($B$7="IT",'IT 02 - Executive Summary'!C20,'OT 02 - Executive Summary'!B37*'OT 02 - Executive Summary'!B38*'OT 02 - Executive Summary'!B39*'OT 06 - Assessment Adjustments'!D17)
A22: Last simulation run | B22: =IF($B$7="IT",'IT 02 - Executive Summary'!B26,'OT 02 - Executive Summary'!L35) | C22: =IF($B$7="IT",'IT 02 - Executive Summary'!C26,'OT 02 - Executive Summary'!B35)
A25: ACTOR CONTRIBUTION
A26: Actor | B26: AAL | C26: Successful event frequency / yr
A27: =IF($B$7="IT",'IT 02 - Executive Summary'!A30,'OT CALC - Actor-Scenario Matrix'!A16) | B27: =IF($B$7="IT",'IT 02 - Executive Summary'!B30,SUM('OT CALC - Actor-Scenario Matrix'!B16:F16)) | C27: =IF($B$7="IT",'IT 02 - Executive Summary'!D30,SUM('OT CALC - Actor-Scenario Matrix'!B24:F24))
A28: =IF($B$7="IT",'IT 02 - Executive Summary'!A31,'OT CALC - Actor-Scenario Matrix'!A17) | B28: =IF($B$7="IT",'IT 02 - Executive Summary'!B31,SUM('OT CALC - Actor-Scenario Matrix'!B17:F17)) | C28: =IF($B$7="IT",'IT 02 - Executive Summary'!D31,SUM('OT CALC - Actor-Scenario Matrix'!B25:F25))
A29: =IF($B$7="IT",'IT 02 - Executive Summary'!A32,'OT CALC - Actor-Scenario Matrix'!A18) | B29: =IF($B$7="IT",'IT 02 - Executive Summary'!B32,SUM('OT CALC - Actor-Scenario Matrix'!B18:F18)) | C29: =IF($B$7="IT",'IT 02 - Executive Summary'!D32,SUM('OT CALC - Actor-Scenario Matrix'!B26:F26))
A30: =IF($B$7="IT",'IT 02 - Executive Summary'!A33,"") | B30: =IF($B$7="IT",'IT 02 - Executive Summary'!B33,"") | C30: =IF($B$7="IT",'IT 02 - Executive Summary'!D33,"")
A32: SCENARIO CONTRIBUTION
A33: Scenario | B33: AAL
A34: =IF($B$7="IT",'IT 02 - Executive Summary'!A37,'OT CALC - Actor-Scenario Matrix'!B15) | B34: =IF($B$7="IT",'IT 02 - Executive Summary'!B37,SUM('OT CALC - Actor-Scenario Matrix'!B16:B18))
A35: =IF($B$7="IT",'IT 02 - Executive Summary'!A38,'OT CALC - Actor-Scenario Matrix'!C15) | B35: =IF($B$7="IT",'IT 02 - Executive Summary'!B38,SUM('OT CALC - Actor-Scenario Matrix'!C16:C18))
A36: =IF($B$7="IT",'IT 02 - Executive Summary'!A39,'OT CALC - Actor-Scenario Matrix'!D15) | B36: =IF($B$7="IT",'IT 02 - Executive Summary'!B39,SUM('OT CALC - Actor-Scenario Matrix'!D16:D18))
A37: =IF($B$7="IT",'IT 02 - Executive Summary'!A40,'OT CALC - Actor-Scenario Matrix'!E15) | B37: =IF($B$7="IT",'IT 02 - Executive Summary'!B40,SUM('OT CALC - Actor-Scenario Matrix'!E16:E18))
A38: =IF($B$7="IT","",'OT CALC - Actor-Scenario Matrix'!F15) | B38: =IF($B$7="IT","",SUM('OT CALC - Actor-Scenario Matrix'!F16:F18))
A41: AGGREGATE LOSS-EXCEEDANCE DATA
A42: Exceedance probability | B42: Best AEP | C42: Best OEP | D42: Prudent AEP | E42: Prudent OEP
A43: =IF($B$7="IT",'IT CALC - Aggregate LECs'!B16,'OT CALC - Aggregate LECs'!A16) | B43: =IF($B$7="IT",'IT CALC - Aggregate LECs'!C16,'OT CALC - Aggregate LECs'!B16) | C43: =IF($B$7="IT",'IT CALC - Aggregate LECs'!D16,'OT CALC - Aggregate LECs'!C16) | D43: =IF($B$7="IT",'IT CALC - Aggregate LECs'!E16,'OT CALC - Aggregate LECs'!D16) | E43: =IF($B$7="IT",'IT CALC - Aggregate LECs'!F16,'OT CALC - Aggregate LECs'!E16)
A44: =IF($B$7="IT",'IT CALC - Aggregate LECs'!B17,'OT CALC - Aggregate LECs'!A17) | B44: =IF($B$7="IT",'IT CALC - Aggregate LECs'!C17,'OT CALC - Aggregate LECs'!B17) | C44: =IF($B$7="IT",'IT CALC - Aggregate LECs'!D17,'OT CALC - Aggregate LECs'!C17) | D44: =IF($B$7="IT",'IT CALC - Aggregate LECs'!E17,'OT CALC - Aggregate LECs'!D17) | E44: =IF($B$7="IT",'IT CALC - Aggregate LECs'!F17,'OT CALC - Aggregate LECs'!E17)
A45: =IF($B$7="IT",'IT CALC - Aggregate LECs'!B18,'OT CALC - Aggregate LECs'!A18) | B45: =IF($B$7="IT",'IT CALC - Aggregate LECs'!C18,'OT CALC - Aggregate LECs'!B18) | C45: =IF($B$7="IT",'IT CALC - Aggregate LECs'!D18,'OT CALC - Aggregate LECs'!C18) | D45: =IF($B$7="IT",'IT CALC - Aggregate LECs'!E18,'OT CALC - Aggregate LECs'!D18) | E45: =IF($B$7="IT",'IT CALC - Aggregate LECs'!F18,'OT CALC - Aggregate LECs'!E18)
A46: =IF($B$7="IT",'IT CALC - Aggregate LECs'!B19,'OT CALC - Aggregate LECs'!A19) | B46: =IF($B$7="IT",'IT CALC - Aggregate LECs'!C19,'OT CALC - Aggregate LECs'!B19) | C46: =IF($B$7="IT",'IT CALC - Aggregate LECs'!D19,'OT CALC - Aggregate LECs'!C19) | D46: =IF($B$7="IT",'IT CALC - Aggregate LECs'!E19,'OT CALC - Aggregate LECs'!D19) | E46: =IF($B$7="IT",'IT CALC - Aggregate LECs'!F19,'OT CALC - Aggregate LECs'!E19)
A47: =IF($B$7="IT",'IT CALC - Aggregate LECs'!B20,'OT CALC - Aggregate LECs'!A20) | B47: =IF($B$7="IT",'IT CALC - Aggregate LECs'!C20,'OT CALC - Aggregate LECs'!B20) | C47: =IF($B$7="IT",'IT CALC - Aggregate LECs'!D20,'OT CALC - Aggregate LECs'!C20) | D47: =IF($B$7="IT",'IT CALC - Aggregate LECs'!E20,'OT CALC - Aggregate LECs'!D20) | E47: =IF($B$7="IT",'IT CALC - Aggregate LECs'!F20,'OT CALC - Aggregate LECs'!E20)
A48: =IF($B$7="IT",'IT CALC - Aggregate LECs'!B21,'OT CALC - Aggregate LECs'!A21) | B48: =IF($B$7="IT",'IT CALC - Aggregate LECs'!C21,'OT CALC - Aggregate LECs'!B21) | C48: =IF($B$7="IT",'IT CALC - Aggregate LECs'!D21,'OT CALC - Aggregate LECs'!C21) | D48: =IF($B$7="IT",'IT CALC - Aggregate LECs'!E21,'OT CALC - Aggregate LECs'!D21) | E48: =IF($B$7="IT",'IT CALC - Aggregate LECs'!F21,'OT CALC - Aggregate LECs'!E21)
A49: =IF($B$7="IT",'IT CALC - Aggregate LECs'!B22,'OT CALC - Aggregate LECs'!A22) | B49: =IF($B$7="IT",'IT CALC - Aggregate LECs'!C22,'OT CALC - Aggregate LECs'!B22) | C49: =IF($B$7="IT",'IT CALC - Aggregate LECs'!D22,'OT CALC - Aggregate LECs'!C22) | D49: =IF($B$7="IT",'IT CALC - Aggregate LECs'!E22,'OT CALC - Aggregate LECs'!D22) | E49: =IF($B$7="IT",'IT CALC - Aggregate LECs'!F22,'OT CALC - Aggregate LECs'!E22)
A50: =IF($B$7="IT",'IT CALC - Aggregate LECs'!B23,'OT CALC - Aggregate LECs'!A23) | B50: =IF($B$7="IT",'IT CALC - Aggregate LECs'!C23,'OT CALC - Aggregate LECs'!B23) | C50: =IF($B$7="IT",'IT CALC - Aggregate LECs'!D23,'OT CALC - Aggregate LECs'!C23) | D50: =IF($B$7="IT",'IT CALC - Aggregate LECs'!E23,'OT CALC - Aggregate LECs'!D23) | E50: =IF($B$7="IT",'IT CALC - Aggregate LECs'!F23,'OT CALC - Aggregate LECs'!E23)
A51: =IF($B$7="IT",'IT CALC - Aggregate LECs'!B24,'OT CALC - Aggregate LECs'!A24) | B51: =IF($B$7="IT",'IT CALC - Aggregate LECs'!C24,'OT CALC - Aggregate LECs'!B24) | C51: =IF($B$7="IT",'IT CALC - Aggregate LECs'!D24,'OT CALC - Aggregate LECs'!C24) | D51: =IF($B$7="IT",'IT CALC - Aggregate LECs'!E24,'OT CALC - Aggregate LECs'!D24) | E51: =IF($B$7="IT",'IT CALC - Aggregate LECs'!F24,'OT CALC - Aggregate LECs'!E24)
A52: =IF($B$7="IT",'IT CALC - Aggregate LECs'!B25,'OT CALC - Aggregate LECs'!A25) | B52: =IF($B$7="IT",'IT CALC - Aggregate LECs'!C25,'OT CALC - Aggregate LECs'!B25) | C52: =IF($B$7="IT",'IT CALC - Aggregate LECs'!D25,'OT CALC - Aggregate LECs'!C25) | D52: =IF($B$7="IT",'IT CALC - Aggregate LECs'!E25,'OT CALC - Aggregate LECs'!D25) | E52: =IF($B$7="IT",'IT CALC - Aggregate LECs'!F25,'OT CALC - Aggregate LECs'!E25)
A53: =IF($B$7="IT",'IT CALC - Aggregate LECs'!B26,'OT CALC - Aggregate LECs'!A26) | B53: =IF($B$7="IT",'IT CALC - Aggregate LECs'!C26,'OT CALC - Aggregate LECs'!B26) | C53: =IF($B$7="IT",'IT CALC - Aggregate LECs'!D26,'OT CALC - Aggregate LECs'!C26) | D53: =IF($B$7="IT",'IT CALC - Aggregate LECs'!E26,'OT CALC - Aggregate LECs'!D26) | E53: =IF($B$7="IT",'IT CALC - Aggregate LECs'!F26,'OT CALC - Aggregate LECs'!E26)

Sheet OT 02 - Executive Summary
A1: 02 — Executive Risk Summary
A2: Purpose: Present facility-level financial risk, operational impact, actor/scenario decomposition, risk-financing metrics and the composite five-stage attack-path model.
A3: In plain English: this is the decision view. AAL and control what-ifs support security investment; selected TVaR less retention supports tail-risk transfer decisions.
A4: SHEET TYPE: MODEL RESULT
A5: Inputs / upstream sources
A6: 500,000-year Python simulation using all model inputs, mappings and assumptions.
A7: Calculation / decision logic
A8: AAL = mean(Annual Aggregate Loss). VaR95/99 = annual-loss percentiles. TVaR = mean annual loss at or beyond the VaR threshold. P(any event) = simulated years with ≥1 successful loss event / 100,000. Actor and scenario AAL shares reconcile to facility AAL; actor/scenario VaR and TVaR are not additive.
A9: Key assumptions / defaults
A10: AEP is annual aggregate loss. OEP is the largest single event in a simulated year. Actor/scenario AAL decompositions should reconcile exactly to facility AAL within numerical tolerance. VaR and TVaR on those rows are each row's own annual distribution.
A11: Outputs / downstream use
A12: Primary executive output; links conceptually to 18 matrix, 19 tail metrics and 21–24 loss exceedance curves.
... A15: FINANCIAL RISK
A16: Metric | B16: Prudent | C16: Meaning | L16: Best Estimate
A17: AAL | B17: 1935743 | C17: Mean annual aggregate financial loss (expected value). | L17: 1323497.8
A18: VaR 95% | B18: 924397.25 | C18: 95th percentile of annual aggregate loss. | L18: 0
A19: TVaR 95% | B19: 38708768 | C19: Mean of the worst 5% of simulated annual losses (Expected Shortfall). | L19: 26469955
A20: VaR 99% | B20: 50166814 | C20: 99th percentile of annual aggregate loss. | L20: 34846255
A21: TVaR 99% | B21: 1.282283e+08 | C21: Mean of the worst 1% of simulated annual losses (Expected Shortfall). | L21: 1.0062604e+08
A22: Selected TVaR | B22: 1.282283e+08 | C22: Tail basis selected on 19 Tail Risk Metrics: TVaR 99%. | L22: 1.0062604e+08
A23: Insurance retention | B23: 0 | C23: Amount deliberately retained by the organisation. | L23: 0
A24: Tail loss to transfer above retention | B24: 1.282283e+08 | C24: Selected TVaR minus retention, floored at zero; indicative insurance limit, not expected loss above retention. | L24: 1.0062604e+08
A26: OPERATIONAL IMPACT
A27: Metric | B27: Prudent | C27: Meaning | L27: Best Estimate
A28: P(any successful loss event) | B28: 0.05048 | C28: Share of years with at least one successful loss event. | L28: 0.034304
A29: Mean annual downtime (hours) | B29: 8.9998043 | C29: Expected hours per year including zero-event years. | L29: 6.1289234
A30: Mean downtime | successful year (hours) | B30: 178.28455 | C30: Mean hours in years with at least one successful event. | L30: 178.66498
A31: TVaR 95% downtime (hours) | B31: 179.94664 | C31: Mean downtime in the worst 5% of simulated years. | L31: 122.57847
A33: RUN CONTEXT
A34: Metric | B34: Prudent | C34: Meaning | L34: Best Estimate
A35: Last simulation run | B35: 2026-08-19 12:42 | C35: Timestamp when the Python engine refreshed the workbook. | L35: 2026-08-19 12:42
A36: Simulation years | B36: 500000 | C36: Number of simulated facility-years per reporting basis and per control what-if. | L36: 500000
A37: Reference campaign rate | B37: 0.55 | C37: Centrally governed material-campaign arrival-rate prior before modifiers. | L37: 0.55
A38: Facility exposure multiplier | B38: 1.1 | C38: Combined IT/OT, remote-access, internet-OT and transient-asset exposure factor; supply-chain and wireless are feasibility-only. | L38: 1.1
A39: Threat intensity multiplier | B39: 1 | C39: Σ(Actor Share × Threat Activity × Sector × Asset Type × Geography). Each overlay is applied exactly once. | L39: 1
A40: Selected sector | B40: Power Generation | C40: Sector selected on 03 Facility Inputs; one facility/site is the unit of analysis. | L40: Power Generation
A41: Selected asset type | B41: CCGT | C41: Asset calibration: Reference model working prior. | L41: CCGT
A42: Resolved pack ID | B42: PG-v1.6 | C42: Exactly one registered pack from 28 Sector Pack Registry. | L42: PG-v1.6
A43: Pack calibration status
A44: Simulated campaign rate | B44: 0.906584 | C44: Average Poisson campaign count after all frequency modifiers. | L44: 0.60635
A45: Prudence factor | B45: 1.5 | C45: Applied only to frequency. Reporting selection: Both; detailed result sheets use Prudent. | L45: 1
A47: Decompositions use the Prudent annual loss distribution (detailed basis when reporting is Both). AAL shares sum to facility AAL. VaR and TVaR are each row's own annual distribution and do not add to the facility totals. Best Estimate is in hidden column L; unhide column L to compare with Prudent.
A49: THREAT ACTOR DECOMPOSITION · Prudent
A50: Threat actor | B50: AAL | C50: VaR 95% | D50: TVaR 95% | E50: VaR 99% | F50: TVaR 99% | G50: Attempts / yr | H50: Events / yr | I50: P(success) | J50: AAL share | K50: Rank
A51: Cybercriminal | B51: 1102563.7 | C51: 0 | D51: 22051275 | E51: 29383434 | F51: 84017400 | G51: 0.681216 | H51: 0.033176 | I51: 0.04947336 | J51: 0.56958169 | K51: 1
A52: Nation State | B52: 556851.86 | C52: 0 | D52: 11137037 | E52: 6510374.9 | F52: 54709926 | G52: 0.180244 | H52: 0.012746 | I52: 0.070898187 | J52: 0.28766828 | K52: 2
A53: Malicious Insider | B53: 276327.37 | C53: 0 | D53: 5526547.3 | E53: 0 | F53: 27632737 | G53: 0.045124 | H53: 0.005856 | I53: 0.12949257 | J53: 0.14275003 | K53: 3
A56: SCENARIO DECOMPOSITION · Prudent
A57: Scenario | B57: AAL | C57: VaR 95% | D57: TVaR 95% | E57: VaR 99% | F57: TVaR 99% | G57: Attempts / yr | H57: Events / yr | I57: P(success) | J57: AAL share | K57: Rank
A58: Operational Disruption | B58: 812442.68 | C58: 0 | D58: 16248854 | E58: 24334738 | F58: 59102890 | G58: 0.535944 | H58: 0.031962 | I58: 0.06031968 | J58: 0.41970587 | K58: 1
A59: Destructive or Integrity Attack | B59: 613047.7 | C59: 0 | D59: 12260954 | E59: 0 | F59: 61304770 | G59: 0.135498 | H59: 0.005608 | I59: 0.041891688 | J59: 0.31669892 | K59: 2
A60: Process Manipulation | B60: 226518.06 | C60: 0 | D60: 4530361.3 | E60: 0 | F60: 22651806 | G60: 0.087954 | H60: 0.004884 | I60: 0.056832935 | J60: 0.11701867 | K60: 3
A61: Safety System Compromise | B61: 165049.02 | C61: 0 | D61: 3300980.3 | E61: 0 | F61: 16504902 | G61: 0.045402 | H61: 0.002318 | I61: 0.052083214 | J61: 0.085263911 | K61: 4
A62: Loss of Control or Visibility | B62: 118685.51 | C62: 0 | D62: 2373710.2 | E62: 0 | F62: 11868551 | G62: 0.101786 | H62: 0.007006 | I62: 0.068345976 | J62: 0.061312639 | K62: 5
A65: ASSUMED ATTACK PATH
A66: The model does not assume one named intrusion. Each simulated campaign draws a threat actor and an adverse scenario, then tests whether that actor can complete a five-stage ATT&CK for ICS path against this facility. A successful loss event occurs only if every required stage is passed. Prevent/resist controls are stage barriers; detect/contain and recover/restore change how long and how costly a successful event is, not whether the path succeeds. Facility topology (remote access, IT-OT connectivity, internet-exposed OT, transient assets, supply chain, wireless, safety systems) can close techniques before the path is quantified. Stage-by-stage probabilities are on 15 Attack Path Calc.
A68: Stage | B68: Name | C68: What the adversary does | E68: Modelling note
A69: S1 | B69: Initial access | C69: Gain a foothold from outside (remote access, internet-exposed OT, supply chain, or transient media). | E69: Required except for Malicious Insider, who is already inside.
A70: S2 | B70: Establish presence | C70: Persist, escalate privilege, execute code, and evade detection on the compromised system. | E70: Required for all actors.
A71: S3 | B71: Move into OT | C71: Lateral movement and command-and-control to reach process-adjacent systems. | E71: Required for all actors.
A72: S4 | B72: Understand the process | C72: Discovery and collection of OT/process information needed to cause the intended harm. | E72: Required for all actors.
A73: S5 | B73: Achieve the adverse outcome | C73: Impact, impair process control, or inhibit response — the scenario-defining techniques. | E73: Requires at least one scenario-defining technique. Actor S5 capability × scenario difficulty.

Sheet IT 02 - Executive Summary
A1: 02 — Executive Risk Summary
A2: Python-populated organisation-level risk metrics, decompositions and run context.
A5: FINANCIAL RISK
A6: Metric | B6: Best Estimate | C6: Prudent | D6: Meaning
A7: AAL | B7: 1059877.3 | C7: 1311679.4 | D7: Mean annual aggregate financial loss.
A8: VaR 95% | B8: 5487402.5 | C8: 7125948 | D8: 95th percentile annual aggregate loss.
A9: TVaR 95% | B9: 18021076 | C9: 20885315 | D9: Mean annual loss in the worst 5% of years.
A10: VaR 99% | B10: 22824448 | C10: 26218159 | D10: 99th percentile annual aggregate loss.
A11: TVaR 99% | B11: 46179340 | C11: 51675145 | D11: Mean annual loss in the worst 1% of years.
A12: Selected TVaR | B12: 46179340 | C12: 51675145 | D12: Tail metric selected on 08.
A13: Insurance retention | B13: 0 | C13: 0 | D13: Organisation-selected retention.
A14: Tail loss above retention | B14: 46179340 | C14: 51675145 | D14: Selected TVaR less retention, floored at zero.
A16: EVENT AND RUN CONTEXT
A17: Metric | B17: Best Estimate | C17: Prudent | D17: Meaning
A18: P(any successful event) | B18: 0.114878 | C18: 0.140772
A19: Successful events / year | B19: 0.12094386 | C19: 0.15117983
A20: Material campaigns / year | B20: 1 | C20: 1.25
A21: Use exposure adjustments? | B21: No | C21: No
A22: Sector | B22: Financial Services | C22: Financial Services
A23: Resolved pack ID | B23: FS-v1.1.1 | C23: FS-v1.1.1
A24: Pack status | B24: Development — working priors; calibration required | C24: Development — working priors; calibration required
A25: Simulation years | B25: 500000 | C25: 500000
A26: Last run | B26: 2026-08-21 10:19 UTC | C26: 2026-08-21 10:19 UTC
A28: THREAT-ACTOR DECOMPOSITION
A29: Threat actor | B29: AAL | C29: Attempts / yr | D29: Events / yr | E29: P(success) | F29: AAL share | G29: 1-in-20 AEP | H29: 1-in-100 AEP
A30: Nation-state | B30: 119201.14 | C30: 0.15 | D30: 0.013632509 | E30: 0.090883393 | F30: 0.09087674 | G30: 0 | H30: 2412035.6
A31: Cybercriminal | B31: 651035.53 | C31: 0.85 | D31: 0.076702191 | E31: 0.090237872 | F31: 0.49633741 | G31: 2309382.9 | H31: 16138275
A32: Malicious insider | B32: 301385.84 | C32: 0.125 | D32: 0.036279943 | E32: 0.29023954 | F32: 0.22977097 | G32: 0 | H32: 8325961.9
A33: Hacktivist | B33: 240056.84 | C33: 0.125 | D33: 0.024565183 | E33: 0.19652146 | F33: 0.18301488 | G33: 0 | H33: 6353896.7
A35: SCENARIO DECOMPOSITION
A36: Scenario | B36: AAL | C36: Attempts / yr | D36: Events / yr | E36: P(success) | F36: AAL share | G36: 1-in-20 AEP | H36: 1-in-100 AEP
A37: Critical business-service disruption | B37: 575998.21 | C37: 0.41125 | D37: 0.051753306 | E37: 0.1258439 | F37: 0.43913035 | G37: 421378.54 | H37: 15039969
A38: Sensitive-data compromise | B38: 292163.99 | C38: 0.32125 | D38: 0.025781651 | E38: 0.080254165 | F38: 0.2227404 | G38: 0 | H38: 8461016.1
A39: Data or transaction-integrity compromise | B39: 183681.88 | C39: 0.17125 | D39: 0.019789662 | E39: 0.11556007 | F39: 0.14003565 | G39: 0 | H39: 5108821.5
A40: Cyber-enabled theft or fraud | B40: 259835.28 | C40: 0.34625 | D40: 0.053855207 | E40: 0.1555385 | F40: 0.1980936 | G40: 355893.83 | H40: 6844977.2
A42: TOP CONTROL WHAT-IFS
A43: Control | B43: Current maturity | C43: What-if maturity | D43: Current AAL | E43: What-if AAL | F43: AAL reduction
A44: Privileged access management | B44: Developing | C44: Managed | D44: 1308717.6 | E44: 1200150.2 | F44: 108567.33
A45: DDoS protection and service resilience | B45: Developing | C45: Managed | D45: 1308717.6 | E45: 1214101.7 | F45: 94615.903
A46: Payment and fraud controls | B46: Developing | C46: Managed | D46: 1308717.6 | E46: 1228605.4 | F46: 80112.178
A47: Data protection and DLP | B47: Developing | C47: Managed | D47: 1308717.6 | E47: 1232571 | F47: 76146.594
A48: Identity, authentication and MFA | B48: Developing | C48: Managed | D48: 1308717.6 | E48: 1236947.2 | F48: 71770.39

Sheet 5 Advanced - Governed
A1: 5 Advanced - Governed
A2: Method guides, source evidence, validation, change logs and the outside-in adjustment audit trail.
A3: Advanced / Governed. Read Only. Not required to complete an assessment.
A4: Workbook tab | B4: Purpose | C4: Open
A5: 01 Model Guide | B5: Documentation / governance | C5: =HYPERLINK("#'OT CORE - Model Guide'!A1","Open")
A6: 10 Mapping Change Log | B6: Documentation / governance | C6: =HYPERLINK("#'OT CORE - Mapping Change Log'!A1","Open")
A7: 26 Sources and Evidence | B7: Documentation / governance | C7: =HYPERLINK("#'OT 26 - Sources and Evidence'!A1","Open")
A8: 27 Validation Tests | B8: Documentation / governance | C8: =HYPERLINK("#'OT 27 - Validation Tests'!A1","Open")
A9: 00 OI Adjustment Rationale | B9: Documentation / governance | C9: =HYPERLINK("#'00 COMMON - OI Audit Trail'!A1","Open")
A10: IT 01 Model Guide | B10: Documentation / governance | C10: =HYPERLINK("#'IT CORE - Model Guide'!A1","Open")
A11: IT 21 Sources and Evidence | B11: Documentation / governance | C11: =HYPERLINK("#'IT 21 - Sources and Evidence'!A1","Open")
A12: IT 22 Validation Tests | B12: Documentation / governance | C12: =HYPERLINK("#'IT 22 - Validation Tests'!A1","Open")

Sheet IT CORE - Model Guide
A1: Guided IT Cyber Risk Quantification — v1.1.1
A2: Organisation-level IT-CRQ model with modular, pack-driven workbook geometry.
A4: SHEET TYPE: MODEL DOCUMENTATION
A6: Purpose
A7: Quantify annual financial loss for an organisation across four actors, four loss scenarios and six composite attack routes.
A9: Calculation / decision logic
A10: Campaign frequency is separated from conditional attack-path success. Enterprise ATT&CK techniques are filtered by actor, scenario and route; controls adjust stage-through probabilities relative to a reference profile. Scenario losses use transparent P50/P99 impact drivers and a Monte Carlo annual-loss simulation.
A12: Outputs / downstream use
A13: AAL, VaR, TVaR, AEP/OEP loss-exceedance curves, actor/scenario decompositions, control what-if reductions and an interactive dashboard suite.
A15: Workbook convention
A16: Yellow cells with blue font are editable. Engine results and resolved pack values are not manually editable.
A20: MODEL FLOW
A21: 1 | B21: Select sector and organisation inputs | C21: 03 Organisation Inputs
A22: 2 | B22: Choose whether to apply IT Exposure Adjustment Model recommendations | C22: 03 and 04
A23: 3 | B23: Assess NIST CSF 2.0-aligned control families | C23: 05 Control Assessment
A24: 4 | B24: Review organisation-scale impact inputs and pack-derived BIA drivers | C24: 06 Impact and BIA
A25: 5 | B25: Python loads and validates the selected sector-pack workbook | C25: 09 Sector Pack Registry
A26: 6 | B26: Engine evaluates actor × scenario × route × TTP relevance and composite stages | C26: 10–12
A27: 7 | B27: Engine simulates annual aggregate and occurrence losses | C27: 13–19
A28: 8 | B28: Review interactive dashboards, executive results, curves, what-ifs and validation | C28: 00 Dashboard suite; 02, 15–22
A30: IMPORTANT LIMITATIONS
A31: Frequency and sector calibration values are development working priors and require approval before external reliance.
A32: The model excludes pure intellectual-property theft as a loss scenario.
A33: Ransomware, DDoS, phishing, account takeover and supply-chain compromise are mechanisms/routes, not separate financial-loss scenarios.
A34: When the exposure-adjustment switch is No, all exposure-model factors are neutral; organisation route-applicability inputs still apply.
A35: Asset and vulnerability records are not ingested by this CRQ workbook. A separate evidence model recommends governed route/stage factors for sheet 04.

Sheet OT CORE - Model Guide
A1: 01 — Model Guide | Guided OT-CRQ v1.8 (multi-sector, facility-level)
A2: Purpose: Explain the model workflow, sheet categories, engine boundary, and how to review the model from inputs through results.
A3: In plain English: select a facility sector and asset type, complete controls and BIA, review the common mappings plus sector rationale, run the compatible Python engine, then review calculations, results, curves and validation.
A4: SHEET TYPE: MODEL GUIDE
A5: Inputs / upstream sources
A6: All workbook sheets plus the ot-crq Python package (run_simulation.command / .bat / Run_OT_CRQ_Simulation.app).
A7: Calculation / decision logic
A8: The workbook is the transparent input / audit / reporting layer. Python performs the 500,000-year stochastic simulation and writes calculation outputs back into Excel.
A9: Key assumptions / defaults
A10: One common OT engine covers Power Generation, Energy Assets and Manufacturing at facility level. V1.8 formalises three governed sector packs: sector threat/frequency context, sector-specific scenario/BIA starting points, TTP emphasis/rationale and assessment evidence requirements; the composite stage-barrier method and common 18-driver BIA are retained.
A11: Outputs / downstream use
A12: Provides navigation and governance context; no numerical risk calculation is performed on this sheet.
A13: Workbook convention: yellow cells / blue font are editable inputs or calibration assumptions; engine-output cells are not manually editable.
A15: Step | B15: Model stage | C15: What the user / model does | D15: Sheets | E15: Category colour | F15: Primary output | G15: Edit? | H15: Notes
A16: 1 | B16: Define facility | C16: Select sector/asset type and describe facility architecture | D16: 03, 28 | E16: Blue | F16: Facility context / feasibility | G16: Yes | H16: Facility characteristics gate TTPs and calibrate exposure.
A17: 2 | B17: Assess controls | C17: Assess maturity, coverage and supporting evidence | D17: 04 | E17: Blue | F17: Maturity / coverage | G17: Yes | H17: Implementation quality is maturity; no separate implementation-quality score.
A18: 3 | B18: Set consequence inputs | C18: Enter facility economics and the common Base/Stress BIA assumptions | D18: 05 | E18: Blue | F18: Loss severity assumptions | G18: Yes | H18: Base = median; Stress = configured upper percentile.
A19: 4 | B19: Calibrate likelihood | C19: Set campaign, actor, scenario, stage and facility/sector/region priors | D19: 06–07, 28 | E19: Amber | F19: Likelihood priors | G19: Calibration | H19: Do not tune merely to reach a preferred AAL.
A20: 4 | B20: Calibrate likelihood | C20: Set campaign, actor, scenario, stage and facility/sector/region priors; review sector pack frequency overlay | D20: 06–07, 28, 30–33 | E20: Amber | F20: Likelihood priors | G20: Calibration | H20: Sector multipliers are working priors unless marked reference; do not tune to reach a preferred AAL.
A21: 5 | B21: Review attack-path mappings | C21: Review scenario, actor, facility, sector and TTP-control mappings plus sector TTP emphasis | D21: 09–14, 29–33 | E21: Purple | F21: Relevant attack path | G21: Calibration | H21: ATT&CK supplies taxonomy / mitigation relationships; sector packs add governed context rather than bespoke hidden paths.
A22: 7 | B22: Trace calculations | C22: Review TTP relevance, stage barriers, frequency and consequence build-up | D22: 14–17 | E22: Teal | F22: P(success), LEF, event severity | G22: No | H22: Values are engine outputs; equations are documented on each sheet.
A23: 8 | B23: Review results | C23: Review AAL, tail risk, matrices and what-if analysis | D23: 02, 18–20 | E23: Green | F23: Risk metrics | G23: No | H23: Actor/scenario decompositions reconcile to facility AAL.
A24: 9 | B24: Review LECs | C24: Review aggregate, scenario, actor and actor-scenario Loss Exceedance Curves (LECs) | D24: 21–24 | E24: Green | F24: LECs: AEP / OEP | G24: No | H24: AEP is the primary annual aggregate-loss LEC; OEP is the single-occurrence LEC.
A25: 10 | B25: Review charts & QA | C25: Review visuals, evidence register and automated validation | D25: 25–27 | E25: Green/Grey/Orange | F25: Handover QA | G25: No | H25: Treat the run as valid only when validation passes.
A28: CALCULATION ENGINE BOUNDARY
A29: Deterministic Excel links | B29: TTP/actor/facility/sector filtering, composite control-barrier aggregation, attack-path probability, best-estimate and prudent frequency simulation, common OT BIA, AAL, VaR/TVaR, AEP/OEP LECs and control what-ifs.
A30: Python engine | B30: TTP/actor/facility filtering, control-barrier aggregation, attack-path probability, best-estimate and prudent campaign-frequency simulation, driver-built OT impact, revenue-based BI, AAL, VaR/TVaR, AEP/OEP LECs and 100k control what-ifs.
A31: Last complete engine run in attached baseline: 2026-08-19 10:33 | Power Generation / CCGT | 500,000 years per view | Validation: PASS. Rerun with a compatible engine after sector or input changes. | B31: ot-crq CLI / run_simulation.command|.bat / Run_OT_CRQ_Simulation.app — run after changing model inputs. Prefer a copy under assessments/.
A32: Last complete engine run: 2026-08-19 12:42 | 500,000 years per view | Reporting: Both | Detailed basis: Prudent | Validation: PASS
A34: VERSION HISTORY
A35: v1.7 | B35: 2026-08-19 | C35: Three explicit sector packs; asset-type frequency overlay and calibration status | D35: Retains the common 18-driver V1.6 BIA; OP-02 wording generalised | E35: Unchanged | F35: Pack, asset and sector-TTP validation added; stochastic results remain the attached V1.6 PG baseline until rerun
A36: Version | B36: Date | C36: Frequency | D36: Impact / BIA | E36: Insurance | F36: Validation
A37: v1.6 | B37: 2026-08-18 | C37: Retains v1.5 0.55 reference λ and 1.50× frequency-only prudence | D37: Editable OT cost-driver matrix; unit-rate/quantity equations; 100% BI factor default; scenario calibration | E37: Selectable TVaR95/99 less retention | F37: 500,000 years per view; 45 automated checks
A38: v1.5 | B38: 2026-08-18 | C38: 0.55 reference λ; 1.50× prudence; success sigma removed | D38: Revenue-based BI plus manually entered aggregate non-BI components | E38: Selectable TVaR95/99 less retention | F38: 39 automated checks
A39: v1.8 | B39: 2026-08-23 | C39: Formalised PG / Energy Assets / Manufacturing sector packs; evidence-informed sector actor overlays and pack-specific BIA starting points | D39: Common 18-driver BIA retained; manufacturing quality/WIP extension flagged as optional | E39: Unchanged | F39: Workbook content updated; stochastic outputs must be rerun with a compatible engine before production use

Sheet OT CORE - Control Method
A1: 07 — Control Model Assumptions
A2: Purpose: Define the maturity factors, default coverage, control-barrier aggregation rules and causal control channels used by the model.
A3: In plain English: this sheet converts the maturity judgement into a simple implementation factor and defines the reference security state used to compare actual controls with the baseline.
A4: SHEET TYPE: MODEL ASSUMPTIONS / CALIBRATION
A5: Inputs / upstream sources
A6: Core control-model design established in earlier versions and retained in v1.4. Values are calibration/model-structure assumptions, not empirical effectiveness claims.
A7: Calculation / decision logic
A8: Maturity is implementation quality. Not Assessed → Developing. Applied TTP-control efficacy = Base Efficacy × Maturity Factor × Coverage. Reference barriers use Developing maturity and 75% coverage. Multiple controls on the same TTP receive diminishing incremental credit; stage barriers use equal weighting across TTPs.
A9: Key assumptions / defaults
A10: No global effectiveness tier. Optimised = 0.95 rather than perfect 1.00. Coverage is separate from maturity. Scenario-defining TTPs are not given arbitrary 2× barrier weight.
A11: Outputs / downstream use
A12: Feeds 04 Control Assessment, 13 TTP-Control Map, 15 Attack Path Calc and consequence control factors.
A13: Workbook convention: yellow cells / blue font are editable inputs or calibration assumptions; engine-output cells are not manually editable.
A15: Maturity level | B15: Maturity factor | C15: Definition / assessment anchor
A16: Absent | B16: 0 | C16: Control is absent or materially non-functional.
A17: Initial | B17: 0.25 | C17: Control exists, but design/operation is inconsistent and significant weaknesses remain.
A18: Developing | B18: 0.5 | C18: Control design is broadly appropriate and routinely operated, but execution is inconsistent and effectiveness evidence is limited.
A19: Managed | B19: 0.75 | C19: Control is consistently operated and monitored; exceptions are actively managed and effectiveness is supported by evidence.
A20: Optimised | B20: 0.95 | C20: Control is continuously monitored/tested and demonstrates sustained operational effectiveness; no control is assumed perfect.
A24: Parameter | B24: Value | C24: Parameter type | D24: How used
A26: BASELINE_MATURITY_LEVEL | B26: Developing | C26: Model structure | D26: Reference state and default for Not Assessed.
A27: DEFAULT_COVERAGE | B27: 0.75 | C27: Model default | D27: Used when a control-specific coverage value is blank.
A28: AGG_INCREMENT | B28: 0.25 | C28: Model structure / calibration | D28: Strongest distinct control on a TTP receives full credit; later controls receive diminishing incremental credit.
A29: ADJ_FLOOR | B29: 0.4 | C29: Model bound | D29: Minimum residual-risk adjustment vs reference controls.
A30: ADJ_CEILING | B30: 2 | C30: Model bound | D30: Maximum residual-risk adjustment vs reference controls.
A31: DUR_FLOOR | B31: 0.4 | C31: Model bound | D31: Detect × Recover cannot reduce outage below this factor of reference duration.
A32: CONSEQ_FLOOR | B32: 0.4 | C32: Model bound | D32: Recover/Safety controls cannot reduce non-BI consequence below this factor.
A33: CONSEQ_CEILING | B33: 2 | C33: Model bound | D33: Weak Recover/Safety controls cannot increase non-BI consequence above this factor.
A34: DEFAULT_TTP_CONTROL_BASE_EFFICACY | B34: 0.8 | C34: Working prior / seed only | D34: Current seed/reference value for non-excluded TTP-control mappings. Row-level Base Efficacy on 13 is the value actually used and remains editable relationship by relationship.
A38: SEVERITY MODEL SETTINGS
A40: Parameter | B40: Value | C40: Parameter type | D40: How used
A41: STRESS_Z | B41: 2.3263479 | C41: Severity convention | D41: P50/P99 inputs fit the conditional lognormal severity distributions.
A42: LOSS_DOWNTIME_RHO | B42: 0.75 | C42: Dependence parameter | D42: Gaussian-copula correlation between downtime and aggregate non-BI severity.
A43: Safety / Resilience | B43: Changes physical/safety consequence-sensitive non-BI costs.

Sheet OT CORE - Scenario Definitions
A1: 08 — Common OT Adverse Scenario Definitions (multi-sector v1.8)
A2: Narrative definition of each adverse scenario. These are deliberately sector-agnostic so the engine remains common across Power Generation, Energy Assets and Manufacturing; sector packs on 30–32 provide sector-specific interpretation and BIA starting points.
A3: In plain English: what each of the five bad outcomes actually means, in one sentence each.
A5: Scenario | B5: Common OT definition | C5: Defining TTPs | D5: Supporting TTPs | E5: Enabling TTPs
A6: Operational Disruption | B6: Cyber compromise causes material interruption, shutdown or degradation of the facility's critical operation or service without requiring sustained loss of process control or physical destruction. | C6: 4 | D6: 3 | E6: 56
A7: Loss of Control or Visibility | B7: Cyber compromise prevents or materially degrades operators' ability to observe, command or manage the OT process or production system. | C7: 4 | D7: 5 | E7: 56
A8: Process Manipulation | B8: An adversary intentionally alters process or production-control logic, parameters, I/O, recipes, programs or commands, causing operations to deviate from their intended state. | C8: 3 | D8: 7 | E8: 52
A9: Safety System Compromise | B9: Cyber compromise degrades, disables or manipulates protection, interlock or safety functions intended to prevent or respond to abnormal or unsafe operating conditions. | C9: 5 | D9: 6 | E9: 57
A10: Destructive or Integrity Attack | B10: Cyber activity destroys, corrupts or persistently alters OT systems, logic, firmware, configurations or equipment, requiring significant restoration, integrity assurance or recommissioning and potentially causing physical damage. | C10: 3 | D10: 5 | E10: 55

Sheet OT CORE - Scenario-TTP Map
A1: 09 — Scenario → TTP Mapping
A2: Purpose: Define which ATT&CK ICS techniques are relevant to each adverse scenario and assign an explicit attack stage and scenario role.
A3: In plain English: which attacker techniques could produce each bad outcome. S5 techniques cause the outcome. S1-S4 techniques are the candidate enabling universe — the pool of methods an attacker could draw on to get there, not a literal single path that uses all of them.
A4: SHEET TYPE: MAPPING / MODEL LOGIC
A5: Inputs / upstream sources
A6: ATT&CK ICS technique taxonomy plus model mapping judgement inherited from the predecessor model.
A7: Calculation / decision logic
A8: Scenario relevance is a model relationship. Attack stage is explicit; scenario-defining / supporting impact techniques sit in S5. The engine does not infer stage by first matching a tactic string.
A9: Key assumptions / defaults
A10: Scenario mapping is model logic, not an ATT&CK probability. Mapping snapshot must be version-governed and periodically reviewed.
A11: Outputs / downstream use
A12: Feeds 14 TTP Relevance Calc and 15 Attack Path Calc.
A13: Workbook convention: yellow cells / blue font are editable inputs or calibration assumptions; engine-output cells are not manually editable.
A15: Scenario | B15: TTP ID | C15: Technique | D15: ATT&CK tactic(s) | E15: Scenario role | F15: Attack stage | G15: Mapping basis | H15: Technique URL
A16: Safety System Compromise | B16: T0800 | C16: Activate Firmware Update Mode | D16: Inhibit Response Function | E16: Scenario-defining | F16: S5 | G16: Model Mapping | H16: https://attack.mitre.org/techniques/T0800
A17: Destructive or Integrity Attack | B17: T0800 | C17: Activate Firmware Update Mode | D17: Inhibit Response Function | E17: Supporting / impact | F17: S5 | G17: RECLASSIFIED v1.2: Activate Firmware Update Mode denies normal functionality but does not itself imply destructive or integrity compromise. | H17: https://attack.mitre.org/techniques/T0800
A18: Operational Disruption | B18: T0830 | C18: Adversary-in-the-Middle | D18: Collection | E18: Candidate enabling technique | F18: S4 | G18: Model Mapping | H18: https://attack.mitre.org/techniques/T0830
A19: Loss of Control or Visibility | B19: T0830 | C19: Adversary-in-the-Middle | D19: Collection | E19: Candidate enabling technique | F19: S4 | G19: Model Mapping | H19: https://attack.mitre.org/techniques/T0830
A20: Process Manipulation | B20: T0830 | C20: Adversary-in-the-Middle | D20: Collection | E20: Candidate enabling technique | F20: S4 | G20: Model Mapping | H20: https://attack.mitre.org/techniques/T0830
A21: Safety System Compromise | B21: T0830 | C21: Adversary-in-the-Middle | D21: Collection | E21: Candidate enabling technique | F21: S4 | G21: Model Mapping | H21: https://attack.mitre.org/techniques/T0830
A22: Destructive or Integrity Attack | B22: T0830 | C22: Adversary-in-the-Middle | D22: Collection | E22: Candidate enabling technique | F22: S4 | G22: Model Mapping | H22: https://attack.mitre.org/techniques/T0830
A23: Safety System Compromise | B23: T0878 | C23: Alarm Suppression | D23: Inhibit Response Function | E23: Scenario-defining | F23: S5 | G23: Model Mapping | H23: https://attack.mitre.org/techniques/T0878
A24: Operational Disruption | B24: T0802 | C24: Automated Collection | D24: Collection | E24: Candidate enabling technique | F24: S4 | G24: Model Mapping | H24: https://attack.mitre.org/techniques/T0802
A25: Loss of Control or Visibility | B25: T0802 | C25: Automated Collection | D25: Collection | E25: Candidate enabling technique | F25: S4 | G25: Model Mapping | H25: https://attack.mitre.org/techniques/T0802
A26: Process Manipulation | B26: T0802 | C26: Automated Collection | D26: Collection | E26: Candidate enabling technique | F26: S4 | G26: Model Mapping | H26: https://attack.mitre.org/techniques/T0802
... A64: Destructive or Integrity Attack | B64: T0884 | C64: Connection Proxy | D64: Command and Control | E64: Candidate enabling technique | F64: S3 | G64: Model Mapping | H64: https://attack.mitre.org/techniques/T0884
A65: Operational Disruption | B65: T0879 | C65: Damage to Property | D65: Impact | E65: Removed — moved scenario | G65: MOVED v1.2 to Destructive or Integrity Attack: Damage to Property is damage/destruction of equipment and environment; belongs under Destructive or Integrity. | H65: https://attack.mitre.org/techniques/T0879
A66: Destructive or Integrity Attack | B66: T0809 | C66: Data Destruction | D66: Inhibit Response Function | E66: Scenario-defining | F66: S5 | G66: Model Mapping | H66: https://attack.mitre.org/techniques/T0809
A67: Operational Disruption | B67: T0811 | C67: Data from Information Repositories | D67: Collection | E67: Candidate enabling technique | F67: S4 | G67: Model Mapping | H67: https://attack.mitre.org/techniques/T0811
A68: Loss of Control or Visibility | B68: T0811 | C68: Data from Information Repositories | D68: Collection | E68: Candidate enabling technique | F68: S4 | G68: Model Mapping | H68: https://attack.mitre.org/techniques/T0811
A69: Process Manipulation | B69: T0811 | C69: Data from Information Repositories | D69: Collection | E69: Candidate enabling technique | F69: S4 | G69: Model Mapping | H69: https://attack.mitre.org/techniques/T0811
A70: Safety System Compromise | B70: T0811 | C70: Data from Information Repositories | D70: Collection | E70: Candidate enabling technique | F70: S4 | G70: Model Mapping | H70: https://attack.mitre.org/techniques/T0811
A71: Destructive or Integrity Attack | B71: T0811 | C71: Data from Information Repositories | D71: Collection | E71: Candidate enabling technique | F71: S4 | G71: Model Mapping | H71: https://attack.mitre.org/techniques/T0811
A72: Operational Disruption | B72: T0893 | C72: Data from Local System | D72: Collection | E72: Candidate enabling technique | F72: S4 | G72: Model Mapping | H72: https://attack.mitre.org/techniques/T0893
A73: Loss of Control or Visibility | B73: T0893 | C73: Data from Local System | D73: Collection | E73: Candidate enabling technique | F73: S4 | G73: Model Mapping | H73: https://attack.mitre.org/techniques/T0893
A74: Process Manipulation | B74: T0893 | C74: Data from Local System | D74: Collection | E74: Candidate enabling technique | F74: S4 | G74: Model Mapping | H74: https://attack.mitre.org/techniques/T0893
A75: Safety System Compromise | B75: T0893 | C75: Data from Local System | D75: Collection | E75: Candidate enabling technique | F75: S4 | G75: Model Mapping | H75: https://attack.mitre.org/techniques/T0893
A76: Destructive or Integrity Attack | B76: T0893 | C76: Data from Local System | D76: Collection | E76: Candidate enabling technique | F76: S4 | G76: Model Mapping | H76: https://attack.mitre.org/techniques/T0893
A77: Operational Disruption | B77: T1694.001 | C77: Default Credentials | D77: Lateral Movement, Persistence | E77: Candidate enabling technique | F77: S3 | G77: Model Mapping | H77: https://attack.mitre.org/techniques/T1694/001
... A173: Loss of Control or Visibility | B173: T0827 | C173: Loss of Control | D173: Impact | E173: Scenario-defining | F173: S5 | G173: Model Mapping | H173: https://attack.mitre.org/techniques/T0827
A174: Operational Disruption | B174: T0828 | C174: Loss of Productivity and Revenue | D174: Impact | E174: Removed — see mapping basis | G174: REMOVED v1.2: Loss of Productivity and Revenue is a consequence; the CRQ engine quantifies financial consequence separately (sheets 05/17). | H174: https://attack.mitre.org/techniques/T0828
A175: Operational Disruption | B175: T0837 | C175: Loss of Protection | D175: Impact | E175: Removed — moved scenario | G175: MOVED v1.2 to Safety System Compromise: Loss of Protection compromises protective functions preventing faults and abnormal conditions. | H175: https://attack.mitre.org/techniques/T0837
A176: Safety System Compromise | B176: T0880 | C176: Loss of Safety | D176: Impact | E176: Scenario-defining | F176: S5 | G176: Model Mapping | H176: https://attack.mitre.org/techniques/T0880
A177: Loss of Control or Visibility | B177: T0829 | C177: Loss of View | D177: Impact | E177: Scenario-defining | F177: S5 | G177: Model Mapping | H177: https://attack.mitre.org/techniques/T0829
A178: Safety System Compromise | B178: T0835 | C178: Manipulate I/O Image | D178: Inhibit Response Function | E178: Supporting / impact | F178: S5 | G178: Model Mapping | H178: https://attack.mitre.org/techniques/T0835
A179: Process Manipulation | B179: T0831 | C179: Manipulation of Control | D179: Impact | E179: Scenario-defining | F179: S5 | G179: Model Mapping | H179: https://attack.mitre.org/techniques/T0831
A180: Operational Disruption | B180: T0832 | C180: Manipulation of View | D180: Impact | E180: Removed — moved scenario | G180: MOVED v1.2 to Loss of Control or Visibility: Manipulation of View is deceptive visibility; belongs under Loss of Control or Visibility. | H180: https://attack.mitre.org/techniques/T0832
A181: Operational Disruption | B181: T0849 | C181: Masquerading | D181: Evasion | E181: Candidate enabling technique | F181: S2 | G181: Model Mapping | H181: https://attack.mitre.org/techniques/T0849
A182: Loss of Control or Visibility | B182: T0849 | C182: Masquerading | D182: Evasion | E182: Candidate enabling technique | F182: S2 | G182: Model Mapping | H182: https://attack.mitre.org/techniques/T0849
A183: Process Manipulation | B183: T0849 | C183: Masquerading | D183: Evasion | E183: Candidate enabling technique | F183: S2 | G183: Model Mapping | H183: https://attack.mitre.org/techniques/T0849
A184: Safety System Compromise | B184: T0849 | C184: Masquerading | D184: Evasion | E184: Candidate enabling technique | F184: S2 | G184: Model Mapping | H184: https://attack.mitre.org/techniques/T0849
A185: Destructive or Integrity Attack | B185: T0849 | C185: Masquerading | D185: Evasion | E185: Candidate enabling technique | F185: S2 | G185: Model Mapping | H185: https://attack.mitre.org/techniques/T0849
A186: Safety System Compromise | B186: T0838 | C186: Modify Alarm Settings | D186: Inhibit Response Function | E186: Scenario-defining | F186: S5 | G186: Model Mapping | H186: https://attack.mitre.org/techniques/T0838
A187: Operational Disruption | B187: T0821 | C187: Modify Controller Tasking | D187: Execution | E187: Candidate enabling technique | F187: S2 | G187: Model Mapping | H187: https://attack.mitre.org/techniques/T0821
A188: Loss of Control or Visibility | B188: T0821 | C188: Modify Controller Tasking | D188: Execution | E188: Candidate enabling technique | F188: S2 | G188: Model Mapping | H188: https://attack.mitre.org/techniques/T0821
A189: Process Manipulation | B189: T0821 | C189: Modify Controller Tasking | D189: Execution | E189: Supporting / impact | F189: S5 | G189: RESTAGED v1.2: In the Process Manipulation scenario this technique directly implements the adverse outcome, so it is staged S5 rather than inheriting its ATT&CK tactic. CRQ stage is scenario-specific. | H189: https://attack.mitre.org/techniques/T0821
A190: Safety System Compromise | B190: T0821 | C190: Modify Controller Tasking | D190: Execution | E190: Candidate enabling technique | F190: S2 | G190: Model Mapping | H190: https://attack.mitre.org/techniques/T0821
A191: Destructive or Integrity Attack | B191: T0821 | C191: Modify Controller Tasking | D191: Execution | E191: Supporting / impact | F191: S5 | G191: STRENGTHENED v1.2: Modify Controller Tasking as a persistent integrity compromise. | H191: https://attack.mitre.org/techniques/T0821
A192: Destructive or Integrity Attack | B192: T1693 | C192: Modify Firmware | D192: Impair Process Control, Inhibit Response Function, Persistence | E192: Excluded — parent/sub duplicate | F192: S5 | G192: SUPPRESSED v1.2: parent technique carries no separate weight where applicable sub-techniques are mapped in the same scenario. Prevents one underlying behaviour receiving multiple weights in the stage barrier. | H192: https://attack.mitre.org/techniques/T1693
... A326: Destructive or Integrity Attack | B326: T1693.001 | C326: System Firmware | D326: Impair Process Control, Inhibit Response Function, Persistence | E326: Scenario-defining | F326: S5 | G326: Model Mapping | H326: https://attack.mitre.org/techniques/T1693/001
A327: Operational Disruption | B327: T0882 | C327: Theft of Operational Information | D327: Impact | E327: Removed — see mapping basis | G327: REMOVED v1.2: Theft of Operational Information is an exfiltration outcome, not a disruption mechanism. | H327: https://attack.mitre.org/techniques/T0882
A328: Operational Disruption | B328: T0864 | C328: Transient Cyber Asset | D328: Initial Access | E328: Candidate enabling technique | F328: S1 | G328: Model Mapping | H328: https://attack.mitre.org/techniques/T0864
A329: Loss of Control or Visibility | B329: T0864 | C329: Transient Cyber Asset | D329: Initial Access | E329: Candidate enabling technique | F329: S1 | G329: Model Mapping | H329: https://attack.mitre.org/techniques/T0864
A330: Process Manipulation | B330: T0864 | C330: Transient Cyber Asset | D330: Initial Access | E330: Candidate enabling technique | F330: S1 | G330: Model Mapping | H330: https://attack.mitre.org/techniques/T0864
A331: Safety System Compromise | B331: T0864 | C331: Transient Cyber Asset | D331: Initial Access | E331: Candidate enabling technique | F331: S1 | G331: Model Mapping | H331: https://attack.mitre.org/techniques/T0864
A332: Destructive or Integrity Attack | B332: T0864 | C332: Transient Cyber Asset | D332: Initial Access | E332: Candidate enabling technique | F332: S1 | G332: Model Mapping | H332: https://attack.mitre.org/techniques/T0864
A333: Process Manipulation | B333: T1692 | C333: Unauthorized Message | D333: Evasion, Impair Process Control | E333: Excluded — parent/sub duplicate | F333: S5 | G333: SUPPRESSED v1.2: parent technique carries no separate weight where applicable sub-techniques are mapped in the same scenario. Prevents one underlying behaviour receiving multiple weights in the stage barrier. | H333: https://attack.mitre.org/techniques/T1692
A334: Operational Disruption | B334: T0863 | C334: User Execution | D334: Execution | E334: Candidate enabling technique | F334: S2 | G334: Model Mapping | H334: https://attack.mitre.org/techniques/T0863
A335: Loss of Control or Visibility | B335: T0863 | C335: User Execution | D335: Execution | E335: Candidate enabling technique | F335: S2 | G335: Model Mapping | H335: https://attack.mitre.org/techniques/T0863
A336: Process Manipulation | B336: T0863 | C336: User Execution | D336: Execution | E336: Candidate enabling technique | F336: S2 | G336: Model Mapping | H336: https://attack.mitre.org/techniques/T0863
A337: Safety System Compromise | B337: T0863 | C337: User Execution | D337: Execution | E337: Candidate enabling technique | F337: S2 | G337: Model Mapping | H337: https://attack.mitre.org/techniques/T0863
A338: Destructive or Integrity Attack | B338: T0863 | C338: User Execution | D338: Execution | E338: Candidate enabling technique | F338: S2 | G338: Model Mapping | H338: https://attack.mitre.org/techniques/T0863
A339: Operational Disruption | B339: T0859 | C339: Valid Accounts | D339: Lateral Movement, Persistence | E339: Candidate enabling technique | F339: S3 | G339: Model Mapping | H339: https://attack.mitre.org/techniques/T0859
... A366: Destructive or Integrity Attack | B366: T0836 | C366: Modify Parameter | D366: Impair Process Control | E366: Supporting / impact | F366: S5 | G366: ADDED v1.2: Modify Parameter where the purpose is destructive. | H366: https://attack.mitre.org/techniques/T0836

Sheet OT CORE - Actor-TTP Map
A1: 11 — Threat Actor → TTP Applicability
A2: Purpose: Specify whether a scenario-relevant TTP is applicable to each of the three threat-actor archetypes.
A3: In plain English: the model runs all three actors automatically. External actors use the full path; Malicious Insider starts inside the trust boundary and bypasses external Initial Access.
A4: SHEET TYPE: MAPPING / MODEL LOGIC
A5: Inputs / upstream sources
A6: Scenario-TTP library plus actor-archetype modelling judgement. ATT&CK group observations are evidence, not a capability veto.
A7: Calculation / decision logic
A8: ActorApplicable is a binary gate. Relevant TTP = ScenarioRelevant AND ActorApplicable AND FacilityFeasible. For Malicious Insider, S1 TTPs are not required because S1 is bypassed.
A9: Key assumptions / defaults
A10: Absence of a publicly reported ATT&CK technique does not prove an actor cannot use it; named-group observations can later refine the archetype.
A11: Outputs / downstream use
A12: Feeds 14 TTP Relevance Calc and the Python engine.
A13: Workbook convention: yellow cells / blue font are editable inputs or calibration assumptions; engine-output cells are not manually editable.
A15: Threat actor | B15: TTP ID | C15: Technique | D15: Stage | E15: Applicable? | F15: Rationale
A16: Nation State | B16: T0800 | C16: Activate Firmware Update Mode | D16: S5 | E16: Yes | F16: Scenario-relevant TTP retained for this external actor archetype.
A17: Nation State | B17: T0801 | C17: Monitor Process State | D17: S4 | E17: Yes | F17: Scenario-relevant TTP retained for this external actor archetype.
A18: Nation State | B18: T0802 | C18: Automated Collection | D18: S4 | E18: Yes | F18: Scenario-relevant TTP retained for this external actor archetype.
A19: Nation State | B19: T0806 | C19: Brute Force I/O | D19: S5 | E19: Yes | F19: Scenario-relevant TTP retained for this external actor archetype.
A20: Nation State | B20: T0807 | C20: Command-Line Interface | D20: S2 | E20: Yes | F20: Scenario-relevant TTP retained for this external actor archetype.
A21: Nation State | B21: T0809 | C21: Data Destruction | D21: S5 | E21: Yes | F21: Scenario-relevant TTP retained for this external actor archetype.
A22: Nation State | B22: T0811 | C22: Data from Information Repositories | D22: S4 | E22: Yes | F22: Scenario-relevant TTP retained for this external actor archetype.
A23: Nation State | B23: T0813 | C23: Denial of Control | D23: S5 | E23: Yes | F23: Scenario-relevant TTP retained for this external actor archetype.
A24: Nation State | B24: T0814 | C24: Denial of Service | D24: S5 | E24: Yes | F24: Scenario-relevant TTP retained for this external actor archetype.
A25: Nation State | B25: T0815 | C25: Denial of View | D25: S5 | E25: Yes | F25: Scenario-relevant TTP retained for this external actor archetype.
A26: Nation State | B26: T0816 | C26: Device Restart/Shutdown | D26: S5 | E26: Yes | F26: Scenario-relevant TTP retained for this external actor archetype.
... A306: Malicious Insider | B306: T1695.003 | C306: Wi-Fi | D306: S5 | E306: Yes | F306: Applicable after the trusted-access starting point.

Sheet OT CORE - Facility Feasibility
A1: 12 — Facility Feasibility Rules
A2: Purpose: Gate TTPs or whole scenarios when the facility lacks the architectural condition required for that route.
A3: In plain English: this prevents nonsensical paths such as wireless compromise when the OT environment has no wireless connectivity.
A4: SHEET TYPE: MAPPING / MODEL LOGIC
A5: Inputs / upstream sources
A6: 03 Facility Inputs plus explicit rule table below.
A7: Calculation / decision logic
A8: Relevant TTP = ScenarioRelevant AND ActorApplicable AND FacilityFeasible. Rules below are explicit exceptions; a TTP with no facility rule defaults to feasible. Current Facility Value and Feasible? are formula-linked to 04 Facility Inputs for review transparency.
A9: Key assumptions / defaults
A10: Rules are intentionally narrow. A facility input can affect both feasibility (is a route possible?) and frequency exposure (does it make campaigns more likely?) for different causal reasons.
A11: Outputs / downstream use
A12: Feeds 14 TTP Relevance Calc and attack-path generation.
A13: Workbook convention: yellow cells / blue font are editable inputs or calibration assumptions; engine-output cells are not manually editable.
A15: Rule target | B15: ID / Scenario | C15: Technique / Scenario | D15: Rule code | E15: Facility input 1 | F15: Facility input 2 | G15: Required condition | H15: Rationale | I15: Current facility value | J15: Feasible?
A16: TTP | B16: T0822 | C16: External Remote Services | D16: REMOTE_REQUIRED | E16: REMOTE_ACCESS | G16: Not None | H16: Requires a remote-access path. | I16: =INDEX('OT 03 - Facility Inputs'!$C$16:$C$29,MATCH(E16,'OT 03 - Facility Inputs'!$A$16:$A$29,0)) | J16: =IF(INDEX('OT 03 - Facility Inputs'!$C$16:$C$29,MATCH(E16,'OT 03 - Facility Inputs'!$A$16:$A$29,0))<>"None","Yes","No")
A17: TTP | B17: T0866 | C17: Exploitation of Remote Services | D17: REMOTE_OR_ITOT | E17: REMOTE_ACCESS | F17: IT_OT_CONNECTIVITY | G17: Remote path or IT-OT connection | H17: Requires a remotely reachable service or an IT-to-OT path. | I17: =INDEX('OT 03 - Facility Inputs'!$C$16:$C$29,MATCH(E17,'OT 03 - Facility Inputs'!$A$16:$A$29,0))&" / "&INDEX('OT 03 - Facility Inputs'!$C$16:$C$29,MATCH(F17,'OT 03 - Facility Inputs'!$A$16:$A$29,0)) | J17: =IF(OR(INDEX('OT 03 - Facility Inputs'!$C$16:$C$29,MATCH(E17,'OT 03 - Facility Inputs'!$A$16:$A$29,0))<>"None",INDEX('OT 03 - Facility Inputs'!$C$16:$C$29,MATCH(F17,'OT 03 - Facility Inputs'!$A$16:$A$29,0))="Yes"),"Yes","No")
A18: TTP | B18: T0886 | C18: Remote Services | D18: REMOTE_OR_ITOT | E18: REMOTE_ACCESS | F18: IT_OT_CONNECTIVITY | G18: Remote path or IT-OT connection | H18: Requires a remotely reachable service or an IT-to-OT path. | I18: =INDEX('OT 03 - Facility Inputs'!$C$16:$C$29,MATCH(E18,'OT 03 - Facility Inputs'!$A$16:$A$29,0))&" / "&INDEX('OT 03 - Facility Inputs'!$C$16:$C$29,MATCH(F18,'OT 03 - Facility Inputs'!$A$16:$A$29,0)) | J18: =IF(OR(INDEX('OT 03 - Facility Inputs'!$C$16:$C$29,MATCH(E18,'OT 03 - Facility Inputs'!$A$16:$A$29,0))<>"None",INDEX('OT 03 - Facility Inputs'!$C$16:$C$29,MATCH(F18,'OT 03 - Facility Inputs'!$A$16:$A$29,0))="Yes"),"Yes","No")
A19: TTP | B19: T0883 | C19: Internet Accessible Device | D19: INTERNET_OT | E19: INTERNET_OT | G19: Yes | H19: Requires a critical OT service/device to be internet accessible. | I19: =INDEX('OT 03 - Facility Inputs'!$C$16:$C$29,MATCH(E19,'OT 03 - Facility Inputs'!$A$16:$A$29,0)) | J19: =IF(INDEX('OT 03 - Facility Inputs'!$C$16:$C$29,MATCH(E19,'OT 03 - Facility Inputs'!$A$16:$A$29,0))="Yes","Yes","No")
A20: TTP | B20: T0864 | C20: Transient Cyber Asset | D20: TRANSIENT_REQUIRED | E20: TRANSIENT_ASSETS | G20: Not None | H20: Requires transient/contractor assets. | I20: =INDEX('OT 03 - Facility Inputs'!$C$16:$C$29,MATCH(E20,'OT 03 - Facility Inputs'!$A$16:$A$29,0)) | J20: =IF(INDEX('OT 03 - Facility Inputs'!$C$16:$C$29,MATCH(E20,'OT 03 - Facility Inputs'!$A$16:$A$29,0))<>"None","Yes","No")
A21: TTP | B21: T0847 | C21: Replication Through Removable Media | D21: TRANSIENT_REQUIRED | E21: TRANSIENT_ASSETS | G21: Not None | H21: Uses transient/removable-media route as a feasibility proxy. | I21: =INDEX('OT 03 - Facility Inputs'!$C$16:$C$29,MATCH(E21,'OT 03 - Facility Inputs'!$A$16:$A$29,0)) | J21: =IF(INDEX('OT 03 - Facility Inputs'!$C$16:$C$29,MATCH(E21,'OT 03 - Facility Inputs'!$A$16:$A$29,0))<>"None","Yes","No")
A22: TTP | B22: T0862 | C22: Supply Chain Compromise | D22: SUPPLY_CHAIN | E22: SUPPLY_CHAIN_ROUTE | G22: Yes | H22: Requires a trusted supplier/update route. | I22: =INDEX('OT 03 - Facility Inputs'!$C$16:$C$29,MATCH(E22,'OT 03 - Facility Inputs'!$A$16:$A$29,0)) | J22: =IF(INDEX('OT 03 - Facility Inputs'!$C$16:$C$29,MATCH(E22,'OT 03 - Facility Inputs'!$A$16:$A$29,0))="Yes","Yes","No")
A23: TTP | B23: T0860 | C23: Wireless Compromise | D23: WIRELESS | E23: WIRELESS_OT | G23: Yes | H23: Requires wireless OT connectivity. | I23: =INDEX('OT 03 - Facility Inputs'!$C$16:$C$29,MATCH(E23,'OT 03 - Facility Inputs'!$A$16:$A$29,0)) | J23: =IF(INDEX('OT 03 - Facility Inputs'!$C$16:$C$29,MATCH(E23,'OT 03 - Facility Inputs'!$A$16:$A$29,0))="Yes","Yes","No")
A24: TTP | B24: T0887 | C24: Wireless Sniffing | D24: WIRELESS | E24: WIRELESS_OT | G24: Yes | H24: Requires wireless OT connectivity. | I24: =INDEX('OT 03 - Facility Inputs'!$C$16:$C$29,MATCH(E24,'OT 03 - Facility Inputs'!$A$16:$A$29,0)) | J24: =IF(INDEX('OT 03 - Facility Inputs'!$C$16:$C$29,MATCH(E24,'OT 03 - Facility Inputs'!$A$16:$A$29,0))="Yes","Yes","No")
A25: TTP | B25: T1695.003 | C25: Wi-Fi | D25: WIRELESS | E25: WIRELESS_OT | G25: Yes | H25: Requires wireless OT connectivity. | I25: =INDEX('OT 03 - Facility Inputs'!$C$16:$C$29,MATCH(E25,'OT 03 - Facility Inputs'!$A$16:$A$29,0)) | J25: =IF(INDEX('OT 03 - Facility Inputs'!$C$16:$C$29,MATCH(E25,'OT 03 - Facility Inputs'!$A$16:$A$29,0))="Yes","Yes","No")
A26: Scenario | B26: Safety System Compromise | C26: Safety System Compromise | D26: SIS_PRESENT | E26: SAFETY_SYSTEM | G26: Not None | H26: Scenario not quantified when no safety/protection system exists. | I26: =INDEX('OT 03 - Facility Inputs'!$C$16:$C$29,MATCH(E26,'OT 03 - Facility Inputs'!$A$16:$A$29,0)) | J26: =IF(INDEX('OT 03 - Facility Inputs'!$C$16:$C$29,MATCH(E26,'OT 03 - Facility Inputs'!$A$16:$A$29,0))<>"None","Yes","No")

Sheet OT CORE - TTP-Control Map
A1: 13 — TTP → Control Mapping & Efficacy
A2: Purpose: Link ATT&CK ICS techniques to controls and calculate the realised efficacy of each TTP-control relationship.
A3: In plain English: this is where control efficacy actually lives. A control does not have one universal effectiveness score; efficacy is evaluated for each mapped TTP relationship.
A4: SHEET TYPE: MAPPING / MODEL LOGIC
A5: Inputs / upstream sources
A6: ATT&CK mitigation relationships, 04 Control Assessment and the editable Base Efficacy prior on this sheet.
A7: Calculation / decision logic
A8: Applied Efficacy(c,t) = Base Efficacy(c,t) × Maturity Factor(c) × Coverage Used(c). Maturity and coverage columns are formula-linked to 04. The Python engine independently performs the same deterministic calculation before aggregating barriers.
A9: Key assumptions / defaults
A10: Base Efficacy is an explicit WORKING PRIOR, not an empirical fact. The current Power Generation reference calibration uses 80% for non-excluded mappings; ATT&CK identifies mitigation applicability but does not quantify probability of prevention. Where a relevant TTP has no mapped control in a causal channel, the model assigns zero efficacy for that channel; this is a mapping-coverage limitation, not evidence that the technique is inherently unmitigable. Calibrate mappings and efficacy values when testing / incident / SME evidence is available.
A11: Outputs / downstream use
A12: Feeds 15 Attack Path Calc and Detect/Recover/Safety consequence adjustments. Control what-if results remain provisional until Base Efficacy is calibrated.
A13: Workbook convention: yellow cells / blue font are editable inputs or calibration assumptions; engine-output cells are not manually editable.
A15: TTP ID | B15: Technique | C15: Control ID | D15: Control | E15: Channel | F15: Base efficacy | G15: Maturity factor | H15: Coverage used | I15: Applied efficacy | J15: Mapping source | K15: Technique URL | L15: Control URL | M15: Efficacy basis / status
A16: T0800 | B16: Activate Firmware Update Mode | C16: M0801 | D16: Access Management | E16: Prevent / Resist | F16: 0.8 | G16: =IFERROR(INDEX('OT 04 - Control Assessment'!$I$16:$I$67,MATCH(C16,'OT 04 - Control Assessment'!$A$16:$A$67,0)),0) | H16: =IFERROR(INDEX('OT 04 - Control Assessment'!$J$16:$J$67,MATCH(C16,'OT 04 - Control Assessment'!$A$16:$A$67,0)),0) | I16: =F16*G16*H16 | J16: Direct ATT&CK mitigation relationship | K16: https://attack.mitre.org/techniques/T0800 | L16: https://attack.mitre.org/mitigations/M0801 | M16: Current Power Generation working prior (80%) because ATT&CK establishes mitigation applicability but does not quantify efficacy. Replace with test / incident / SME calibration when available.
A17: T0858 | B17: Change Operating Mode | C17: M0801 | D17: Access Management | E17: Prevent / Resist | F17: 0.8 | G17: =IFERROR(INDEX('OT 04 - Control Assessment'!$I$16:$I$67,MATCH(C17,'OT 04 - Control Assessment'!$A$16:$A$67,0)),0) | H17: =IFERROR(INDEX('OT 04 - Control Assessment'!$J$16:$J$67,MATCH(C17,'OT 04 - Control Assessment'!$A$16:$A$67,0)),0) | I17: =F17*G17*H17 | J17: Direct ATT&CK mitigation relationship | K17: https://attack.mitre.org/techniques/T0858 | L17: https://attack.mitre.org/mitigations/M0801 | M17: Current Power Generation working prior (80%) because ATT&CK establishes mitigation applicability but does not quantify efficacy. Replace with test / incident / SME calibration when available.
A18: T1694.001 | B18: Default Credentials | C18: M0801 | D18: Access Management | E18: Prevent / Resist | F18: 0.8 | G18: =IFERROR(INDEX('OT 04 - Control Assessment'!$I$16:$I$67,MATCH(C18,'OT 04 - Control Assessment'!$A$16:$A$67,0)),0) | H18: =IFERROR(INDEX('OT 04 - Control Assessment'!$J$16:$J$67,MATCH(C18,'OT 04 - Control Assessment'!$A$16:$A$67,0)),0) | I18: =F18*G18*H18 | J18: Direct ATT&CK mitigation relationship | K18: https://attack.mitre.org/techniques/T1694/001 | L18: https://attack.mitre.org/mitigations/M0801 | M18: Current Power Generation working prior (80%) because ATT&CK establishes mitigation applicability but does not quantify efficacy. Replace with test / incident / SME calibration when available.
A19: T0868 | B19: Detect Operating Mode | C19: M0801 | D19: Access Management | E19: Prevent / Resist | F19: 0.8 | G19: =IFERROR(INDEX('OT 04 - Control Assessment'!$I$16:$I$67,MATCH(C19,'OT 04 - Control Assessment'!$A$16:$A$67,0)),0) | H19: =IFERROR(INDEX('OT 04 - Control Assessment'!$J$16:$J$67,MATCH(C19,'OT 04 - Control Assessment'!$A$16:$A$67,0)),0) | I19: =F19*G19*H19 | J19: Direct ATT&CK mitigation relationship | K19: https://attack.mitre.org/techniques/T0868 | L19: https://attack.mitre.org/mitigations/M0801 | M19: Current Power Generation working prior (80%) because ATT&CK establishes mitigation applicability but does not quantify efficacy. Replace with test / incident / SME calibration when available.
A20: T0816 | B20: Device Restart/Shutdown | C20: M0801 | D20: Access Management | E20: Prevent / Resist | F20: 0.8 | G20: =IFERROR(INDEX('OT 04 - Control Assessment'!$I$16:$I$67,MATCH(C20,'OT 04 - Control Assessment'!$A$16:$A$67,0)),0) | H20: =IFERROR(INDEX('OT 04 - Control Assessment'!$J$16:$J$67,MATCH(C20,'OT 04 - Control Assessment'!$A$16:$A$67,0)),0) | I20: =F20*G20*H20 | J20: Direct ATT&CK mitigation relationship | K20: https://attack.mitre.org/techniques/T0816 | L20: https://attack.mitre.org/mitigations/M0801 | M20: Current Power Generation working prior (80%) because ATT&CK establishes mitigation applicability but does not quantify efficacy. Replace with test / incident / SME calibration when available.
A21: T0843.001 | B21: Download All | C21: M0801 | D21: Access Management | E21: Prevent / Resist | F21: 0.8 | G21: =IFERROR(INDEX('OT 04 - Control Assessment'!$I$16:$I$67,MATCH(C21,'OT 04 - Control Assessment'!$A$16:$A$67,0)),0) | H21: =IFERROR(INDEX('OT 04 - Control Assessment'!$J$16:$J$67,MATCH(C21,'OT 04 - Control Assessment'!$A$16:$A$67,0)),0) | I21: =F21*G21*H21 | J21: Direct ATT&CK mitigation relationship | K21: https://attack.mitre.org/techniques/T0843/001 | L21: https://attack.mitre.org/mitigations/M0801 | M21: Current Power Generation working prior (80%) because ATT&CK establishes mitigation applicability but does not quantify efficacy. Replace with test / incident / SME calibration when available.
A22: T0871 | B22: Execution through API | C22: M0801 | D22: Access Management | E22: Prevent / Resist | F22: 0.8 | G22: =IFERROR(INDEX('OT 04 - Control Assessment'!$I$16:$I$67,MATCH(C22,'OT 04 - Control Assessment'!$A$16:$A$67,0)),0) | H22: =IFERROR(INDEX('OT 04 - Control Assessment'!$J$16:$J$67,MATCH(C22,'OT 04 - Control Assessment'!$A$16:$A$67,0)),0) | I22: =F22*G22*H22 | J22: Direct ATT&CK mitigation relationship | K22: https://attack.mitre.org/techniques/T0871 | L22: https://attack.mitre.org/mitigations/M0801 | M22: Current Power Generation working prior (80%) because ATT&CK establishes mitigation applicability but does not quantify efficacy. Replace with test / incident / SME calibration when available.
A23: T1694.002 | B23: Hardcoded Credentials | C23: M0801 | D23: Access Management | E23: Prevent / Resist | F23: 0.8 | G23: =IFERROR(INDEX('OT 04 - Control Assessment'!$I$16:$I$67,MATCH(C23,'OT 04 - Control Assessment'!$A$16:$A$67,0)),0) | H23: =IFERROR(INDEX('OT 04 - Control Assessment'!$J$16:$J$67,MATCH(C23,'OT 04 - Control Assessment'!$A$16:$A$67,0)),0) | I23: =F23*G23*H23 | J23: Direct ATT&CK mitigation relationship | K23: https://attack.mitre.org/techniques/T1694/002 | L23: https://attack.mitre.org/mitigations/M0801 | M23: Current Power Generation working prior (80%) because ATT&CK establishes mitigation applicability but does not quantify efficacy. Replace with test / incident / SME calibration when available.
A24: T1694 | B24: Insecure Credentials | C24: M0801 | D24: Access Management | E24: Prevent / Resist | F24: 0.8 | G24: =IFERROR(INDEX('OT 04 - Control Assessment'!$I$16:$I$67,MATCH(C24,'OT 04 - Control Assessment'!$A$16:$A$67,0)),0) | H24: =IFERROR(INDEX('OT 04 - Control Assessment'!$J$16:$J$67,MATCH(C24,'OT 04 - Control Assessment'!$A$16:$A$67,0)),0) | I24: =F24*G24*H24 | J24: Direct ATT&CK mitigation relationship | K24: https://attack.mitre.org/techniques/T1694 | L24: https://attack.mitre.org/mitigations/M0801 | M24: Current Power Generation working prior (80%) because ATT&CK establishes mitigation applicability but does not quantify efficacy. Replace with test / incident / SME calibration when available.
A25: T0838 | B25: Modify Alarm Settings | C25: M0801 | D25: Access Management | E25: Prevent / Resist | F25: 0.8 | G25: =IFERROR(INDEX('OT 04 - Control Assessment'!$I$16:$I$67,MATCH(C25,'OT 04 - Control Assessment'!$A$16:$A$67,0)),0) | H25: =IFERROR(INDEX('OT 04 - Control Assessment'!$J$16:$J$67,MATCH(C25,'OT 04 - Control Assessment'!$A$16:$A$67,0)),0) | I25: =F25*G25*H25 | J25: Direct ATT&CK mitigation relationship | K25: https://attack.mitre.org/techniques/T0838 | L25: https://attack.mitre.org/mitigations/M0801 | M25: Current Power Generation working prior (80%) because ATT&CK establishes mitigation applicability but does not quantify efficacy. Replace with test / incident / SME calibration when available.
A26: T1693 | B26: Modify Firmware | C26: M0801 | D26: Access Management | E26: Prevent / Resist | F26: 0.8 | G26: =IFERROR(INDEX('OT 04 - Control Assessment'!$I$16:$I$67,MATCH(C26,'OT 04 - Control Assessment'!$A$16:$A$67,0)),0) | H26: =IFERROR(INDEX('OT 04 - Control Assessment'!$J$16:$J$67,MATCH(C26,'OT 04 - Control Assessment'!$A$16:$A$67,0)),0) | I26: =F26*G26*H26 | J26: Direct ATT&CK mitigation relationship | K26: https://attack.mitre.org/techniques/T1693 | L26: https://attack.mitre.org/mitigations/M0801 | M26: Current Power Generation working prior (80%) because ATT&CK establishes mitigation applicability but does not quantify efficacy. Replace with test / incident / SME calibration when available.
A27: T1693.002 | B27: Module Firmware | C27: M0801 | D27: Access Management | E27: Prevent / Resist | F27: 0.8 | G27: =IFERROR(INDEX('OT 04 - Control Assessment'!$I$16:$I$67,MATCH(C27,'OT 04 - Control Assessment'!$A$16:$A$67,0)),0) | H27: =IFERROR(INDEX('OT 04 - Control Assessment'!$J$16:$J$67,MATCH(C27,'OT 04 - Control Assessment'!$A$16:$A$67,0)),0) | I27: =F27*G27*H27 | J27: Direct ATT&CK mitigation relationship | K27: https://attack.mitre.org/techniques/T1693/002 | L27: https://attack.mitre.org/mitigations/M0801 | M27: Current Power Generation working prior (80%) because ATT&CK establishes mitigation applicability but does not quantify efficacy. Replace with test / incident / SME calibration when available.
... A417: T0814 | B417: Denial of Service | C417: M0815 | D417: Watchdog Timers | E417: Safety / Resilience | F417: 0.8 | G417: =IFERROR(INDEX('OT 04 - Control Assessment'!$I$16:$I$67,MATCH(C417,'OT 04 - Control Assessment'!$A$16:$A$67,0)),0) | H417: =IFERROR(INDEX('OT 04 - Control Assessment'!$J$16:$J$67,MATCH(C417,'OT 04 - Control Assessment'!$A$16:$A$67,0)),0) | I417: =F417*G417*H417 | J417: Direct ATT&CK mitigation relationship | K417: https://attack.mitre.org/techniques/T0814 | L417: https://attack.mitre.org/mitigations/M0815 | M417: Current Power Generation working prior (80%) because ATT&CK establishes mitigation applicability but does not quantify efficacy. Replace with test / incident / SME calibration when available.

Sheet OT CORE - Mapping Change Log
A1: 10 — Scenario-TTP Mapping Change Log (v1.1 to v1.2)
A2: Every change made to the Power Generation scenario pack, with the reason. Rows removed or suppressed are retained on 09 Scenario-TTP Map with their reason recorded in Mapping basis rather than deleted, so the v1.1 position remains auditable.
A3: In plain English: what changed in the technique mappings, and why.
A5: Change | B5: Scenario | C5: TTP ID | D5: Technique | E5: From -> To | F5: Reason
A6: DROP | B6: Operational Disruption | C6: T0882 | D6: Theft of Operational Information | F6: Theft of Operational Information is an exfiltration outcome, not a disruption mechanism.
A7: DROP | B7: Operational Disruption | C7: T0828 | D7: Loss of Productivity and Revenue | F7: Loss of Productivity and Revenue is a consequence; the CRQ engine quantifies financial consequence separately (sheets 05/17).
A8: MOVE-OUT | B8: Operational Disruption | C8: T0832 | D8: Manipulation of View | F8: Manipulation of View is deceptive visibility; belongs under Loss of Control or Visibility.
A9: MOVE-IN | B9: Loss of Control or Visibility | C9: T0832 | D9: Manipulation of View | E9: Supporting / impact / S5 | F9: Manipulation of View is deceptive visibility; belongs under Loss of Control or Visibility.
A10: MOVE-OUT | B10: Operational Disruption | C10: T0837 | D10: Loss of Protection | F10: Loss of Protection compromises protective functions preventing faults and abnormal conditions.
A11: MOVE-IN | B11: Safety System Compromise | C11: T0837 | D11: Loss of Protection | E11: Scenario-defining / S5 | F11: Loss of Protection compromises protective functions preventing faults and abnormal conditions.
A12: MOVE-OUT | B12: Operational Disruption | C12: T0879 | D12: Damage to Property | F12: Damage to Property is damage/destruction of equipment and environment; belongs under Destructive or Integrity.
A13: MOVE-IN | B13: Destructive or Integrity Attack | C13: T0879 | D13: Damage to Property | E13: Supporting / impact / S5 | F13: Damage to Property is damage/destruction of equipment and environment; belongs under Destructive or Integrity.
A14: RECLASSIFY | B14: Process Manipulation | C14: T1691.001 | D14: Command Message | E14: Scenario-defining / S5 -> Supporting / impact / S5 | F14: Block Command Message prevents a command reaching its target (inhibit response); it does not issue a malicious command, so it cannot define Process Manipulation.
A15: RECLASSIFY | B15: Safety System Compromise | C15: T0851 | D15: Rootkit | E15: Scenario-defining / S5 -> Enabling / prerequisite / S2 | F15: Rootkit hides malware and connections through OS manipulation — an evasion technique, not a safety-system outcome.
A16: RECLASSIFY | B16: Destructive or Integrity Attack | C16: T0851 | D16: Rootkit | E16: Scenario-defining / S5 -> Enabling / prerequisite / S2 | F16: As above: evasion, not a destructive or integrity outcome.
A17: RECLASSIFY | B17: Destructive or Integrity Attack | C17: T0800 | D17: Activate Firmware Update Mode | E17: Scenario-defining / S5 -> Supporting / impact / S5 | F17: Activate Firmware Update Mode denies normal functionality but does not itself imply destructive or integrity compromise.
A18: RESTAGE | B18: Process Manipulation | C18: T0821 | D18: Modify Controller Tasking | E18: Enabling / prerequisite / S2 -> Supporting / impact / S5 | F18: In the Process Manipulation scenario this technique directly implements the adverse outcome, so it is staged S5 rather than inheriting its ATT&CK tactic. CRQ stage is scenario-specific.
A19: RESTAGE | B19: Process Manipulation | C19: T0889 | D19: Modify Program | E19: Enabling / prerequisite / S2 -> Supporting / impact / S5 | F19: In the Process Manipulation scenario this technique directly implements the adverse outcome, so it is staged S5 rather than inheriting its ATT&CK tactic. CRQ stage is scenario-specific.
A20: RESTAGE | B20: Process Manipulation | C20: T0843.002 | D20: Online Edit | E20: Enabling / prerequisite / S3 -> Supporting / impact / S5 | F20: In the Process Manipulation scenario this technique directly implements the adverse outcome, so it is staged S5 rather than inheriting its ATT&CK tactic. CRQ stage is scenario-specific.
A21: RESTAGE | B21: Process Manipulation | C21: T0848 | D21: Rogue Master | E21: Enabling / prerequisite / S1 -> Supporting / impact / S5 | F21: In the Process Manipulation scenario this technique directly implements the adverse outcome, so it is staged S5 rather than inheriting its ATT&CK tactic. CRQ stage is scenario-specific.
A22: ADD | B22: Loss of Control or Visibility | C22: T1691.001 | D22: Command Message | E22: Supporting / impact / S5 | F22: Block Command Message can cause loss or denial of operator control.
A23: ADD | B23: Loss of Control or Visibility | C23: T1691.002 | D23: Reporting Message | E23: Supporting / impact / S5 | F23: Block Reporting Message can cause loss of process visibility.
A24: ADD | B24: Loss of Control or Visibility | C24: T1692.002 | D24: Reporting Message | E24: Supporting / impact / S5 | F24: Unauthorized Reporting Message falsifies process telemetry presented to operators.
... A61: SUPPRESS-PARENT | B61: Process Manipulation | C61: T1694 | D61: Insecure Credentials | E61: Enabling / prerequisite -> Excluded — parent/sub duplicate | F61: sub-techniques mapped in this scenario

Sheet OT PACK - Loaded Registry
A1: 28 — Sector & Asset Pack Registry
A2: Purpose: Govern the facility-level sector and asset-type packs used by the common OT-CRQ model without duplicating the engine or BIA.
A3: In plain English: select Sector and Plant / Asset Type on 03. This registry resolves the pack, records calibration status, and supplies the asset-type frequency overlay for the companion engine.
A4: SHEET TYPE: MODEL ASSUMPTIONS / SECTOR PACK GOVERNANCE
A5: Inputs / upstream sources
A6: 03 Facility Inputs, 06 Frequency Assumptions, NIST/DOE/API sector guidance, internal incident evidence and structured expert elicitation.
A7: Calculation / decision logic
A8: Common engine and 18-driver BIA are retained. Intended actor intensity = reference λ × facility exposure × Σ(actor share × threat activity × sector × asset type × geography). Apply the asset-type multiplier exactly once.
A9: Key assumptions / defaults
A10: Power Generation remains the V1.6 reference pack. Energy Assets and Manufacturing are now working v1.0 packs with explicit threat/frequency overlays, BIA starting points and sector evidence. EA/MF remain controlled working calibrations and must not be described as externally validated.
A11: Outputs / downstream use
A12: Resolves the selected pack on 03, provides governed asset-type values, and documents the calibration status required by the Python engine.
A13: Workbook convention: yellow cells / blue font are editable calibration assumptions. Development-pack outputs require a compatible engine rerun and pack-level approval.
A15: Sector | B15: Pack ID | C15: Version | D15: Pack status | E15: Frequency treatment | F15: BIA treatment | G15: TTP treatment | H15: Primary evidence
A16: Power Generation | B16: PG-v1.6 | C16: 1.6 | D16: Reference pack / working calibration | E16: V1.6 0.55 reference λ; sector actor multipliers 1.00 / 1.00 / 1.00 | F16: Common 18-driver V1.6 BIA + formalised PG guidance on sheet 30 | G16: Common ATT&CK for ICS mapping + facility gates + PG emphasis | H16: NIST SP 800-82; DOE C2M2; MITRE ATT&CK for ICS
A17: Energy Assets | B17: EA-v1.0 | C17: 1.0 | D17: Working pack — controlled calibration | E17: 0.55 reference λ + sector actor overlay 1.15 NS / 1.00 CC / 1.00 Insider | F17: Common 18-driver BIA + energy scenario/BIA guidance on sheet 31 | G17: Common ATT&CK for ICS + facility gates + energy rationale/emphasis | H17: DOE C2M2; API 1164; NIST SP 800-82; MITRE ATT&CK for ICS
A18: Manufacturing | B18: MF-v1.0 | C18: 1.0 | D18: Working pack — controlled calibration | E18: 0.55 reference λ + sector actor overlay 0.85 NS / 1.25 CC / 1.00 Insider | F18: Common 18-driver BIA + manufacturing scenario guidance; quality/WIP extension flagged | G18: Common ATT&CK for ICS + facility gates + manufacturing rationale/emphasis | H18: NIST IR 8183; NIST SP 1800-10; NIST SP 800-82; MITRE ATT&CK for ICS
A22: REGISTERED ASSET TYPES
A24: Sector | B24: Plant / asset type | C24: Pack ID | D24: Operating profile | E24: Safety / protection context | F24: BIA treatment | G24: Calibration status
A25: Power Generation | B25: CCGT | C25: PG-v1.6 | D25: Continuous generation | E25: Protection / trip systems | F25: Existing V1.6 reference asset type | G25: Reference model working prior
A26: Power Generation | B26: OCGT | C26: PG-v1.6 | D26: Peaking generation | E26: Protection / trip systems | F26: Use facility downtime and capacity inputs | G26: Development archetype
A27: Power Generation | B27: Coal/Oil Thermal | C27: PG-v1.6 | D27: Continuous generation | E27: Protection / trip systems | F27: Use facility downtime and capacity inputs | G27: Development archetype
A28: Power Generation | B28: Nuclear | C28: PG-v1.6 | D28: Continuous generation | E28: Safety and protection systems | F28: Requires separate nuclear-sector validation before production use | G28: Restricted development archetype
A29: Power Generation | B29: Hydro | C29: PG-v1.6 | D29: Generation and water-control operation | E29: Protection / trip systems | F29: Use facility downtime and capacity inputs | G29: Development archetype
A30: Power Generation | B30: Renewables | C30: PG-v1.6 | D30: Distributed or central generation | E30: Protection / trip systems | F30: Use facility downtime and capacity inputs | G30: Development archetype
A31: Energy Assets | B31: Upstream Onshore | C31: EA-v1.0 | D31: Production and gathering | E31: Process safety / ESD where present | F31: Current 18-driver BIA retained | G31: Working pack v1.0 — facility calibration required
A32: Energy Assets | B32: Upstream Offshore | C32: EA-v1.0 | D32: Offshore production | E32: Process safety / ESD where present | F32: Current 18-driver BIA retained | G32: Working pack v1.0 — facility calibration required
A33: Energy Assets | B33: Pipeline/Storage/Terminal | C33: EA-v1.0 | D33: Distributed transport and storage | E33: SCADA protection / ESD where present | F33: Current 18-driver BIA retained | G33: Working pack v1.0 — facility calibration required
A34: Energy Assets | B34: Refinery/Petrochemical | C34: EA-v1.0 | D34: Continuous process operation | E34: SIS / ESD / fire-and-gas where present | F34: Current 18-driver BIA retained | G34: Working pack v1.0 — facility calibration required
A35: Energy Assets | B35: LNG | C35: EA-v1.0 | D35: Liquefaction, storage or regasification | E35: SIS / ESD / fire-and-gas where present | F35: Current 18-driver BIA retained | G35: Working pack v1.0 — facility calibration required
... A39: Manufacturing | B39: Hybrid Manufacturing | C39: MF-v1.0 | D39: Mixed process and discrete production | E39: Process and machine safeguards where present | F39: Current 18-driver BIA retained | G39: Working pack v1.0 — facility calibration required
A42: ASSET-TYPE FREQUENCY OVERLAY — EXPLICIT WORKING PRIORS
A44: Sector | B44: Plant / asset type | C44: Nation State | D44: Cybercriminal | E44: Malicious Insider | F44: Parameter type | G44: Status | H44: Rationale / how used | I44: Evidence requirement
A45: Power Generation | B45: CCGT | C45: 1 | D45: 1 | E45: 1 | F45: Calibration parameter | G45: Reference | H45: Multiplies the actor-specific sector intensity after the selected sector row. Neutral 1.00 avoids unsupported differentiation. | I45: Replace only with a compatible facility-year denominator or approved structured elicitation.
A46: Power Generation | B46: OCGT | C46: 1 | D46: 1 | E46: 1 | F46: Calibration parameter | G46: Working prior | H46: Multiplies the actor-specific sector intensity after the selected sector row. Neutral 1.00 avoids unsupported differentiation. | I46: Replace only with a compatible facility-year denominator or approved structured elicitation.
A47: Power Generation | B47: Coal/Oil Thermal | C47: 1 | D47: 1 | E47: 1 | F47: Calibration parameter | G47: Working prior | H47: Multiplies the actor-specific sector intensity after the selected sector row. Neutral 1.00 avoids unsupported differentiation. | I47: Replace only with a compatible facility-year denominator or approved structured elicitation.
A48: Power Generation | B48: Nuclear | C48: 1 | D48: 1 | E48: 1 | F48: Calibration parameter | G48: Working prior | H48: Multiplies the actor-specific sector intensity after the selected sector row. Neutral 1.00 avoids unsupported differentiation. | I48: Replace only with a compatible facility-year denominator or approved structured elicitation.
A49: Power Generation | B49: Hydro | C49: 1 | D49: 1 | E49: 1 | F49: Calibration parameter | G49: Working prior | H49: Multiplies the actor-specific sector intensity after the selected sector row. Neutral 1.00 avoids unsupported differentiation. | I49: Replace only with a compatible facility-year denominator or approved structured elicitation.
A50: Power Generation | B50: Renewables | C50: 1 | D50: 1 | E50: 1 | F50: Calibration parameter | G50: Working prior | H50: Multiplies the actor-specific sector intensity after the selected sector row. Neutral 1.00 avoids unsupported differentiation. | I50: Replace only with a compatible facility-year denominator or approved structured elicitation.
A51: Energy Assets | B51: Upstream Onshore | C51: 1 | D51: 1 | E51: 1 | F51: Calibration parameter | G51: Working pack v1.0 | H51: Asset-type multiplier remains neutral 1.00. Sector differentiation is applied at actor level; do not infer unsupported within-sector differences without a compatible denominator. | I51: Replace the neutral asset-type multiplier only with a compatible facility-year denominator or approved structured elicitation. Sector threat differences are handled separately at actor level.
A52: Energy Assets | B52: Upstream Offshore | C52: 1 | D52: 1 | E52: 1 | F52: Calibration parameter | G52: Working pack v1.0 | H52: Asset-type multiplier remains neutral 1.00. Sector differentiation is applied at actor level; do not infer unsupported within-sector differences without a compatible denominator. | I52: Replace the neutral asset-type multiplier only with a compatible facility-year denominator or approved structured elicitation. Sector threat differences are handled separately at actor level.
