Workbook

Sheet 00 Pack Guide
A1: IT Sector Pack - Financial Services - v1.1.1
A2: Orientation for the pack owner. Lists what this Financial Services pack contains and what belongs in the assessment workbook instead.
A3: This workbook contains Financial Services reference calibration. Do not enter client-specific or assessment-specific data in this workbook.
A4: SHEET TYPE: MODEL DOCUMENTATION
A6: Purpose
A7: Supply broad Financial Services actor, scenario, route, control and impact assumptions.
A9: Calculation / decision logic
A10: Python validates schema, evidence grades, route-stage coverage, mappings and conditional distributions before simulation.
A12: Outputs / downstream use
A13: Loaded by Guided_IT_CRQ_Model_v1_1_1.xlsx. The prepare command resizes the main workbook from any conformant sector pack.
A15: Workbook convention
A16: Yellow cells with blue font are editable. Engine results and resolved pack values are not manually editable.
A20: PACK DESIGN PRINCIPLES
A21: 1 | B21: One common IT-CRQ engine; packs contain data and rationale only.
A22: 2 | B22: No product-specific or banking-subsector engines.
A23: 3 | B23: Actor, scenario and route weights are conditional distributions and are validated to sum to 100%.
A24: 4 | B24: Reference controls prevent comparison against an unrealistic zero-control organisation.
A25: 5 | B25: Impact assumptions follow a transparent Base/P99 driver structure inspired by the supplied Balbix model.
A26: 6 | B26: All working priors remain editable and must be approved before external use.

Sheet 01 Pack Metadata
A1: 01 — Pack Metadata
A2: Identity, schema, minimum engine version, status and unit of analysis for this pack.
A3: How used in the model: Validated fail-closed before any other pack table is used. Mismatched PACK_ID, SECTOR, DOMAIN or SCHEMA_VERSION stops the run.
A14: DOMAIN | B14: IT
A15: Key | B15: Value | C15: Description | D15: Evidence grade | E15: Source ID
A16: PACK_ID | B16: FS-v1.1.1 | C16: Unique pack identifier | D16: D | E16: SRC-10
A17: SECTOR | B17: Financial Services | C17: Exact main-workbook sector selection | D17: D | E17: SRC-10
A18: PACK_VERSION | B18: 1.1.1 | C18: Pack content version | D18: D | E18: SRC-10
A19: SCHEMA_VERSION | B19: CRQ-PACK-1.1 | C19: Required table schema | D19: D | E19: SRC-10
A20: MIN_ENGINE_VERSION | B20: 1.1.1 | C20: Minimum compatible Python engine | D20: D | E20: SRC-10
A21: STATUS | B21: Development — working priors; calibration required | C21: Must not be described as externally validated | D21: D | E21: SRC-10
A22: RISK_DOMAIN | B22: IT | C22: Pack content domain | D22: D | E22: SRC-10
A23: UNIT_OF_ANALYSIS | B23: Organisation | C23: Frequency denominator | D23: D | E23: SRC-10
A24: ATTACK_DOMAIN | B24: Enterprise | C24: MITRE ATT&CK domain | D24: C | E24: SRC-01
A25: REFERENCE_CAMPAIGNS_PER_YEAR | B25: 1 | C25: Material-campaign arrival-rate prior per organisation-year | D25: D | E25: SRC-10
A26: DEFAULT_PRUDENCE_FACTOR | B26: 1.25 | C26: Separate frequency prudence factor | D26: D | E26: SRC-10
A27: CONTROL_AGG_INCREMENT | B27: 0.25 | C27: Diminishing-return increment after first mapped control | D27: D | E27: SRC-10
A28: CONTROL_ADJ_FLOOR | B28: 0.4 | C28: Reference-relative control-ratio lower bound | D28: D | E28: SRC-10
A29: CONTROL_ADJ_CEILING | B29: 2 | C29: Reference-relative control-ratio upper bound | D29: D | E29: SRC-10
A30: DURATION_FACTOR_FLOOR | B30: 0.4 | C30: Minimum duration-loss factor | D30: D | E30: SRC-10
A31: EXPOSURE_FACTOR_FLOOR | B31: 0.4 | C31: Minimum exposure-loss factor | D31: D | E31: SRC-10
A32: CONSEQUENCE_FACTOR_FLOOR | B32: 0.4 | C32: Minimum direct-consequence factor | D32: D | E32: SRC-10
A33: CONSEQUENCE_FACTOR_CEILING | B33: 2 | C33: Maximum direct-consequence factor | D33: D | E33: SRC-10
A34: LOSS_BLOCK_RHO | B34: 0.5 | C34: Within-event dependence across loss blocks | D34: D | E34: SRC-10
A35: CREATED_DATE | B35: 2026-08-21 | C35: Pack creation date | D35: D | E35: SRC-10
A36: DESCRIPTION | B36: Broad Financial Services profile | C36: No granular banking/insurance sub-packs | D36: D | E36: SRC-10
A37: CONTROL_BARRIER_CAP | B37: 0.95 | C37: Maximum aggregate control barrier; no control combination is treated as perfect | D37: D | E37: SRC-10

Sheet 02 Actor Weights
A1: 02 — Threat-Actor Weights
A2: Reference mix of material campaigns across the four IT threat actors for a broad Financial Services organisation.
A3: How used in the model: it_crq uses these weights as the actor campaign mix (they should sum to 1). Assessment overlays on IT 07 can scale activity but do not replace this mix unless an override is provided.
A4: Proposed: 10% / 80% / 8% / 2% (Nation-state / Cybercriminal / Insider / Hacktivist).
A5: The proposed shift is directionally informed by Verizon’s Financial & Insurance breach data and cross-checked against Mandiant’s more targeted investigation population, which shows a larger espionage component. The reduction in hacktivist share follows from the limited ideological/disruptive motive observed once financial and espionage motives are considered. The exact allocation remains a structured working prior rather than a direct transformation of either dataset.
A6: Supporting evidence
A7: Verizon 2026 DBIR Executive Summary Financial and Insurance (p.14)
A8: Mandiant M-Trends 2026
A9: Microsoft Digital Defense Report 2025
A15: Actor ID | B15: Threat actor | C15: Weight | D15: Basis / limitation | E15: Evidence grade | F15: Source ID
A16: A_NS | B16: Nation-state | C16: 0.1 | D16: Working prior; broad FS sector context, not an observed annual incident share. | E16: D | F16: SRC-10
A17: A_CC | B17: Cybercriminal | C17: 0.8 | D17: Working prior reflecting financially motivated disruption, data compromise and theft routes. | E17: D | F17: SRC-10
A18: A_MI | B18: Malicious insider | C18: 0.08 | D18: Working prior for authorised-access misuse and collusion. | E18: D | F18: SRC-10
A19: A_HA | B19: Hacktivist | C19: 0.02 | D19: Working prior reflecting direct-availability and public-service targeting. | E19: D | F19: SRC-04; SRC-05
A20: CHECK | B20: Total | C20: =SUM(C16:C19) -> 1 | D20: Must equal 100%

Sheet 03 Actor Scenario
A1: 03 — Actor-to-Scenario Propensity
A2: For each actor, the conditional share of campaigns that lead to each of the four IT loss scenarios.
A3: How used in the model: Combined with actor weights and route propensities to build actor–scenario–route cells that the Monte Carlo simulates.
A5: Each actor's conditional distribution across the four FS loss scenarios. E.g. Hacktivist 75%/15%/8%/2% (Disruption/Data/Integrity/Fraud); Cybercriminal 30%/25%/10%/35%; Nation-state 25%/35%/30%/10%; Malicious Insider 20%/30%/25%/25%.
A6: The pattern is well supported directionally: hacktivists overwhelmingly pursue disruption rather than monetisable fraud — CISA and the FBI's joint advisory on pro-Russia hacktivist groups describes DDoS, defacement and “hack-and-leak” publicity operations as their dominant playbook, with fraud essentially absent from that threat picture. Cybercriminals split across data theft and fraud, consistent with the financial-motive evidence already used for the actor mix (Section 2.1). Nation-state actors weight toward data and integrity compromise over disruption, consistent with Mandiant and Microsoft's framing of state actors as primarily intelligence-driven. The insider row's more even split matches CERT/Secret Service research on financial-sector insider fraud, which documents both direct monetary fraud and data theft for resale, with a smaller but real sabotage/integrity component tied to grievance-driven incidents. As with the actor mix itself, this is Evidence Grade D — the direction is evidenced, the exact percentages are structured judgement.
A7: Supporting evidence
A8: CISA/FBI Pro-Russia Hacktivists Conduct Opportunistic Attacks Against Critical Infrastructure
A9: CMU SEI Insider Fraud in Financial Services (National Insider Threat Center)
A10: Mandiant M-Trends 2026
A15: Actor ID | B15: SC_DISR | C15: SC_DATA | D15: SC_INT | E15: SC_FRAUD | F15: Row total
A16: A_NS | B16: 0.25 | C16: 0.35 | D16: 0.3 | E16: 0.1 | F16: =SUM(B16:E16) -> 1
A17: A_CC | B17: 0.3 | C17: 0.25 | D17: 0.1 | E17: 0.35 | F17: =SUM(B17:E17) -> 1
A18: A_MI | B18: 0.2 | C18: 0.3 | D18: 0.25 | E18: 0.25 | F18: =SUM(B18:E18) -> 1
A19: A_HA | B19: 0.75 | C19: 0.15 | D19: 0.08 | E19: 0.02 | F19: =SUM(B19:E19) -> 1

Sheet 04 Route Definitions
A1: 04 — Route Definitions
A2: Stable identifiers and descriptions of the composite IT attack routes (identity, endpoint, exploit, supply chain, DDoS, insider).
A3: How used in the model: Route IDs key sheets 05–07 and 13. The engine does not invent routes that are not listed here.
A15: Route ID | B15: Attack route | C15: Definition | D15: Evidence grade | E15: Source ID
A16: R_ID | B16: Identity and credential compromise | C16: Phishing, credential theft, valid accounts and cloud/SaaS identity abuse. | D16: C | E16: SRC-01; SRC-04
A17: R_USER | B17: User endpoint and social engineering | C17: User interaction leading to endpoint execution, privilege and movement. | D17: C | E17: SRC-01; SRC-04
A18: R_EXP | B18: Public-facing application exploitation | C18: Exploitation of internet-facing applications, APIs, appliances and remote services. | D18: C | E18: SRC-01; SRC-04
A19: R_TP | B19: Third-party or software supply chain | C19: Trusted relationship, delegated access, managed service or software compromise. | D19: C | E19: SRC-01; SRC-04
A20: R_DDOS | B20: Direct availability or DDoS | C20: Direct network or endpoint denial of public digital services. | D20: C | E20: SRC-01; SRC-05
A21: R_INS | B21: Insider or trusted access | C21: Authorised or collusive access used to manipulate, disclose, disrupt or steal. | D21: C | E21: SRC-01; SRC-04

Sheet 05 Actor Route
A1: 05 — Actor-to-Route Propensity
A2: Reference distribution of each actor’s campaigns across composite routes.
A3: How used in the model: Multiplied with scenario-route propensity and normalised so each actor–scenario pair has a coherent route mix.
A4: Each actor's reference distribution across the six FS attack routes. E.g. Malicious Insider 87% via R_INS (trusted access); Hacktivist 60% via R_DDOS; Nation-state and Cybercriminal both weighted toward R_ID (identity/credential compromise).
A5: The insider row is close to definitionally true — an actor who already holds trusted access predominantly manifests through the insider route rather than needing an external one — so it needs little external justification beyond internal consistency. The hacktivist DDoS weighting is directly evidenced by the same CISA/FBI advisory cited in 2.5. Nation-state and cybercriminal weighting toward identity/credential compromise is consistent with Verizon's and Mandiant's initial-access vector data. Relative ordering is well evidenced; exact percentages remain Grade D.
A6: Supporting evidence
A7: CISA/FBI Pro-Russia Hacktivists Conduct Opportunistic Attacks Against Critical Infrastructure
A8: Verizon 2026 Data Breach Investigations Report
A15: Actor ID | B15: R_ID | C15: R_USER | D15: R_EXP | E15: R_TP | F15: R_DDOS | G15: R_INS | H15: Row total
A16: A_NS | B16: 0.25 | C16: 0.15 | D16: 0.25 | E16: 0.25 | F16: 0.05 | G16: 0.05 | H16: =SUM(B16:G16) -> 1
A17: A_CC | B17: 0.3 | C17: 0.25 | D17: 0.22 | E17: 0.1 | F17: 0.08 | G17: 0.05 | H17: =SUM(B17:G17) -> 1
A18: A_MI | B18: 0.05 | C18: 0.03 | D18: 0 | E18: 0.05 | F18: 0 | G18: 0.87 | H18: =SUM(B18:G18) -> 1
A19: A_HA | B19: 0.1 | C19: 0.08 | D19: 0.15 | E19: 0.05 | F19: 0.6 | G19: 0.02 | H19: =SUM(B19:G19) -> 1

Sheet 06 Scenario Route
A1: 06 — Scenario-to-Route Propensity
A2: Reference distribution of each loss scenario across composite routes.
A3: How used in the model: Combined with actor-route propensity; the product is the route mix used for TTP and control calculations.
A5: Each loss scenario's reference distribution across the six attack routes. R_DDOS contributes 0% to SC_DATA, SC_INT and SC_FRAUD and only to SC_DISR (20%).
A6: This table is largely a structural constraint rather than an externally evidenced probability: it encodes which routes are mechanically capable of producing which loss outcome. The DDoS-to-disruption-only pattern mirrors MITRE ATT&CK's separation of the Impact tactic's availability techniques (e.g. Network/Endpoint Denial of Service) from data-manipulation and exfiltration techniques — DDoS cannot mechanically produce a confidentiality or integrity loss, so its 0% weighting elsewhere is a structural constraint, not a calibrated probability, and is a good internal-consistency check on the table. The relative weighting of the remaining routes (e.g. R_ID highest for SC_FRAUD at 35%, consistent with credential-enabled account-takeover fraud) draws on the same route-prevalence evidence used elsewhere in this document.
A7: Supporting evidence
A8: MITRE ATT&CK Enterprise Matrix (Impact tactic)
A9: Verizon 2026 Data Breach Investigations Report
A15: Scenario ID | B15: R_ID | C15: R_USER | D15: R_EXP | E15: R_TP | F15: R_DDOS | G15: R_INS | H15: Row total
A16: SC_DISR | B16: 0.15 | C16: 0.22 | D16: 0.23 | E16: 0.15 | F16: 0.2 | G16: 0.05 | H16: =SUM(B16:G16) -> 1
A17: SC_DATA | B17: 0.3 | C17: 0.22 | D17: 0.23 | E17: 0.17 | F17: 0 | G17: 0.08 | H17: =SUM(B17:G17) -> 1
A18: SC_INT | B18: 0.22 | C18: 0.15 | D18: 0.2 | E18: 0.2 | F18: 0 | G18: 0.23 | H18: =SUM(B18:G18) -> 1
A19: SC_FRAUD | B19: 0.35 | C19: 0.15 | D19: 0.12 | E19: 0.1 | F19: 0 | G19: 0.28 | H19: =SUM(B19:G19) -> 1

Sheet 07 Stage Requirements
A1: 07 — Scenario-Aware Stage Requirements
A2: Which of the five composite stages are required for each scenario–route pair (ALL rows, with optional actor overrides).
A3: How used in the model: Gates the attack path: a required stage with no viable TTP fails the path. Not an assessment input sheet.
A15: Route ID | B15: Scenario ID | C15: Actor ID | D15: S1 | E15: S2 | F15: S3 | G15: S4 | H15: S5 | I15: Rationale | J15: Evidence grade | K15: Source ID | L15: Override rule
A16: R_ID | B16: SC_DISR | C16: ALL | D16: 1 | E16: 0 | F16: 1 | G16: 1 | H16: 1 | I16: Scenario-route mask; actor-specific rows may override ALL. | J16: D | K16: SRC-10 | L16: Exact actor row overrides ALL
A17: R_ID | B17: SC_DATA | C17: ALL | D17: 1 | E17: 0 | F17: 1 | G17: 1 | H17: 1 | I17: Scenario-route mask; actor-specific rows may override ALL. | J17: D | K17: SRC-10 | L17: Exact actor row overrides ALL
A18: R_ID | B18: SC_INT | C18: ALL | D18: 1 | E18: 0 | F18: 1 | G18: 1 | H18: 1 | I18: Scenario-route mask; actor-specific rows may override ALL. | J18: D | K18: SRC-10 | L18: Exact actor row overrides ALL
A19: R_ID | B19: SC_FRAUD | C19: ALL | D19: 1 | E19: 0 | F19: 1 | G19: 0 | H19: 1 | I19: Scenario-route mask; actor-specific rows may override ALL. | J19: D | K19: SRC-10 | L19: Exact actor row overrides ALL
A20: R_USER | B20: SC_DISR | C20: ALL | D20: 1 | E20: 1 | F20: 1 | G20: 1 | H20: 1 | I20: Scenario-route mask; actor-specific rows may override ALL. | J20: D | K20: SRC-10 | L20: Exact actor row overrides ALL
A21: R_USER | B21: SC_DATA | C21: ALL | D21: 1 | E21: 1 | F21: 1 | G21: 1 | H21: 1 | I21: Scenario-route mask; actor-specific rows may override ALL. | J21: D | K21: SRC-10 | L21: Exact actor row overrides ALL
A22: R_USER | B22: SC_INT | C22: ALL | D22: 1 | E22: 1 | F22: 1 | G22: 1 | H22: 1 | I22: Scenario-route mask; actor-specific rows may override ALL. | J22: D | K22: SRC-10 | L22: Exact actor row overrides ALL
A23: R_USER | B23: SC_FRAUD | C23: ALL | D23: 1 | E23: 1 | F23: 0 | G23: 0 | H23: 1 | I23: Scenario-route mask; actor-specific rows may override ALL. | J23: D | K23: SRC-10 | L23: Exact actor row overrides ALL
A24: R_EXP | B24: SC_DISR | C24: ALL | D24: 1 | E24: 1 | F24: 1 | G24: 1 | H24: 1 | I24: Scenario-route mask; actor-specific rows may override ALL. | J24: D | K24: SRC-10 | L24: Exact actor row overrides ALL
A25: R_EXP | B25: SC_DATA | C25: ALL | D25: 1 | E25: 1 | F25: 1 | G25: 1 | H25: 1 | I25: Scenario-route mask; actor-specific rows may override ALL. | J25: D | K25: SRC-10 | L25: Exact actor row overrides ALL
A26: R_EXP | B26: SC_INT | C26: ALL | D26: 1 | E26: 1 | F26: 1 | G26: 1 | H26: 1 | I26: Scenario-route mask; actor-specific rows may override ALL. | J26: D | K26: SRC-10 | L26: Exact actor row overrides ALL
A27: R_EXP | B27: SC_FRAUD | C27: ALL | D27: 1 | E27: 1 | F27: 1 | G27: 1 | H27: 1 | I27: Scenario-route mask; actor-specific rows may override ALL. | J27: D | K27: SRC-10 | L27: Exact actor row overrides ALL
... A39: R_INS | B39: SC_FRAUD | C39: ALL | D39: 0 | E39: 0 | F39: 1 | G39: 0 | H39: 1 | I39: Scenario-route mask; actor-specific rows may override ALL. | J39: D | K39: SRC-10 | L39: Exact actor row overrides ALL

Sheet 08 Stage Priors
A1: 08 — Reference Stage-Through Priors
A2: Reference stage-through probabilities after the pack’s reference control profile.
A3: How used in the model: Used as the prior; assessed control maturity on IT 05 adjusts through-probabilities relative to this reference, not relative to zero controls.
A15: Route ID | B15: Route | C15: S1 | D15: S2 | E15: S3 | F15: S4 | G15: S5
A16: R_ID | B16: Identity and credential compromise | C16: 0.3 | D16: 1 | E16: 0.55 | F16: 0.55 | G16: 0.65
A17: R_USER | B17: User endpoint and social engineering | C17: 0.35 | D17: 0.6 | E17: 0.45 | F17: 0.45 | G17: 0.6
A18: R_EXP | B18: Public-facing application exploitation | C18: 0.25 | D18: 0.6 | E18: 0.5 | F18: 0.45 | G18: 0.6
A19: R_TP | B19: Third-party or software supply chain | C19: 1 | D19: 1 | E19: 0.55 | F19: 0.55 | G19: 0.65
A20: R_DDOS | B20: Direct availability or DDoS | C20: 0.6 | D20: 1 | E20: 1 | F20: 1 | G20: 0.6
A21: R_INS | B21: Insider or trusted access | C21: 1 | D21: 1 | E21: 0.7 | F21: 0.65 | G21: 0.65

Sheet 09 Scenario Parameters
A1: 09 — Scenario Impact Parameters
A2: P50/P99 scenario quantities (shares, days, direct amounts) with evidence grades.
A3: How used in the model: Scaled by organisation size from IT 03 to produce event-loss distributions. Blank assessment overrides on IT 06 keep these pack values.
A15: Scenario ID | B15: Scenario | C15: IR_DAYS_P50 | D15: IR_DAYS_P99 | E15: CYBER_DAYS_P50 | F15: CYBER_DAYS_P99 | G15: LEGAL_DAYS_P50 | H15: LEGAL_DAYS_P99 | I15: RESTORE_DAYS_P50 | J15: RESTORE_DAYS_P99 | K15: DOWNTIME_DAYS_P50 | L15: DOWNTIME_DAYS_P99 | M15: AFFECTED_SERVICE_SHARE_P50 | N15: AFFECTED_SERVICE_SHARE_P99 | O15: AFFECTED_RECORD_SHARE_P50 | P15: AFFECTED_RECORD_SHARE_P99 | Q15: AFFECTED_ENDPOINT_SHARE_P50 | R15: AFFECTED_ENDPOINT_SHARE_P99 | S15: AFFECTED_SERVER_SHARE_P50 | T15: AFFECTED_SERVER_SHARE_P99 | U15: REGULATORY_REVENUE_SHARE_P50 | V15: REGULATORY_REVENUE_SHARE_P99 | W15: PAYMENT_FLOW_DAYS_P50 | X15: PAYMENT_FLOW_DAYS_P99 | Y15: DIVERTED_SHARE_P50 | Z15: DIVERTED_SHARE_P99 | AA15: FRAUD_RECOVERY_RATE_P50 | AB15: FRAUD_RECOVERY_RATE_P99 | AC15: MONITORING_TAKEUP_P50 | AD15: MONITORING_TAKEUP_P99 | AE15: EXTORTION_DIRECT_P50 | AF15: EXTORTION_DIRECT_P99 | AG15: POST_EVENT_REVENUE_SHARE_P50 | AH15: POST_EVENT_REVENUE_SHARE_P99 | AI15: CHURN_REVENUE_SHARE_P50 | AJ15: CHURN_REVENUE_SHARE_P99 | AK15: Evidence grade | AL15: Source ID
A16: SC_DISR | B16: Critical business-service disruption | C16: 10 | D16: 60 | E16: 10 | F16: 90 | G16: 5 | H16: 45 | I16: 15 | J16: 120 | K16: 3 | L16: 30 | M16: 0.3 | N16: 0.85 | O16: 0 | P16: 0.05 | Q16: 0.1 | R16: 0.5 | S16: 0.1 | T16: 0.6 | U16: 0 | V16: 0.002 | W16: 0 | X16: 0 | Y16: 0 | Z16: 0 | AA16: 0 | AB16: 0 | AC16: 0.05 | AD16: 0.2 | AE16: 1000000 | AF16: 20000000 | AG16: 0.0005 | AH16: 0.005 | AI16: 0.001 | AJ16: 0.01 | AK16: D | AL16: SRC-10
A17: SC_DATA | B17: Sensitive-data compromise | C17: 20 | D17: 120 | E17: 30 | F17: 180 | G17: 30 | H17: 180 | I17: 20 | J17: 120 | K17: 1 | L17: 10 | M17: 0.1 | N17: 0.4 | O17: 0.05 | P17: 0.8 | Q17: 0.05 | R17: 0.3 | S17: 0.05 | T17: 0.25 | U17: 0.001 | V17: 0.01 | W17: 0 | X17: 0 | Y17: 0 | Z17: 0 | AA17: 0 | AB17: 0 | AC17: 0.1 | AD17: 0.25 | AE17: 500000 | AF17: 10000000 | AG17: 0.001 | AH17: 0.008 | AI17: 0.002 | AJ17: 0.03 | AK17: D | AL17: SRC-10
A18: SC_INT | B18: Data or transaction-integrity compromise | C18: 15 | D18: 90 | E18: 20 | F18: 150 | G18: 20 | H18: 120 | I18: 20 | J18: 150 | K18: 2 | L18: 20 | M18: 0.2 | N18: 0.7 | O18: 0 | P18: 0.1 | Q18: 0.1 | R18: 0.4 | S18: 0.1 | T18: 0.5 | U18: 0.0005 | V18: 0.006 | W18: 2 | X18: 10 | Y18: 0.005 | Z18: 0.05 | AA18: 0.8 | AB18: 0.3 | AC18: 0.05 | AD18: 0.2 | AE18: 0 | AF18: 0 | AG18: 0.001 | AH18: 0.008 | AI18: 0.001 | AJ18: 0.02 | AK18: D | AL18: SRC-10
A19: SC_FRAUD | B19: Cyber-enabled theft or fraud | C19: 10 | D19: 60 | E19: 10 | F19: 90 | G19: 15 | H19: 90 | I19: 5 | J19: 60 | K19: 0 | L19: 5 | M19: 0 | N19: 0.2 | O19: 0 | P19: 0.05 | Q19: 0.02 | R19: 0.15 | S19: 0.02 | T19: 0.1 | U19: 0.0002 | V19: 0.003 | W19: 2 | X19: 15 | Y19: 0.01 | Z19: 0.1 | AA19: 0.8 | AB19: 0.2 | AC19: 0.05 | AD19: 0.2 | AE19: 0 | AF19: 0 | AG19: 0.0005 | AH19: 0.005 | AI19: 0.001 | AJ19: 0.02 | AK19: D | AL19: SRC-10

Sheet 10 Driver Rates
A1: 10 — Impact Driver Rates
A2: Unit-cost and rate assumptions (notification, forensics, restoration, and so on) at P50/P99.
A3: How used in the model: Applied to the applicable loss blocks for each actor/scenario. Organisation overrides on IT 06 replace individual rates when populated.
A15: Rate ID | B15: Driver | C15: P50 | D15: P99 | E15: Unit | F15: Source / status | G15: Evidence grade | H15: Source ID
A16: NOTIFICATION_PER_RECORD | B16: Notification cost per affected record | C16: 0.5 | D16: 1 | E16: USD/record | G16: D | H16: SRC-07
A17: CREDIT_MONITORING_PER_RECORD | B17: Credit monitoring per participating record | C17: 8 | D17: 20 | E17: USD/record | G17: D | H17: SRC-07
A18: FORENSIC_DAILY | B18: Daily forensic investigation team | C18: 2000 | D18: 4000 | E18: USD/day | G18: D | H18: SRC-07
A19: EXTERNAL_CYBER_DAILY | B19: Daily external cyber response team | C19: 3000 | D19: 5000 | E19: USD/day | G19: D | H19: SRC-07
A20: RESTORATION_DAILY | B20: Daily data restoration team | C20: 2000 | D20: 4000 | E20: USD/day | G20: D | H20: SRC-07
A21: LEGAL_DAILY | B21: Daily external legal team | C21: 5000 | D21: 10000 | E21: USD/day | G21: D | H21: SRC-07
A22: ENDPOINT_REPAIR | B22: Endpoint repair/replacement unit cost | C22: 200 | D22: 500 | E22: USD/endpoint | G22: D | H22: SRC-07
A23: SERVER_REPAIR | B23: Server repair/replacement unit cost | C23: 5000 | D23: 8000 | E23: USD/server | G23: D | H23: SRC-07

Sheet 11 Impact Driver Matrix
A1: 11 — Actor and Scenario Impact Applicability
A2: Which loss blocks and drivers apply to each actor and scenario.
A3: How used in the model: Turns organisation scale and pack rates into the three IT loss blocks (duration, exposure, direct). Zeros here mean that driver is not modelled for that pair.
A15: Driver ID | B15: Driver | C15: Loss block | D15: Nation-state | E15: Cybercriminal | F15: Malicious insider | G15: Hacktivist | H15: SC_DISR | I15: SC_DATA | J15: SC_INT | K15: SC_FRAUD | L15: Evidence grade | M15: Source ID | N15: Rationale
A16: IR_FORENSICS | B16: Forensic investigation | C16: Duration | D16: 1 | E16: 1 | F16: 1 | G16: 1 | H16: 1 | I16: 1 | J16: 1 | K16: 1 | L16: D | M16: SRC-10 | N16: Response cost scales with investigation days.
A17: EXTERNAL_RESPONSE | B17: External cyber response | C17: Duration | D17: 1 | E17: 1 | F17: 1 | G17: 1 | H17: 1 | I17: 1 | J17: 1 | K17: 1 | L17: D | M17: SRC-10 | N17: Response support is applicable across material events.
A18: LEGAL_RESPONSE | B18: External legal response | C18: Duration | D18: 1 | E18: 1 | F18: 1 | G18: 1 | H18: 1 | I18: 1 | J18: 1 | K18: 1 | L18: D | M18: SRC-10 | N18: Legal support is applicable across material events.
A19: RESTORATION | B19: Restoration team | C19: Duration | D19: 1 | E19: 1 | F19: 1 | G19: 1 | H19: 1 | I19: 1 | J19: 1 | K19: 1 | L19: D | M19: SRC-10 | N19: Restoration cost scales with restoration days.
A20: BUSINESS_INTERRUPTION | B20: Business interruption | C20: Duration | D20: 1 | E20: 1 | F20: 1 | G20: 1 | H20: 1 | I20: 1 | J20: 1 | K20: 0 | L20: D | M20: SRC-10 | N20: Not a primary theft/fraud loss driver.
A21: ENDPOINT_RECOVERY | B21: Endpoint recovery | C21: Duration | D21: 1 | E21: 1 | F21: 1 | G21: 1 | H21: 1 | I21: 1 | J21: 1 | K21: 0 | L21: D | M21: SRC-10 | N21: Not a primary theft/fraud loss driver.
A22: SERVER_RECOVERY | B22: Server recovery | C22: Duration | D22: 1 | E22: 1 | F22: 1 | G22: 1 | H22: 1 | I22: 1 | J22: 1 | K22: 0 | L22: D | M22: SRC-10 | N22: Not a primary theft/fraud loss driver.
A23: NOTIFICATION | B23: Notification | C23: Exposure | D23: 1 | E23: 1 | F23: 1 | G23: 0 | H23: 0 | I23: 1 | J23: 0 | K23: 0 | L23: D | M23: SRC-10 | N23: Hacktivist campaigns excluded absent evidence of personal-data notification.
A24: CREDIT_MONITORING | B24: Credit monitoring | C24: Exposure | D24: 1 | E24: 1 | F24: 1 | G24: 0 | H24: 0 | I24: 1 | J24: 0 | K24: 0 | L24: D | M24: SRC-10 | N24: Monitoring take-up is distinct from notification population.
A25: REGULATORY | B25: Regulatory consequence | C25: Exposure | D25: 1 | E25: 1 | F25: 1 | G25: 1 | H25: 0 | I25: 1 | J25: 1 | K25: 1 | L25: D | M25: SRC-10 | N25: Applies to data, integrity and fraud events.
A26: CUSTOMER_ATTRITION | B26: Customer attrition | C26: Exposure | D26: 1 | E26: 1 | F26: 1 | G26: 1 | H26: 1 | I26: 1 | J26: 1 | K26: 1 | L26: D | M26: SRC-10 | N26: Post-event customer response can arise across material events.
A27: FRAUD_NET_RECOVERY | B27: Funds at risk net of recovery | C27: Direct | D27: 0 | E27: 1 | F27: 1 | G27: 0 | H27: 0 | I27: 0 | J27: 1 | K27: 1 | L27: D | M27: SRC-10 | N27: Limited to financially motivated or insider integrity/fraud events.
... A29: POST_EVENT_UPLIFT | B29: Post-event security uplift | C29: Direct | D29: 1 | E29: 1 | F29: 1 | G29: 1 | H29: 1 | I29: 1 | J29: 1 | K29: 1 | L29: D | M29: SRC-10 | N29: Direct post-event remediation expenditure.

Sheet 12 TTP Catalogue
A1: 12 — Enterprise ATT&CK Catalogue
A2: Enterprise ATT&CK techniques in scope for this pack, with actor and scenario applicability.
A3: How used in the model: Techniques that are not applicable are excluded from the route path. Weights and barriers still come from sheets 13 and 15.
A15: TTP ID | B15: Technique | C15: Stage | D15: Platforms | E15: MITRE URL | F15: Nation-state | G15: Cybercriminal | H15: Malicious insider | I15: Hacktivist | J15: SC_DISR | K15: SC_DATA | L15: SC_INT | M15: SC_FRAUD
A16: T1566 | B16: Phishing | C16: S1 | D16: Windows; SaaS; Office Suite | E16: https://attack.mitre.org/techniques/T1566/ | F16: 1 | G16: 1 | H16: 1 | I16: 1 | J16: 1 | K16: 1 | L16: 1 | M16: 1
A17: T1078 | B17: Valid Accounts | C17: S1 | D17: Identity Provider; SaaS; IaaS; Windows | E17: https://attack.mitre.org/techniques/T1078/ | F17: 1 | G17: 1 | H17: 1 | I17: 1 | J17: 1 | K17: 1 | L17: 1 | M17: 1
A18: T1110 | B18: Brute Force | C18: S1 | D18: Identity Provider; SaaS; Windows | E18: https://attack.mitre.org/techniques/T1110/ | F18: 1 | G18: 1 | H18: 0 | I18: 1 | J18: 1 | K18: 1 | L18: 1 | M18: 1
A19: T1190 | B19: Exploit Public-Facing Application | C19: S1 | D19: Network Devices; SaaS; IaaS | E19: https://attack.mitre.org/techniques/T1190/ | F19: 1 | G19: 1 | H19: 0 | I19: 1 | J19: 1 | K19: 1 | L19: 1 | M19: 1
A20: T1498 | B20: Network Denial of Service | C20: S1 | D20: Network Devices | E20: https://attack.mitre.org/techniques/T1498/ | F20: 1 | G20: 1 | H20: 0 | I20: 1 | J20: 1 | K20: 0 | L20: 0 | M20: 0
A21: T1203 | B21: Exploitation for Client Execution | C21: S2 | D21: Windows; macOS; Linux | E21: https://attack.mitre.org/techniques/T1203/ | F21: 1 | G21: 1 | H21: 0 | I21: 0 | J21: 1 | K21: 1 | L21: 1 | M21: 1
A22: T1059 | B22: Command and Scripting Interpreter | C22: S2 | D22: Windows; macOS; Linux; IaaS | E22: https://attack.mitre.org/techniques/T1059/ | F22: 1 | G22: 1 | H22: 1 | I22: 1 | J22: 1 | K22: 1 | L22: 1 | M22: 1
A23: T1554 | B23: Compromise Client Software Binary | C23: S2 | D23: Windows; macOS; Linux | E23: https://attack.mitre.org/techniques/T1554/ | F23: 1 | G23: 1 | H23: 0 | I23: 0 | J23: 1 | K23: 1 | L23: 1 | M23: 1
A24: T1068 | B24: Exploitation for Privilege Escalation | C24: S3 | D24: Windows; macOS; Linux | E24: https://attack.mitre.org/techniques/T1068/ | F24: 1 | G24: 1 | H24: 1 | I24: 1 | J24: 1 | K24: 1 | L24: 1 | M24: 1
A25: T1003 | B25: OS Credential Dumping | C25: S3 | D25: Windows; Linux; macOS | E25: https://attack.mitre.org/techniques/T1003/ | F25: 1 | G25: 1 | H25: 1 | I25: 1 | J25: 1 | K25: 1 | L25: 1 | M25: 1
A26: T1098 | B26: Account Manipulation | C26: S3 | D26: Identity Provider; SaaS; Windows | E26: https://attack.mitre.org/techniques/T1098/ | F26: 1 | G26: 1 | H26: 1 | I26: 1 | J26: 1 | K26: 1 | L26: 1 | M26: 1
A27: T1199 | B27: Trusted Relationship | C27: S3 | D27: SaaS; IaaS; Network Devices | E27: https://attack.mitre.org/techniques/T1199/ | F27: 1 | G27: 1 | H27: 1 | I27: 1 | J27: 1 | K27: 1 | L27: 1 | M27: 1
... A38: T1657 | B38: Financial Theft | C38: S5 | D38: SaaS; Office Suite; Identity Provider | E38: https://attack.mitre.org/techniques/T1657/ | F38: 1 | G38: 1 | H38: 1 | I38: 0 | J38: 0 | K38: 0 | L38: 0 | M38: 1

Sheet 13 Route TTP Map
A1: 13 — Route-to-TTP Mapping
A2: Which catalogue techniques belong to each composite route, with relevance weights.
A3: How used in the model: Builds the TTP set for each route. Combined with control efficacy (sheet 15) to compute stage barriers.
A15: Route ID | B15: TTP ID | C15: Relevance weight | D15: Rationale
A16: R_ID | B16: T1566 | C16: 1 | D16: Technique contributes to the route and relevant composite stage.
A17: R_ID | B17: T1078 | C17: 1 | D17: Technique contributes to the route and relevant composite stage.
A18: R_ID | B18: T1110 | C18: 0.7 | D18: Technique contributes to the route and relevant composite stage.
A19: R_ID | B19: T1098 | C19: 0.7 | D19: Technique contributes to the route and relevant composite stage.
A20: R_ID | B20: T1087 | C20: 0.6 | D20: Technique contributes to the route and relevant composite stage.
A21: R_ID | B21: T1213 | C21: 0.8 | D21: Technique contributes to the route and relevant composite stage.
A22: R_ID | B22: T1567 | C22: 0.7 | D22: Technique contributes to the route and relevant composite stage.
A23: R_ID | B23: T1657 | C23: 0.8 | D23: Technique contributes to the route and relevant composite stage.
A24: R_ID | B24: T1565 | C24: 0.5 | D24: Technique contributes to the route and relevant composite stage.
A25: R_ID | B25: T1486 | C25: 0.7 | D25: Technique contributes to the route and relevant composite stage.
A26: R_ID | B26: T1490 | C26: 0.6 | D26: Technique contributes to the route and relevant composite stage.
A27: R_USER | B27: T1566 | C27: 1 | D27: Technique contributes to the route and relevant composite stage.
... A67: R_INS | B67: T1657 | C67: 0.9 | D67: Technique contributes to the route and relevant composite stage.

Sheet 14 Control Reference
A1: 14 — Reference Control Profile
A2: Reference maturity and coverage for each control in the FS control set.
A3: How used in the model: The assessed organisation on IT 05 is measured relative to this profile so the model does not treat ‘no assessment’ as ‘no control’.
A15: Control ID | B15: Control family | C15: NIST CSF 2.0 | D15: MITRE mitigations | E15: Reference maturity | F15: Reference coverage | G15: Description | H15: Status | I15: Evidence grade | J15: Source ID
A16: C01 | B16: Asset and vulnerability management | C16: ID.AM; ID.RA | D16: M1016; M1051 | E16: Developing | F16: 0.75 | G16: Inventory, vulnerability identification, prioritisation and remediation. | H16: Working prior | I16: D | J16: SRC-10
A17: C02 | B17: Identity, authentication and MFA | C17: PR.AA | D17: M1032; M1036 | E17: Developing | F17: 0.75 | G17: Strong authentication, conditional access and account-use policies. | H17: Working prior | I17: D | J17: SRC-10
A18: C03 | B18: Privileged access management | C18: PR.AA | D18: M1026; M1018 | E18: Developing | F18: 0.75 | G18: Privileged identity lifecycle, vaulting and just-in-time access. | H18: Working prior | I18: D | J18: SRC-10
A19: C04 | B19: Email, web security and awareness | C19: PR.AT; PR.DS | D19: M1017; M1021 | E19: Developing | F19: 0.75 | G19: Phishing resistance, content filtering and workforce awareness. | H19: Working prior | I19: D | J19: SRC-10
A20: C05 | B20: Endpoint protection and execution control | C20: PR.PS; DE.CM | D20: M1040; M1049 | E20: Developing | F20: 0.75 | G20: EDR, anti-malware, application control and behaviour prevention. | H20: Working prior | I20: D | J20: SRC-10
A21: C06 | B21: Secure configuration and patching | C21: PR.PS | D21: M1042; M1051 | E21: Developing | F21: 0.75 | G21: Secure configuration, patching and hardening of technology platforms. | H21: Working prior | I21: D | J21: SRC-10
A22: C07 | B22: Network security and segmentation | C22: PR.IR; PR.PS | D22: M1030; M1037 | E22: Developing | F22: 0.75 | G22: Traffic restriction, segmentation and prevention of unauthorised movement. | H22: Working prior | I22: D | J22: SRC-10
A23: C08 | B23: Cloud and SaaS security | C23: PR.AA; PR.PS; DE.CM | D23: M1047; M1032 | E23: Developing | F23: 0.75 | G23: Cloud posture, SaaS configuration, logging and identity guardrails. | H23: Working prior | I23: D | J23: SRC-10
A24: C09 | B24: Application and API security | C24: ID.RA; PR.PS | D24: M1050; M1051 | E24: Developing | F24: 0.75 | G24: Secure development, testing, WAF/API protection and remediation. | H24: Working prior | I24: D | J24: SRC-10
A25: C10 | B25: Logging, detection and threat response | C25: DE.CM; DE.AE; RS.AN | D25: M1047 | E25: Developing | F25: 0.75 | G25: Detection engineering, telemetry, triage and response containment. | H25: Working prior | I25: D | J25: SRC-10
A26: C11 | B26: Data protection and DLP | C26: PR.DS | D26: M1041; M1057 | E26: Developing | F26: 0.75 | G26: Encryption, access restriction, data discovery and exfiltration controls. | H26: Working prior | I26: D | J26: SRC-10
A27: C12 | B27: Third-party and supply-chain security | C27: GV.SC; ID.RA | D27: M1045; M1051 | E27: Developing | F27: 0.75 | G27: Supplier assurance, delegated-access control and software integrity. | H27: Working prior | I27: D | J27: SRC-10
... A30: C15 | B30: Payment and fraud controls | C30: PR.AA; DE.AE; RS.MI | D30: M1018; M1047 | E30: Developing | F30: 0.75 | G30: Transaction monitoring, dual control, beneficiary and payment safeguards. | H30: Working prior | I30: D | J30: SRC-10

Sheet 15 Control TTP Map
A1: 15 — Control-to-TTP Efficacy Map
A2: How each control affects each TTP (prevent, contain, or reduce a loss block) and base efficacy.
A3: How used in the model: Converts IT 05 maturity into TTP barriers and duration/exposure/consequence factors used in frequency and severity.
A15: Control ID | B15: TTP ID | C15: Base efficacy | D15: Effect | E15: Rationale | F15: Evidence grade | G15: Source ID
A16: C01 | B16: T1190 | C16: 0.35 | D16: PREVENT_SUCCESS | E16: Channel-specific reference-relative control effect. | F16: D | G16: SRC-10
A17: C01 | B17: T1210 | C17: 0.35 | D17: PREVENT_SUCCESS | E17: Channel-specific reference-relative control effect. | F17: D | G17: SRC-10
A18: C01 | B18: T1068 | C18: 0.3 | D18: PREVENT_SUCCESS | E18: Channel-specific reference-relative control effect. | F18: D | G18: SRC-10
A19: C02 | B19: T1078 | C19: 0.65 | D19: PREVENT_SUCCESS | E19: Channel-specific reference-relative control effect. | F19: D | G19: SRC-10
A20: C02 | B20: T1110 | C20: 0.65 | D20: PREVENT_SUCCESS | E20: Channel-specific reference-relative control effect. | F20: D | G20: SRC-10
A21: C02 | B21: T1098 | C21: 0.45 | D21: PREVENT_SUCCESS | E21: Channel-specific reference-relative control effect. | F21: D | G21: SRC-10
A22: C03 | B22: T1003 | C22: 0.55 | D22: PREVENT_SUCCESS | E22: Channel-specific reference-relative control effect. | F22: D | G22: SRC-10
A23: C03 | B23: T1068 | C23: 0.45 | D23: PREVENT_SUCCESS | E23: Channel-specific reference-relative control effect. | F23: D | G23: SRC-10
A24: C03 | B24: T1098 | C24: 0.55 | D24: PREVENT_SUCCESS | E24: Channel-specific reference-relative control effect. | F24: D | G24: SRC-10
A25: C03 | B25: T1657 | C25: 0.45 | D25: PREVENT_SUCCESS | E25: Channel-specific reference-relative control effect. | F25: D | G25: SRC-10
A26: C04 | B26: T1566 | C26: 0.55 | D26: PREVENT_SUCCESS | E26: Channel-specific reference-relative control effect. | F26: D | G26: SRC-10
A27: C04 | B27: T1203 | C27: 0.25 | D27: PREVENT_SUCCESS | E27: Channel-specific reference-relative control effect. | F27: D | G27: SRC-10
... A66: C15 | B66: T1657 | C66: 0.55 | D66: REDUCE_CONSEQUENCE | E66: Channel-specific reference-relative control effect. | F66: D | G66: SRC-10

Sheet 16 Sources
A1: 16 — Sources and Evidence
A2: Bibliography and limitations for pack assumptions.
A3: How used in the model: Traceability only. The engine does not read frequencies or losses from this sheet.
A15: Source ID | B15: Source | C15: URL / file | D15: How used | E15: Limitation
A16: SRC-01 | B16: MITRE Enterprise ATT&CK | C16: https://attack.mitre.org/matrices/enterprise/ | D16: Technique taxonomy and route behaviour | E16: ATT&CK is not a frequency or probability dataset.
A17: SRC-02 | B17: MITRE Enterprise mitigations | C17: https://attack.mitre.org/mitigations/enterprise/ | D17: Mitigation identifiers and control rationale | E17: Mappings do not establish quantified efficacy.
A18: SRC-03 | B18: NIST CSF 2.0 | C18: https://nvlpubs.nist.gov/nistpubs/CSWP/NIST.CSWP.29.pdf | D18: Control-family governance structure | E18: Outcome framework, not a calibration dataset.
A19: SRC-04 | B19: ENISA Threat Landscape: Finance Sector | C19: https://www.enisa.europa.eu/sites/default/files/2025-02/Finance%20TL%202024_Final.pdf | D19: FS threat, actor and outcome context | E19: Incident reporting scope is not an organisation-year denominator.
A20: SRC-05 | B20: ENISA Threat Landscape 2025 | C20: https://www.enisa.europa.eu/publications/enisa-threat-landscape-2025 | D20: Hacktivism, DDoS and ransomware context | E20: European collection; should not be treated as global actor shares.
A21: SRC-06 | B21: FS-ISAC Knowledge | C21: https://www.fsisac.com/knowledge | D21: Identity, fraud, DDoS, cloud and third-party context | E21: Public material does not provide a complete frequency calibration.
A22: SRC-07 | B22: Balbix Breach Impact Model | C22: Balbix Breach Impact Model.xlsx | D22: Driver architecture and identifiable unit-cost assumptions | E22: Rebuilt taxonomy and formulas; source workbook contains working assumptions.
A23: SRC-08 | B23: CISA KEV | C23: https://www.cisa.gov/known-exploited-vulnerabilities-catalog | D23: Future exposure-adjustment evidence | E23: Not directly converted into annual organisation-level frequency.
A24: SRC-09 | B24: FIRST EPSS | C24: https://www.first.org/epss/ | D24: Future exposure-adjustment evidence | E24: 30-day population exploitation probability, not financial risk.
A25: SRC-10 | B25: Structured expert judgement | C25: Internal documented elicitation record | D25: Working priors where A–C evidence is unavailable | E25: Requires named experts, rationale, range and independent challenge.

Sheet 17 Evidence Register
A1: 17 — Evidence Grade Register
A2: The evidence-grade scale (A–D) applied to material pack assumptions.
A3: How used in the model: Governance labels only. Grades do not rescale Python results.
A15: Grade | B15: Definition | C15: Minimum record | D15: Use
A16: A | B16: Direct empirical evidence | C16: Internal incidents, claims, organisation-years, control tests or BIA evidence | D16: Preferred calibration
A17: B | B17: Relevant portfolio evidence | C17: Comparable anonymised FS incidents, claims or control-testing evidence | D17: Portfolio calibration
A18: C | B18: External evidence | C18: Regulators, ENISA, DBIR, published incidents and case studies | D18: Context and bounded calibration
A19: D | B19: Structured expert judgement | C19: Named experts, documented rationale, range/distribution and independent challenge | D19: Only where A–C are unavailable

Sheet 18 Validation
A1: 18 — Pack Validation
A2: Spreadsheet checks (IDs present, weights, row counts).
A3: How used in the model: Advisory in Excel. Python repeats identity, schema and structural checks and fails closed independently.
A15: Check | B15: Actual | C15: Expected | D15: Tolerance | E15: Status
A16: Actor weights total | B16: ='02 Actor Weights'!C20 -> 1 | C16: 1 | D16: 1e-06 | E16: =IF(ABS(B16-C16)<=D16,"PASS","FAIL") -> PASS
A17: Actor-scenario rows total | B17: =MIN('03 Actor Scenario'!F16:F19) -> 1 | C17: 1 | D17: 1e-06 | E17: =IF(AND(MIN('03 Actor Scenario'!F16:F19)>=1-D17,MAX('03 Actor Scenario'!F16:F19)<=1+D17),"PASS","FAIL") -> PASS
A18: Actor-route rows total | B18: =MIN('05 Actor Route'!H16:H19) -> 1 | C18: 1 | D18: 1e-06 | E18: =IF(AND(MIN('05 Actor Route'!H16:H19)>=1-D18,MAX('05 Actor Route'!H16:H19)<=1+D18),"PASS","FAIL") -> PASS
A19: Scenario-route rows total | B19: =MIN('06 Scenario Route'!H16:H19) -> 1 | C19: 1 | D19: 1e-06 | E19: =IF(AND(MIN('06 Scenario Route'!H16:H19)>=1-D19,MAX('06 Scenario Route'!H16:H19)<=1+D19),"PASS","FAIL") -> PASS
A20: Required metadata populated | B20: =COUNTA('01 Pack Metadata'!B16:B37) -> 22 | C20: 22 | D20: 0 | E20: =IF(ABS(B20-C20)<=D20,"PASS","FAIL") -> PASS
