Workbook

Sheet 01 Model Guide
A1: Guided IT Cyber Risk Quantification — v1.1.1
A2: Organisation-level IT-CRQ model with modular, pack-driven workbook geometry.
A4: SHEET TYPE: MODEL DOCUMENTATION
A6: Purpose
A7: Quantify annual financial loss for an organisation across four actors, four loss scenarios and six composite attack routes.
A9: Calculation / decision logic
A10: Campaign frequency is separated from conditional attack-path success. Enterprise ATT&CK techniques are filtered by actor, scenario and route; controls adjust stage-through probabilities relative to a reference profile. Scenario losses use transparent P50/P99 impact drivers and a Monte Carlo annual-loss simulation.
A12: Outputs / downstream use
A13: AAL, VaR, TVaR, AEP/OEP loss-exceedance curves, actor/scenario decompositions, control what-if reductions and an interactive dashboard suite.
A15: Workbook convention
A16: Yellow cells with blue font are editable. Engine results and resolved pack values are not manually editable.
A20: MODEL FLOW
A21: 1 | B21: Select sector and organisation inputs | C21: 03 Organisation Inputs
A22: 2 | B22: Choose whether to apply IT Exposure Adjustment Model recommendations | C22: 03 and 04
A23: 3 | B23: Assess NIST CSF 2.0-aligned control families | C23: 05 Control Assessment
A24: 4 | B24: Review organisation-scale impact inputs and pack-derived BIA drivers | C24: 06 Impact and BIA
A25: 5 | B25: Python loads and validates the selected sector-pack workbook | C25: 09 Sector Pack Registry
A26: 6 | B26: Engine evaluates actor × scenario × route × TTP relevance and composite stages | C26: 10–12
A27: 7 | B27: Engine simulates annual aggregate and occurrence losses | C27: 13–19
A28: 8 | B28: Review interactive dashboards, executive results, curves, what-ifs and validation | C28: 00 Dashboard suite; 02, 15–22
A30: IMPORTANT LIMITATIONS
A31: Frequency and sector calibration values are development working priors and require approval before external reliance.
A32: The model excludes pure intellectual-property theft as a loss scenario.
A33: Ransomware, DDoS, phishing, account takeover and supply-chain compromise are mechanisms/routes, not separate financial-loss scenarios.
A34: When the exposure-adjustment switch is No, all exposure-model factors are neutral; organisation route-applicability inputs still apply.
A35: Asset and vulnerability records are not ingested by this CRQ workbook. A separate evidence model recommends governed route/stage factors for sheet 04.

Sheet 02 Executive Summary
A1: 02 — Executive Risk Summary
A2: Python-populated organisation-level risk metrics, decompositions and run context.
A5: FINANCIAL RISK
A6: Metric | B6: Best Estimate | C6: Prudent | D6: Meaning
A7: AAL | B7: 1059877.3 | C7: 1311679.4 | D7: Mean annual aggregate financial loss.
A8: VaR 95% | B8: 5487402.5 | C8: 7125948 | D8: 95th percentile annual aggregate loss.
A9: TVaR 95% | B9: 18021076 | C9: 20885315 | D9: Mean annual loss in the worst 5% of years.
A10: VaR 99% | B10: 22824448 | C10: 26218159 | D10: 99th percentile annual aggregate loss.
A11: TVaR 99% | B11: 46179340 | C11: 51675145 | D11: Mean annual loss in the worst 1% of years.
A12: Selected TVaR | B12: 46179340 | C12: 51675145 | D12: Tail metric selected on 08.
A13: Insurance retention | B13: 0 | C13: 0 | D13: Organisation-selected retention.
A14: Tail loss above retention | B14: 46179340 | C14: 51675145 | D14: Selected TVaR less retention, floored at zero.
A16: EVENT AND RUN CONTEXT
A17: Metric | B17: Best Estimate | C17: Prudent | D17: Meaning
A18: P(any successful event) | B18: 0.114878 | C18: 0.140772
A19: Successful events / year | B19: 0.12094386 | C19: 0.15117983
A20: Material campaigns / year | B20: 1 | C20: 1.25
A21: Use exposure adjustments? | B21: No | C21: No
A22: Sector | B22: Financial Services | C22: Financial Services
A23: Resolved pack ID | B23: FS-v1.1.1 | C23: FS-v1.1.1
A24: Pack status | B24: Development — working priors; calibration required | C24: Development — working priors; calibration required
A25: Simulation years | B25: 500000 | C25: 500000
A26: Last run | B26: 2026-08-21 10:19 UTC | C26: 2026-08-21 10:19 UTC
A28: THREAT-ACTOR DECOMPOSITION
A29: Threat actor | B29: AAL | C29: Attempts / yr | D29: Events / yr | E29: P(success) | F29: AAL share | G29: 1-in-20 AEP | H29: 1-in-100 AEP
A30: Nation-state | B30: 119201.14 | C30: 0.15 | D30: 0.013632509 | E30: 0.090883393 | F30: 0.09087674 | G30: 0 | H30: 2412035.6
A31: Cybercriminal | B31: 651035.53 | C31: 0.85 | D31: 0.076702191 | E31: 0.090237872 | F31: 0.49633741 | G31: 2309382.9 | H31: 16138275
A32: Malicious insider | B32: 301385.84 | C32: 0.125 | D32: 0.036279943 | E32: 0.29023954 | F32: 0.22977097 | G32: 0 | H32: 8325961.9
A33: Hacktivist | B33: 240056.84 | C33: 0.125 | D33: 0.024565183 | E33: 0.19652146 | F33: 0.18301488 | G33: 0 | H33: 6353896.7
A35: SCENARIO DECOMPOSITION
A36: Scenario | B36: AAL | C36: Attempts / yr | D36: Events / yr | E36: P(success) | F36: AAL share | G36: 1-in-20 AEP | H36: 1-in-100 AEP
A37: Critical business-service disruption | B37: 575998.21 | C37: 0.41125 | D37: 0.051753306 | E37: 0.1258439 | F37: 0.43913035 | G37: 421378.54 | H37: 15039969
A38: Sensitive-data compromise | B38: 292163.99 | C38: 0.32125 | D38: 0.025781651 | E38: 0.080254165 | F38: 0.2227404 | G38: 0 | H38: 8461016.1
A39: Data or transaction-integrity compromise | B39: 183681.88 | C39: 0.17125 | D39: 0.019789662 | E39: 0.11556007 | F39: 0.14003565 | G39: 0 | H39: 5108821.5
A40: Cyber-enabled theft or fraud | B40: 259835.28 | C40: 0.34625 | D40: 0.053855207 | E40: 0.1555385 | F40: 0.1980936 | G40: 355893.83 | H40: 6844977.2
A42: TOP CONTROL WHAT-IFS
A43: Control | B43: Current maturity | C43: What-if maturity | D43: Current AAL | E43: What-if AAL | F43: AAL reduction
A44: Privileged access management | B44: Developing | C44: Managed | D44: 1308717.6 | E44: 1200150.2 | F44: 108567.33
A45: DDoS protection and service resilience | B45: Developing | C45: Managed | D45: 1308717.6 | E45: 1214101.7 | F45: 94615.903
A46: Payment and fraud controls | B46: Developing | C46: Managed | D46: 1308717.6 | E46: 1228605.4 | F46: 80112.178
A47: Data protection and DLP | B47: Developing | C47: Managed | D47: 1308717.6 | E47: 1232571 | F47: 76146.594
A48: Identity, authentication and MFA | B48: Developing | C48: Managed | D48: 1308717.6 | E48: 1236947.2 | F48: 71770.39

Sheet 03 Organisation Inputs
A1: 03 — Organisation and Run Inputs
A2: Select the sector, organisation scale and whether upstream IT Exposure Adjustment Model recommendations are applied.
A15: Input | B15: Question | C15: Value | D15: Type | E15: How used | F15: Basis / evidence
A16: ASSESSMENT_ID | B16: Assessment reference | C16: IT-CRQ-001 | D16: Text | E16: Reporting and traceability | F16: Client
A17: ORGANISATION | B17: Organisation | C17: Example Financial Institution | D17: Text | E17: Organisation-level unit of analysis | F17: Client
A18: COUNTRY_REGION | B18: Country / region | C18: UAE / GCC | D18: Text | E18: Reporting context; explicit multiplier is on 07 | F18: Client
A19: SECTOR | B19: Sector | C19: Financial Services | D19: Dropdown | E19: Resolves the separate sector-pack workbook | F19: 09 Sector Pack Registry
A20: CURRENCY | B20: Reporting currency | C20: USD | D20: Dropdown | E20: Financial result labels | F20: Client
A21: ANNUAL_REVENUE_AT_RISK | B21: Annual revenue at risk | C21: 1000000000 | D21: Currency/year | E21: Business interruption and revenue-scaled drivers | F21: Client Finance
A22: ANNUAL_PAYMENT_VALUE | B22: Annual payment / transaction value | C22: 5000000000 | D22: Currency/year | E22: Funds-at-risk model for integrity and fraud scenarios | F22: Client Finance
A23: BI_LOSS_FACTOR | B23: Business-interruption loss factor | C23: 1 | D23: Percentage | E23: Share of revenue at risk treated as avoidable loss | F23: Client Finance
A24: EMPLOYEES | B24: Employees | C24: 10000 | D24: Count | E24: Organisation context | F24: Client
A25: CUSTOMERS | B25: Customers / accounts | C25: 2000000 | D25: Count | E25: Potential notification and monitoring scale | F25: Client
A26: SENSITIVE_RECORDS | B26: Sensitive records | C26: 5000000 | D26: Count | E26: Data-compromise scaling | F26: Client
A27: CRITICAL_ENDPOINTS | B27: Critical endpoints | C27: 5000 | D27: Count | E27: Recovery-cost scaling | F27: Client
A28: CRITICAL_SERVERS | B28: Critical servers / workloads | C28: 500 | D28: Count | E28: Recovery-cost scaling | F28: Client
A29: USE_EXPOSURE_MODEL | B29: Use IT Exposure Adjustment Model inputs? | C29: No | D29: Yes / No dropdown | E29: Controls whether sheet 04 recommendations are applied | F29: User decision
A30: SIMULATION_YEARS | B30: Monte Carlo organisation-years | C30: 500000 | D30: Count | E30: Annual-loss simulation size | F30: Model setting
A31: RANDOM_SEED | B31: Random seed | C31: 20260821 | D31: Integer | E31: Reproducible simulation | F31: Model setting
A33: RESOLVED SECTOR PACK
A34: PACK_ID | B34: Resolved pack ID | C34: FS-v1.1.1 | D34: Engine output | E34: Traceability | F34: Separate sector-pack workbook
A35: PACK_VERSION | B35: Resolved pack version | C35: 1.1.1 | D35: Engine output | E35: Compatibility | F35: Separate sector-pack workbook
A36: PACK_STATUS | B36: Pack calibration status | C36: Development — working priors; calibration required | D36: Engine output | E36: Governance | F36: Separate sector-pack workbook
A37: MODEL_STATUS | B37: Last validation status | C37: PASS | D37: Engine output | E37: Model governance | F37: 22 Validation Tests

Sheet 04 Exposure Adjustments
A1: 04 — IT Exposure Adjustment Inputs
A2: Optional upstream recommendations. The CRQ workbook does not ingest raw asset or vulnerability records.
A4: When USE_EXPOSURE_MODEL = No, model feasibility and all recommended factors are ignored and treated as neutral 1.00. Organisation route applicability remains active in both modes.
A15: Route ID | B15: Attack route | C15: Organisation applicable? | D15: Evidence-model feasible? | E15: Opportunity factor | F15: S1 factor | G15: S2 factor | H15: S3 factor | I15: S4 factor | J15: S5 factor | K15: Impact factor | L15: Confidence | M15: Recommendation ID | N15: Evidence date | O15: Rationale | P15: Used opportunity | Q15: Used S1 | R15: Used S2 | S15: Used S3 | T15: Used S4 | U15: Used S5 | V15: Used impact
A16: R_ID | B16: Identity and credential compromise | C16: Yes | D16: Unknown | E16: 1 | F16: 1 | G16: 1 | H16: 1 | I16: 1 | J16: 1 | K16: 1 | L16: Not assessed | O16: No exposure-model recommendation loaded. | P16: 1 | Q16: 1 | R16: 1 | S16: 1 | T16: 1 | U16: 1 | V16: 1
A17: R_USER | B17: User endpoint and social engineering | C17: Yes | D17: Unknown | E17: 1 | F17: 1 | G17: 1 | H17: 1 | I17: 1 | J17: 1 | K17: 1 | L17: Not assessed | O17: No exposure-model recommendation loaded. | P17: 1 | Q17: 1 | R17: 1 | S17: 1 | T17: 1 | U17: 1 | V17: 1
A18: R_EXP | B18: Public-facing application exploitation | C18: Yes | D18: Unknown | E18: 1 | F18: 1 | G18: 1 | H18: 1 | I18: 1 | J18: 1 | K18: 1 | L18: Not assessed | O18: No exposure-model recommendation loaded. | P18: 1 | Q18: 1 | R18: 1 | S18: 1 | T18: 1 | U18: 1 | V18: 1
A19: R_TP | B19: Third-party or software supply chain | C19: Yes | D19: Unknown | E19: 1 | F19: 1 | G19: 1 | H19: 1 | I19: 1 | J19: 1 | K19: 1 | L19: Not assessed | O19: No exposure-model recommendation loaded. | P19: 1 | Q19: 1 | R19: 1 | S19: 1 | T19: 1 | U19: 1 | V19: 1
A20: R_DDOS | B20: Direct availability or DDoS | C20: Yes | D20: Unknown | E20: 1 | F20: 1 | G20: 1 | H20: 1 | I20: 1 | J20: 1 | K20: 1 | L20: Not assessed | O20: No exposure-model recommendation loaded. | P20: 1 | Q20: 1 | R20: 1 | S20: 1 | T20: 1 | U20: 1 | V20: 1
A21: R_INS | B21: Insider or trusted access | C21: Yes | D21: Unknown | E21: 1 | F21: 1 | G21: 1 | H21: 1 | I21: 1 | J21: 1 | K21: 1 | L21: Not assessed | O21: No exposure-model recommendation loaded. | P21: 1 | Q21: 1 | R21: 1 | S21: 1 | T21: 1 | U21: 1 | V21: 1

Sheet 05 Control Assessment
A1: 05 — Control Assessment
A2: NIST CSF 2.0-aligned control families with Enterprise ATT&CK mitigation mappings and reference-relative efficacy.
A15: Control ID | B15: Control family | C15: NIST CSF 2.0 | D15: MITRE mitigations | E15: Actual maturity | F15: Actual coverage | G15: Reference maturity | H15: Reference coverage | I15: Evidence / rationale | J15: Resolved status
A16: C01 | B16: Asset and vulnerability management | C16: ID.AM; ID.RA | D16: M1016; M1051 | E16: Developing | F16: 0.75 | G16: Developing | H16: 0.75 | I16: User assessment required | J16: Working prior
A17: C02 | B17: Identity, authentication and MFA | C17: PR.AA | D17: M1032; M1036 | E17: Developing | F17: 0.75 | G17: Developing | H17: 0.75 | I17: User assessment required | J17: Working prior
A18: C03 | B18: Privileged access management | C18: PR.AA | D18: M1026; M1018 | E18: Developing | F18: 0.75 | G18: Developing | H18: 0.75 | I18: User assessment required | J18: Working prior
A19: C04 | B19: Email, web security and awareness | C19: PR.AT; PR.DS | D19: M1017; M1021 | E19: Developing | F19: 0.75 | G19: Developing | H19: 0.75 | I19: User assessment required | J19: Working prior
A20: C05 | B20: Endpoint protection and execution control | C20: PR.PS; DE.CM | D20: M1040; M1049 | E20: Developing | F20: 0.75 | G20: Developing | H20: 0.75 | I20: User assessment required | J20: Working prior
A21: C06 | B21: Secure configuration and patching | C21: PR.PS | D21: M1042; M1051 | E21: Developing | F21: 0.75 | G21: Developing | H21: 0.75 | I21: User assessment required | J21: Working prior
A22: C07 | B22: Network security and segmentation | C22: PR.IR; PR.PS | D22: M1030; M1037 | E22: Developing | F22: 0.75 | G22: Developing | H22: 0.75 | I22: User assessment required | J22: Working prior
A23: C08 | B23: Cloud and SaaS security | C23: PR.AA; PR.PS; DE.CM | D23: M1047; M1032 | E23: Developing | F23: 0.75 | G23: Developing | H23: 0.75 | I23: User assessment required | J23: Working prior
A24: C09 | B24: Application and API security | C24: ID.RA; PR.PS | D24: M1050; M1051 | E24: Developing | F24: 0.75 | G24: Developing | H24: 0.75 | I24: User assessment required | J24: Working prior
A25: C10 | B25: Logging, detection and threat response | C25: DE.CM; DE.AE; RS.AN | D25: M1047 | E25: Developing | F25: 0.75 | G25: Developing | H25: 0.75 | I25: User assessment required | J25: Working prior
A26: C11 | B26: Data protection and DLP | C26: PR.DS | D26: M1041; M1057 | E26: Developing | F26: 0.75 | G26: Developing | H26: 0.75 | I26: User assessment required | J26: Working prior
A27: C12 | B27: Third-party and supply-chain security | C27: GV.SC; ID.RA | D27: M1045; M1051 | E27: Developing | F27: 0.75 | G27: Developing | H27: 0.75 | I27: User assessment required | J27: Working prior
... A30: C15 | B30: Payment and fraud controls | C30: PR.AA; DE.AE; RS.MI | D30: M1018; M1047 | E30: Developing | F30: 0.75 | G30: Developing | H30: 0.75 | I30: User assessment required | J30: Working prior

Sheet 06 Impact and BIA
A1: 06 — Impact and Business Impact Analysis
A2: Pack-driven P50/P99 assumptions. Python prepares this long table and preserves overrides.
A5: ORGANISATION-SCALE INPUTS
A6: Metric | B6: Value | C6: Source
A7: Annual revenue at risk | B7: 1000000000 | C7: 03 Organisation Inputs
A8: Annual payment value | B8: 5000000000 | C8: 03 Organisation Inputs
A9: BI loss factor | B9: 1 | C9: 03 Organisation Inputs
A10: Customers | B10: 2000000 | C10: 03 Organisation Inputs
A11: Sensitive records | B11: 5000000 | C11: 03 Organisation Inputs
A12: Critical endpoints | B12: 5000 | C12: 03 Organisation Inputs
A13: Critical servers | B13: 500 | C13: 03 Organisation Inputs
A15: PACK ASSUMPTIONS AND ORGANISATION OVERRIDES
A16: Assumption type | B16: Scenario ID | C16: Scenario | D16: Parameter ID | E16: Description | F16: Unit | G16: Pack P50 | H16: Pack P99 | I16: Override P50 | J16: Override P99 | K16: Used P50 | L16: Used P99 | M16: Evidence grade | N16: Source ID
A17: RATE | D17: NOTIFICATION_PER_RECORD | E17: Notification cost per affected record | F17: USD/record | G17: 0.5 | H17: 1 | K17: 0.5 | L17: 1 | M17: D | N17: SRC-07
A18: RATE | D18: CREDIT_MONITORING_PER_RECORD | E18: Credit monitoring per participating record | F18: USD/record | G18: 8 | H18: 20 | K18: 8 | L18: 20 | M18: D | N18: SRC-07
A19: RATE | D19: FORENSIC_DAILY | E19: Daily forensic investigation team | F19: USD/day | G19: 2000 | H19: 4000 | K19: 2000 | L19: 4000 | M19: D | N19: SRC-07
A20: RATE | D20: EXTERNAL_CYBER_DAILY | E20: Daily external cyber response team | F20: USD/day | G20: 3000 | H20: 5000 | K20: 3000 | L20: 5000 | M20: D | N20: SRC-07
A21: RATE | D21: RESTORATION_DAILY | E21: Daily data restoration team | F21: USD/day | G21: 2000 | H21: 4000 | K21: 2000 | L21: 4000 | M21: D | N21: SRC-07
A22: RATE | D22: LEGAL_DAILY | E22: Daily external legal team | F22: USD/day | G22: 5000 | H22: 10000 | K22: 5000 | L22: 10000 | M22: D | N22: SRC-07
A23: RATE | D23: ENDPOINT_REPAIR | E23: Endpoint repair/replacement unit cost | F23: USD/endpoint | G23: 200 | H23: 500 | K23: 200 | L23: 500 | M23: D | N23: SRC-07
A24: RATE | D24: SERVER_REPAIR | E24: Server repair/replacement unit cost | F24: USD/server | G24: 5000 | H24: 8000 | K24: 5000 | L24: 8000 | M24: D | N24: SRC-07
A25: PARAM | B25: SC_DISR | C25: Critical business-service disruption | D25: AFFECTED_ENDPOINT_SHARE | E25: AFFECTED_ENDPOINT_SHARE | F25: share | G25: 0.1 | H25: 0.5 | K25: 0.1 | L25: 0.5 | M25: D | N25: SRC-10
A26: PARAM | B26: SC_DISR | C26: Critical business-service disruption | D26: AFFECTED_RECORD_SHARE | E26: AFFECTED_RECORD_SHARE | F26: share | G26: 0 | H26: 0.05 | K26: 0 | L26: 0.05 | M26: D | N26: SRC-10
A27: PARAM | B27: SC_DISR | C27: Critical business-service disruption | D27: AFFECTED_SERVER_SHARE | E27: AFFECTED_SERVER_SHARE | F27: share | G27: 0.1 | H27: 0.6 | K27: 0.1 | L27: 0.6 | M27: D | N27: SRC-10
A28: PARAM | B28: SC_DISR | C28: Critical business-service disruption | D28: AFFECTED_SERVICE_SHARE | E28: AFFECTED_SERVICE_SHARE | F28: share | G28: 0.3 | H28: 0.85 | K28: 0.3 | L28: 0.85 | M28: D | N28: SRC-10
A29: PARAM | B29: SC_DISR | C29: Critical business-service disruption | D29: CHURN_REVENUE_SHARE | E29: CHURN_REVENUE_SHARE | F29: share | G29: 0.001 | H29: 0.01 | K29: 0.001 | L29: 0.01 | M29: D | N29: SRC-10
A30: PARAM | B30: SC_DISR | C30: Critical business-service disruption | D30: CYBER_DAYS | E30: CYBER_DAYS | F30: days | G30: 10 | H30: 90 | K30: 10 | L30: 90 | M30: D | N30: SRC-10
A31: PARAM | B31: SC_DISR | C31: Critical business-service disruption | D31: DIVERTED_SHARE | E31: DIVERTED_SHARE | F31: share | G31: 0 | H31: 0 | K31: 0 | L31: 0 | M31: D | N31: SRC-10
A32: PARAM | B32: SC_DISR | C32: Critical business-service disruption | D32: DOWNTIME_DAYS | E32: DOWNTIME_DAYS | F32: days | G32: 3 | H32: 30 | K32: 3 | L32: 30 | M32: D | N32: SRC-10
A33: PARAM | B33: SC_DISR | C33: Critical business-service disruption | D33: EXTORTION_DIRECT | E33: EXTORTION_DIRECT | F33: USD | G33: 1000000 | H33: 20000000 | K33: 1000000 | L33: 20000000 | M33: D | N33: SRC-10
A34: PARAM | B34: SC_DISR | C34: Critical business-service disruption | D34: FRAUD_RECOVERY_RATE | E34: FRAUD_RECOVERY_RATE | F34: share | G34: 0 | H34: 0 | K34: 0 | L34: 0 | M34: D | N34: SRC-10
A35: PARAM | B35: SC_DISR | C35: Critical business-service disruption | D35: IR_DAYS | E35: IR_DAYS | F35: days | G35: 10 | H35: 60 | K35: 10 | L35: 60 | M35: D | N35: SRC-10
A36: PARAM | B36: SC_DISR | C36: Critical business-service disruption | D36: LEGAL_DAYS | E36: LEGAL_DAYS | F36: days | G36: 5 | H36: 45 | K36: 5 | L36: 45 | M36: D | N36: SRC-10
... A92: PARAM | B92: SC_FRAUD | C92: Cyber-enabled theft or fraud | D92: RESTORE_DAYS | E92: RESTORE_DAYS | F92: days | G92: 5 | H92: 60 | K92: 5 | L92: 60 | M92: D | N92: SRC-10

Sheet 07 Frequency Assumptions
A1: 07 — Frequency Assumptions
A2: Best-estimate campaign frequency remains separate from conditional attack-path success and prudence.
A15: Parameter | B15: Value | C15: Unit | D15: How used | E15: Status | F15: Source / rationale
A16: ORGANISATION_EXPOSURE_MULT | B16: 1 | C16: multiplier | D16: Scales reference material campaign rate before actor/scenario/route allocation | E16: User input | F16: Organisation context; avoid duplicating sheet 04 route factors
A17: GEOGRAPHY_THREAT_MULT | B17: 1 | C17: multiplier | D17: Scales campaign rate for geography-specific threat context | E17: User input | F17: Use 1.00 unless evidence supports adjustment
A18: PRUDENCE_FREQUENCY_FACTOR | B18: 1.25 | C18: multiplier | D18: Applied only to prudent frequency view | E18: User input | F18: Separate named prudence margin
A19: NATION_STATE_ACTIVITY | B19: 1 | C19: multiplier | D19: Actor-specific activity adjustment | E19: User input | F19: Client threat intelligence
A20: CYBERCRIMINAL_ACTIVITY | B20: 1 | C20: multiplier | D20: Actor-specific activity adjustment | E20: User input | F20: Client threat intelligence
A21: MALICIOUS_INSIDER_ACTIVITY | B21: 1 | C21: multiplier | D21: Actor-specific activity adjustment | E21: User input | F21: Client threat intelligence
A22: HACKTIVIST_ACTIVITY | B22: 1 | C22: multiplier | D22: Actor-specific activity adjustment | E22: User input | F22: Client threat intelligence
A25: RESOLVED PACK FREQUENCY
A26: REFERENCE_CAMPAIGNS_PER_YEAR | B26: 1 | C26: campaigns/org-year | D26: Loaded from selected sector pack | E26: Engine output | F26: Development working prior
A27: PACK_WEIGHTED_ACTIVITY | B27: 1 | C27: multiplier | D27: Σ(actor weight × actor activity) | E27: Engine output | F27: Calculation
A28: BEST_ESTIMATE_LAMBDA | B28: 1 | C28: campaigns/org-year | D28: Reference × organisation × geography × weighted activity | E28: Engine output | F28: Calculation
A29: PRUDENT_LAMBDA | B29: 1.25 | C29: campaigns/org-year | D29: Best estimate × prudence factor | E29: Engine output | F29: Calculation
A30: ACTIVE_ROUTE_OPPORTUNITY | B30: 1 | C30: multiplier | D30: Resulting route-level exposure effect | E30: Engine output | F30: Calculation

Sheet 08 Tail Risk Settings
A1: 08 — Tail-Risk and Reporting Settings
A2: User-selected tail metric and insurance retention; both best-estimate and prudent views remain available.
A15: Parameter | B15: Value | C15: Type | D15: How used | E15: Status | F15: Notes
A16: REPORTING_VIEW | B16: Prudent | C16: Dropdown | D16: Detailed-sheet presentation | E16: User input | F16: Executive summary always shows both views
A17: TVAR_SELECTION | B17: TVaR 99% | C17: Dropdown | D17: Selected tail metric | E17: User input | F17: Does not alter the simulated distribution
A18: INSURANCE_RETENTION | B18: 0 | C18: Currency | D18: Tail loss above retention | E18: User input | F18: Indicative risk-transfer view only
A19: LEC_RETURN_PERIODS | B19: 2,5,10,20,25,50,100,200,250,500 | C19: Text | D19: AEP/OEP curve points | E19: Model setting | F19: Fixed engine-supported list

Sheet 09 Sector Pack Registry
A1: 09 — Sector Pack Registry
A2: The selected sector resolves to one separate workbook. Add future sectors by copying the pack schema and registering the file here.
A15: Sector | B15: Pack ID | C15: Pack version | D15: Relative file path | E15: Schema version | F15: Status | G15: Minimum engine | H15: Description
A16: Financial Services | B16: FS-v1.1.1 | C16: 1.1.1 | D16: sector_packs/IT/IT_CRQ_Sector_Pack_Financial_Services_v1_1_1.xlsx | E16: CRQ-PACK-1.1 | F16: Development — working priors; calibration required | G16: 1.1.1 | H16: Broad Financial Services pack; no granular banking/insurance sub-packs.

Sheet 10 TTP Relevance Calc
A1: 10 — TTP Relevance Calculation
A2: Actor × scenario × route × TTP applicability and control barrier audit.
A5: ENGINE OUTPUT — do not edit. Run the Python engine after changing inputs or sector packs.
A15: Threat actor | B15: Scenario | C15: Route | D15: TTP ID | E15: Technique | F15: Stage | G15: Actor applicable | H15: Scenario applicable | I15: Relevant | J15: Weight | K15: Actual barrier | L15: Reference barrier | M15: Platforms | N15: MITRE URL
A16: Nation-state | B16: Critical business-service disruption | C16: Identity and credential compromise | D16: T1566 | E16: Phishing | F16: S1 | G16: TRUE | H16: TRUE | I16: TRUE | J16: 1 | K16: 0.20625 | L16: 0.20625 | M16: Windows; SaaS; Office Suite | N16: https://attack.mitre.org/techniques/T1566/
A17: Nation-state | B17: Critical business-service disruption | C17: Identity and credential compromise | D17: T1078 | E17: Valid Accounts | F17: S1 | G17: TRUE | H17: TRUE | I17: TRUE | J17: 1 | K17: 0.27210937 | L17: 0.27210937 | M17: Identity Provider; SaaS; IaaS; Windows | N17: https://attack.mitre.org/techniques/T1078/
A18: Nation-state | B18: Critical business-service disruption | C18: Identity and credential compromise | D18: T1110 | E18: Brute Force | F18: S1 | G18: TRUE | H18: TRUE | I18: TRUE | J18: 0.7 | K18: 0.24375 | L18: 0.24375 | M18: Identity Provider; SaaS; Windows | N18: https://attack.mitre.org/techniques/T1110/
A19: Nation-state | B19: Critical business-service disruption | C19: Identity and credential compromise | D19: T1098 | E19: Account Manipulation | F19: S3 | G19: TRUE | H19: TRUE | I19: TRUE | J19: 0.7 | K19: 0.24775473 | L19: 0.24775473 | M19: Identity Provider; SaaS; Windows | N19: https://attack.mitre.org/techniques/T1098/
A20: Nation-state | B20: Critical business-service disruption | C20: Identity and credential compromise | D20: T1087 | E20: Account Discovery | F20: S4 | G20: TRUE | H20: TRUE | I20: TRUE | J20: 0.6 | K20: 0 | L20: 0 | M20: Identity Provider; SaaS; Windows | N20: https://attack.mitre.org/techniques/T1087/
A21: Nation-state | B21: Critical business-service disruption | C21: Identity and credential compromise | D21: T1213 | E21: Data from Information Repositories | F21: S4 | G21: TRUE | H21: FALSE | I21: FALSE | J21: 0.8 | K21: 0.17789062 | L21: 0.17789062 | M21: SaaS; Office Suite; Windows | N21: https://attack.mitre.org/techniques/T1213/
A22: Nation-state | B22: Critical business-service disruption | C22: Identity and credential compromise | D22: T1567 | E22: Exfiltration Over Web Service | F22: S5 | G22: TRUE | H22: FALSE | I22: FALSE | J22: 0.7 | K22: 0.20625 | L22: 0.20625 | M22: SaaS; Office Suite | N22: https://attack.mitre.org/techniques/T1567/
A23: Nation-state | B23: Critical business-service disruption | C23: Identity and credential compromise | D23: T1657 | E23: Financial Theft | F23: S5 | G23: TRUE | H23: FALSE | I23: FALSE | J23: 0.8 | K23: 0.2756543 | L23: 0.2756543 | M23: SaaS; Office Suite; Identity Provider | N23: https://attack.mitre.org/techniques/T1657/
A24: Nation-state | B24: Critical business-service disruption | C24: Identity and credential compromise | D24: T1565 | E24: Data Manipulation | F24: S5 | G24: TRUE | H24: TRUE | I24: TRUE | J24: 0.5 | K24: 0.2206065 | L24: 0.2206065 | M24: SaaS; Databases; Windows | N24: https://attack.mitre.org/techniques/T1565/
A25: Nation-state | B25: Critical business-service disruption | C25: Identity and credential compromise | D25: T1486 | E25: Data Encrypted for Impact | F25: S5 | G25: TRUE | H25: TRUE | I25: TRUE | J25: 0.7 | K25: 0.16875 | L25: 0.16875 | M25: Windows; Linux; IaaS | N25: https://attack.mitre.org/techniques/T1486/
A26: Nation-state | B26: Critical business-service disruption | C26: Identity and credential compromise | D26: T1490 | E26: Inhibit System Recovery | F26: S5 | G26: TRUE | H26: TRUE | I26: TRUE | J26: 0.6 | K26: 0 | L26: 0 | M26: Windows; Linux; IaaS | N26: https://attack.mitre.org/techniques/T1490/
A27: Nation-state | B27: Critical business-service disruption | C27: User endpoint and social engineering | D27: T1566 | E27: Phishing | F27: S1 | G27: TRUE | H27: TRUE | I27: TRUE | J27: 1 | K27: 0.20625 | L27: 0.20625 | M27: Windows; SaaS; Office Suite | N27: https://attack.mitre.org/techniques/T1566/
... A787: Hacktivist | B787: Cyber-enabled theft or fraud | C787: Insider or trusted access | D787: T1657 | E787: Financial Theft | F787: S5 | G787: FALSE | H787: TRUE | I787: FALSE | J787: 0.9 | K787: 0.2756543 | L787: 0.2756543 | M787: SaaS; Office Suite; Identity Provider | N787: https://attack.mitre.org/techniques/T1657/

Sheet 11 Attack Path Calc
A1: 11 — Composite Attack-Path Calculation
A2: Required-stage masks, reference/actual barriers, exposure factors and conditional success.
A5: ENGINE OUTPUT — do not edit. Run the Python engine after changing inputs or sector packs.
A15: Threat actor | B15: Scenario | C15: Route | D15: Path valid | E15: Attempts / yr | F15: Opportunity | G15: P(success) | H15: Duration factor | I15: Exposure factor | J15: Direct factor | K15: Impact factor | L15: S1 required | M15: S1 reference | N15: S1 actual barrier | O15: S1 reference barrier | P15: S1 exposure | Q15: S1 through | R15: S2 required | S15: S2 reference | T15: S2 actual barrier | U15: S2 reference barrier | V15: S2 exposure | W15: S2 through | X15: S3 required | Y15: S3 reference | Z15: S3 actual barrier | AA15: S3 reference barrier | AB15: S3 exposure | AC15: S3 through | AD15: S4 required | AE15: S4 reference | AF15: S4 actual barrier | AG15: S4 reference barrier | AH15: S4 exposure | AI15: S4 through | AJ15: S5 required | AK15: S5 reference | AL15: S5 actual barrier | AM15: S5 reference barrier | AN15: S5 exposure | AO15: S5 through
A16: Nation-state | B16: Critical business-service disruption | C16: Identity and credential compromise | D16: TRUE | E16: 0.0063202247 | F16: 1 | G16: 0.0589875 | H16: 1 | I16: 1 | J16: 1 | K16: 1 | L16: TRUE | M16: 0.3 | N16: 0.24036458 | O16: 0.24036458 | P16: 1 | Q16: 0.3 | R16: FALSE | S16: 1 | T16: 0 | U16: 0 | V16: 1 | W16: 1 | X16: TRUE | Y16: 0.55 | Z16: 0.24775473 | AA16: 0.24775473 | AB16: 1 | AC16: 0.55 | AD16: TRUE | AE16: 0.55 | AF16: 0 | AG16: 0 | AH16: 1 | AI16: 0.55 | AJ16: TRUE | AK16: 0.65 | AL16: 0.12690458 | AM16: 0.12690458 | AN16: 1 | AO16: 0.65
A17: Nation-state | B17: Critical business-service disruption | C17: User endpoint and social engineering | D17: TRUE | E17: 0.0055617978 | F17: 1 | G17: 0.025515 | H17: 1 | I17: 1 | J17: 1 | K17: 1 | L17: TRUE | M17: 0.35 | N17: 0.20625 | O17: 0.20625 | P17: 1 | Q17: 0.35 | R17: TRUE | S17: 0.6 | T17: 0.21243746 | U17: 0.21243746 | V17: 1 | W17: 0.6 | X17: TRUE | Y17: 0.45 | Z17: 0.22161833 | AA17: 0.22161833 | AB17: 1 | AC17: 0.45 | AD17: TRUE | AE17: 0.45 | AF17: 0.17946429 | AG17: 0.17946429 | AH17: 1 | AI17: 0.45 | AJ17: TRUE | AK17: 0.6 | AL17: 0.12265162 | AM17: 0.12265162 | AN17: 1 | AO17: 0.6
A18: Nation-state | B18: Critical business-service disruption | C18: Public-facing application exploitation | D18: TRUE | E18: 0.0096910112 | F18: 1 | G18: 0.02025 | H18: 1 | I18: 1 | J18: 1 | K18: 1 | L18: TRUE | M18: 0.25 | N18: 0.24966305 | O18: 0.24966305 | P18: 1 | Q18: 0.25 | R18: TRUE | S18: 0.6 | T18: 0.1875 | U18: 0.1875 | V18: 1 | W18: 0.6 | X18: TRUE | Y18: 0.5 | Z18: 0.21997578 | AA18: 0.21997578 | AB18: 1 | AC18: 0.5 | AD18: TRUE | AE18: 0.45 | AF18: 0.1907346 | AG18: 0.1907346 | AH18: 1 | AI18: 0.45 | AJ18: TRUE | AK18: 0.6 | AL18: 0.13741994 | AM18: 0.13741994 | AN18: 1 | AO18: 0.6
A19: Nation-state | B19: Critical business-service disruption | C19: Third-party or software supply chain | D19: TRUE | E19: 0.0063202247 | F19: 1 | G19: 0.196625 | H19: 1 | I19: 1 | J19: 1 | K19: 1 | L19: FALSE | M19: 1 | N19: 0 | O19: 0 | P19: 1 | Q19: 1 | R19: FALSE | S19: 1 | T19: 0 | U19: 0 | V19: 1 | W19: 1 | X19: TRUE | Y19: 0.55 | Z19: 0.22181428 | AA19: 0.22181428 | AB19: 1 | AC19: 0.55 | AD19: TRUE | AE19: 0.55 | AF19: 0 | AG19: 0 | AH19: 1 | AI19: 0.55 | AJ19: TRUE | AK19: 0.65 | AL19: 0.19703536 | AM19: 0.19703536 | AN19: 1 | AO19: 0.65
A20: Nation-state | B20: Critical business-service disruption | C20: Direct availability or DDoS | D20: TRUE | E20: 0.0016853933 | F20: 1 | G20: 0.36 | H20: 1 | I20: 1 | J20: 1 | K20: 1 | L20: TRUE | M20: 0.6 | N20: 0.28669922 | O20: 0.28669922 | P20: 1 | Q20: 0.6 | R20: FALSE | S20: 1 | T20: 0 | U20: 0 | V20: 1 | W20: 1 | X20: FALSE | Y20: 1 | Z20: 0 | AA20: 0 | AB20: 1 | AC20: 1 | AD20: FALSE | AE20: 1 | AF20: 0 | AG20: 0 | AH20: 1 | AI20: 1 | AJ20: TRUE | AK20: 0.6 | AL20: 0.225 | AM20: 0.225 | AN20: 1 | AO20: 0.6
A21: Nation-state | B21: Critical business-service disruption | C21: Insider or trusted access | D21: TRUE | E21: 0.00042134831 | F21: 1 | G21: 0.29575 | H21: 1 | I21: 1 | J21: 1 | K21: 1 | L21: FALSE | M21: 1 | N21: 0 | O21: 0 | P21: 1 | Q21: 1 | R21: FALSE | S21: 1 | T21: 0 | U21: 0 | V21: 1 | W21: 1 | X21: TRUE | Y21: 0.7 | Z21: 0.24775473 | AA21: 0.24775473 | AB21: 1 | AC21: 0.7 | AD21: TRUE | AE21: 0.65 | AF21: 0 | AG21: 0 | AH21: 1 | AI21: 0.65 | AJ21: TRUE | AK21: 0.65 | AL21: 0.2206065 | AM21: 0.2206065 | AN21: 1 | AO21: 0.65
A22: Nation-state | B22: Sensitive-data compromise | C22: Identity and credential compromise | D22: TRUE | E22: 0.014858491 | F22: 1 | G22: 0.0589875 | H22: 1 | I22: 1 | J22: 1 | K22: 1 | L22: TRUE | M22: 0.3 | N22: 0.24036458 | O22: 0.24036458 | P22: 1 | Q22: 0.3 | R22: FALSE | S22: 1 | T22: 0 | U22: 0 | V22: 1 | W22: 1 | X22: TRUE | Y22: 0.55 | Z22: 0.24775473 | AA22: 0.24775473 | AB22: 1 | AC22: 0.55 | AD22: TRUE | AE22: 0.55 | AF22: 0.10165179 | AG22: 0.10165179 | AH22: 1 | AI22: 0.55 | AJ22: TRUE | AK22: 0.65 | AL22: 0.20625 | AM22: 0.20625 | AN22: 1 | AO22: 0.65
A23: Nation-state | B23: Sensitive-data compromise | C23: User endpoint and social engineering | D23: TRUE | E23: 0.0065377358 | F23: 1 | G23: 0.025515 | H23: 1 | I23: 1 | J23: 1 | K23: 1 | L23: TRUE | M23: 0.35 | N23: 0.20625 | O23: 0.20625 | P23: 1 | Q23: 0.35 | R23: TRUE | S23: 0.6 | T23: 0.21243746 | U23: 0.21243746 | V23: 1 | W23: 0.6 | X23: TRUE | Y23: 0.45 | Z23: 0.22161833 | AA23: 0.22161833 | AB23: 1 | AC23: 0.45 | AD23: TRUE | AE23: 0.45 | AF23: 0.17893973 | AG23: 0.17893973 | AH23: 1 | AI23: 0.45 | AJ23: TRUE | AK23: 0.6 | AL23: 0.20625 | AM23: 0.20625 | AN23: 1 | AO23: 0.6
A24: Nation-state | B24: Sensitive-data compromise | C24: Public-facing application exploitation | D24: TRUE | E24: 0.011391509 | F24: 1 | G24: 0.02025 | H24: 1 | I24: 1 | J24: 1 | K24: 1 | L24: TRUE | M24: 0.25 | N24: 0.24966305 | O24: 0.24966305 | P24: 1 | Q24: 0.25 | R24: TRUE | S24: 0.6 | T24: 0.1875 | U24: 0.1875 | V24: 1 | W24: 0.6 | X24: TRUE | Y24: 0.5 | Z24: 0.21997578 | AA24: 0.21997578 | AB24: 1 | AC24: 0.5 | AD24: TRUE | AE24: 0.45 | AF24: 0.1907346 | AG24: 0.1907346 | AH24: 1 | AI24: 0.45 | AJ24: TRUE | AK24: 0.6 | AL24: 0.20625 | AM24: 0.20625 | AN24: 1 | AO24: 0.6
A25: Nation-state | B25: Sensitive-data compromise | C25: Third-party or software supply chain | D25: TRUE | E25: 0.0084198113 | F25: 1 | G25: 0.196625 | H25: 1 | I25: 1 | J25: 1 | K25: 1 | L25: FALSE | M25: 1 | N25: 0 | O25: 0 | P25: 1 | Q25: 1 | R25: FALSE | S25: 1 | T25: 0 | U25: 0 | V25: 1 | W25: 1 | X25: TRUE | Y25: 0.55 | Z25: 0.22181428 | AA25: 0.22181428 | AB25: 1 | AC25: 0.55 | AD25: TRUE | AE25: 0.55 | AF25: 0.10376953 | AG25: 0.10376953 | AH25: 1 | AI25: 0.55 | AJ25: TRUE | AK25: 0.65 | AL25: 0.20625 | AM25: 0.20625 | AN25: 1 | AO25: 0.65
A26: Nation-state | B26: Sensitive-data compromise | C26: Direct availability or DDoS | D26: FALSE | E26: 0 | F26: 1 | G26: 0 | H26: 1 | I26: 1 | J26: 1 | K26: 1 | L26: FALSE | M26: 1 | N26: 0 | O26: 0 | P26: 1 | Q26: 1 | R26: FALSE | S26: 1 | T26: 0 | U26: 0 | V26: 1 | W26: 1 | X26: FALSE | Y26: 1 | Z26: 0 | AA26: 0 | AB26: 1 | AC26: 1 | AD26: FALSE | AE26: 1 | AF26: 0 | AG26: 0 | AH26: 1 | AI26: 1 | AJ26: FALSE | AK26: 1 | AL26: 0 | AM26: 0 | AN26: 1 | AO26: 1
A27: Nation-state | B27: Sensitive-data compromise | C27: Insider or trusted access | D27: TRUE | E27: 0.00079245283 | F27: 1 | G27: 0.29575 | H27: 1 | I27: 1 | J27: 1 | K27: 1 | L27: FALSE | M27: 1 | N27: 0 | O27: 0 | P27: 1 | Q27: 1 | R27: FALSE | S27: 1 | T27: 0 | U27: 0 | V27: 1 | W27: 1 | X27: TRUE | Y27: 0.7 | Z27: 0.24775473 | AA27: 0.24775473 | AB27: 1 | AC27: 0.7 | AD27: TRUE | AE27: 0.65 | AF27: 0.10673438 | AG27: 0.10673438 | AH27: 1 | AI27: 0.65 | AJ27: TRUE | AK27: 0.65 | AL27: 0.20625 | AM27: 0.20625 | AN27: 1 | AO27: 0.65
... A111: Hacktivist | B111: Cyber-enabled theft or fraud | C111: Insider or trusted access | D111: TRUE | E111: 0.00014814815 | F111: 1 | G111: 0.455 | H111: 1 | I111: 1 | J111: 1 | K111: 1 | L111: FALSE | M111: 1 | N111: 0 | O111: 0 | P111: 1 | Q111: 1 | R111: FALSE | S111: 1 | T111: 0 | U111: 0 | V111: 1 | W111: 1 | X111: TRUE | Y111: 0.7 | Z111: 0.24775473 | AA111: 0.24775473 | AB111: 1 | AC111: 0.7 | AD111: FALSE | AE111: 1 | AF111: 0 | AG111: 0 | AH111: 1 | AI111: 1 | AJ111: TRUE | AK111: 0.65 | AL111: 0.2206065 | AM111: 0.2206065 | AN111: 1 | AO111: 0.65

Sheet 12 Frequency and Success
A1: 12 — Threat and Successful-Event Frequency
A2: Campaign-rate allocation and successful-event frequency by actor, scenario and route.
A5: ENGINE OUTPUT — do not edit. Run the Python engine after changing inputs or sector packs.
A15: Threat actor | B15: Scenario | C15: Route | D15: Attempts / yr | E15: P(success) | F15: Events / yr | G15: P50 loss | H15: P99 loss | I15: Expected event loss | J15: AAL | K15: Exposure model
A16: Nation-state | B16: Critical business-service disruption | C16: Identity and credential compromise | D16: 0.0063202247 | E16: 0.0589875 | F16: 0.00037281426 | G16: 4420753.4 | H16: 90133014 | I16: 10186142 | J16: 3797.5389 | K16: No
A17: Nation-state | B17: Critical business-service disruption | C17: User endpoint and social engineering | D17: 0.0055617978 | E17: 0.025515 | F17: 0.00014190927 | G17: 4420753.4 | H17: 90133014 | I17: 10186142 | J17: 1445.5079 | K17: No
A18: Nation-state | B18: Critical business-service disruption | C18: Public-facing application exploitation | D18: 0.0096910112 | E18: 0.02025 | F18: 0.00019624298 | G18: 4420753.4 | H18: 90133014 | I18: 10186142 | J18: 1998.9588 | K18: No
A19: Nation-state | B19: Critical business-service disruption | C19: Third-party or software supply chain | D19: 0.0063202247 | E19: 0.196625 | F19: 0.0012427142 | G19: 4420753.4 | H19: 90133014 | I19: 10186142 | J19: 12658.463 | K19: No
A20: Nation-state | B20: Critical business-service disruption | C20: Direct availability or DDoS | D20: 0.0016853933 | E20: 0.36 | F20: 0.00060674157 | G20: 4420753.4 | H20: 90133014 | I20: 10186142 | J20: 6180.3557 | K20: No
A21: Nation-state | B21: Critical business-service disruption | C21: Insider or trusted access | D21: 0.00042134831 | E21: 0.29575 | F21: 0.00012461376 | G21: 4420753.4 | H21: 90133014 | I21: 10186142 | J21: 1269.3335 | K21: No
A22: Nation-state | B22: Sensitive-data compromise | C22: Identity and credential compromise | D22: 0.014858491 | E22: 0.0589875 | F22: 0.00087646521 | G22: 5093972.6 | H22: 88368904 | I22: 10775409 | J22: 9444.271 | K22: No
A23: Nation-state | B23: Sensitive-data compromise | C23: User endpoint and social engineering | D23: 0.0065377358 | E23: 0.025515 | F23: 0.00016681033 | G23: 5093972.6 | H23: 88368904 | I23: 10775409 | J23: 1797.4495 | K23: No
A24: Nation-state | B24: Sensitive-data compromise | C24: Public-facing application exploitation | D24: 0.011391509 | E24: 0.02025 | F24: 0.00023067807 | G24: 5093972.6 | H24: 88368904 | I24: 10775409 | J24: 2485.6505 | K24: No
A25: Nation-state | B25: Sensitive-data compromise | C25: Third-party or software supply chain | D25: 0.0084198113 | E25: 0.196625 | F25: 0.0016555454 | G25: 5093972.6 | H25: 88368904 | I25: 10775409 | J25: 17839.179 | K25: No
A26: Nation-state | B26: Sensitive-data compromise | C26: Direct availability or DDoS | D26: 0 | E26: 0 | F26: 0 | G26: 5093972.6 | H26: 88368904 | I26: 10775409 | J26: 0 | K26: No
A27: Nation-state | B27: Sensitive-data compromise | C27: Insider or trusted access | D27: 0.00079245283 | E27: 0.29575 | F27: 0.00023436792 | G27: 5093972.6 | H27: 88368904 | I27: 10775409 | J27: 2525.4102 | K27: No
... A111: Hacktivist | B111: Cyber-enabled theft or fraud | C111: Insider or trusted access | D111: 0.00014814815 | E111: 0.455 | F111: 6.7407407e-05 | G111: 1835000 | H111: 29830000 | I111: 3754990.8 | J111: 253.11419 | K111: No

Sheet 13 Consequence Calc
A1: 13 — Consequence Calculation
A2: Bottom-up P50/P99 driver calculation and fitted loss distributions.
A5: ENGINE OUTPUT — do not edit. Run the Python engine after changing inputs or sector packs.
A15: Threat actor | B15: Scenario ID | C15: Scenario | D15: Loss block | E15: Driver | F15: Quantile | G15: Amount | H15: Applicable | I15: Evidence grade | J15: Source ID
A16: Nation-state | B16: SC_DISR | C16: Critical business-service disruption | D16: Duration | E16: IR_FORENSICS | F16: P50 | G16: 20000 | H16: TRUE | I16: D | J16: SRC-10
A17: Nation-state | B17: SC_DISR | C17: Critical business-service disruption | D17: Duration | E17: EXTERNAL_RESPONSE | F17: P50 | G17: 30000 | H17: TRUE | I17: D | J17: SRC-10
A18: Nation-state | B18: SC_DISR | C18: Critical business-service disruption | D18: Duration | E18: LEGAL_RESPONSE | F18: P50 | G18: 25000 | H18: TRUE | I18: D | J18: SRC-10
A19: Nation-state | B19: SC_DISR | C19: Critical business-service disruption | D19: Duration | E19: RESTORATION | F19: P50 | G19: 30000 | H19: TRUE | I19: D | J19: SRC-10
A20: Nation-state | B20: SC_DISR | C20: Critical business-service disruption | D20: Duration | E20: BUSINESS_INTERRUPTION | F20: P50 | G20: 2465753.4 | H20: TRUE | I20: D | J20: SRC-10
A21: Nation-state | B21: SC_DISR | C21: Critical business-service disruption | D21: Duration | E21: ENDPOINT_RECOVERY | F21: P50 | G21: 100000 | H21: TRUE | I21: D | J21: SRC-10
A22: Nation-state | B22: SC_DISR | C22: Critical business-service disruption | D22: Duration | E22: SERVER_RECOVERY | F22: P50 | G22: 250000 | H22: TRUE | I22: D | J22: SRC-10
A23: Nation-state | B23: SC_DISR | C23: Critical business-service disruption | D23: Exposure | E23: NOTIFICATION | F23: P50 | G23: 0 | H23: FALSE | I23: D | J23: SRC-10
A24: Nation-state | B24: SC_DISR | C24: Critical business-service disruption | D24: Exposure | E24: CREDIT_MONITORING | F24: P50 | G24: 0 | H24: FALSE | I24: D | J24: SRC-10
A25: Nation-state | B25: SC_DISR | C25: Critical business-service disruption | D25: Exposure | E25: REGULATORY | F25: P50 | G25: 0 | H25: FALSE | I25: D | J25: SRC-10
A26: Nation-state | B26: SC_DISR | C26: Critical business-service disruption | D26: Exposure | E26: CUSTOMER_ATTRITION | F26: P50 | G26: 1000000 | H26: TRUE | I26: D | J26: SRC-10
A27: Nation-state | B27: SC_DISR | C27: Critical business-service disruption | D27: Direct | E27: FRAUD_NET_RECOVERY | F27: P50 | G27: 0 | H27: FALSE | I27: D | J27: SRC-10
... A463: Hacktivist | B463: SC_FRAUD | C463: Cyber-enabled theft or fraud | D463: Direct | E463: POST_EVENT_UPLIFT | F463: P99 | G463: 5000000 | H463: TRUE | I463: D | J463: SRC-10

Sheet 14 Actor Scenario Matrix
A1: 14 — Actor–Scenario Matrix
A2: AAL and event-frequency matrices for the selected reporting basis.
A5: ENGINE OUTPUT — do not edit. Run the Python engine after changing inputs or sector packs.
A15: AAL — Prudent | B15: Critical business-service disruption | C15: Sensitive-data compromise | D15: Data or transaction-integrity compromise | E15: Cyber-enabled theft or fraud
A16: Nation-state | B16: 34187.697 | C16: 42614.95 | D16: 39497.047 | E16: 7587.3365
A17: Cybercriminal | B17: 251325.1 | C17: 143618.54 | D17: 59240.441 | E17: 185707.97
A18: Malicious insider | B18: 58482.762 | C18: 94468.793 | D18: 81826.093 | E18: 63923.536
A19: Hacktivist | B19: 229475.94 | C19: 9152.9954 | D19: 6470.7715 | E19: 1137.5952

Sheet 15 Tail Risk Metrics
A1: 15 — Tail-Risk Metrics
A2: Annual aggregate and occurrence loss metrics for both reporting bases.
A5: ENGINE OUTPUT — do not edit. Run the Python engine after changing inputs or sector packs.
A15: Metric | B15: Best Estimate | C15: Prudent | D15: Definition
A16: AAL | B16: 1059877.3 | C16: 1311679.4 | D16: Mean annual aggregate loss
A17: VaR 95% | B17: 5487402.5 | C17: 7125948 | D17: 95th percentile
A18: TVaR 95% | B18: 18021076 | C18: 20885315 | D18: Exact mean of the worst 5% of annual outcomes
A19: VaR 99% | B19: 22824448 | C19: 26218159 | D19: 99th percentile
A20: TVaR 99% | B20: 46179340 | C20: 51675145 | D20: Exact mean of the worst 1% of annual outcomes
A21: P(any event) | B21: 0.114878 | C21: 0.140772 | D21: Positive-loss year share

Sheet 16 Control What-If
A1: 16 — Control What-If
A2: One-level maturity uplift using the same reference-relative attack-path method.
A5: ENGINE OUTPUT — do not edit. Run the Python engine after changing inputs or sector packs.
A15: Control ID | B15: Control family | C15: Current maturity | D15: What-if maturity | E15: Analytic current AAL | F15: Analytic what-if AAL | G15: AAL reduction | H15: Reduction % | I15: Method | J15: View
A16: C03 | B16: Privileged access management | C16: Developing | D16: Managed | E16: 1308717.6 | F16: 1200150.2 | G16: 108567.33 | H16: 0.082957039 | I16: One-level uplift | J16: Prudent
A17: C13 | B17: DDoS protection and service resilience | C17: Developing | D17: Managed | E17: 1308717.6 | F17: 1214101.7 | G17: 94615.903 | H17: 0.072296656 | I17: One-level uplift | J17: Prudent
A18: C15 | B18: Payment and fraud controls | C18: Developing | D18: Managed | E18: 1308717.6 | F18: 1228605.4 | G18: 80112.178 | H18: 0.06121426 | I18: One-level uplift | J18: Prudent
A19: C11 | B19: Data protection and DLP | C19: Developing | D19: Managed | E19: 1308717.6 | F19: 1232571 | G19: 76146.594 | H19: 0.058184131 | I19: One-level uplift | J19: Prudent
A20: C02 | B20: Identity, authentication and MFA | C20: Developing | D20: Managed | E20: 1308717.6 | F20: 1236947.2 | G20: 71770.39 | H20: 0.054840243 | I20: One-level uplift | J20: Prudent
A21: C08 | B21: Cloud and SaaS security | C21: Developing | D21: Managed | E21: 1308717.6 | F21: 1244829 | G21: 63888.595 | H21: 0.04881771 | I21: One-level uplift | J21: Prudent
A22: C10 | B22: Logging, detection and threat response | C22: Developing | D22: Managed | E22: 1308717.6 | F22: 1260077 | G22: 48640.544 | H22: 0.03716657 | I22: One-level uplift | J22: Prudent
A23: C14 | B23: Backup, recovery and crisis management | C23: Developing | D23: Managed | E23: 1308717.6 | F23: 1268294.7 | G23: 40422.873 | H23: 0.030887393 | I23: One-level uplift | J23: Prudent
A24: C05 | B24: Endpoint protection and execution control | C24: Developing | D24: Managed | E24: 1308717.6 | F24: 1280563.7 | G24: 28153.911 | H24: 0.021512595 | I24: One-level uplift | J24: Prudent
A25: C04 | B25: Email, web security and awareness | C25: Developing | D25: Managed | E25: 1308717.6 | F25: 1283820 | G25: 24897.573 | H25: 0.019024405 | I25: One-level uplift | J25: Prudent
A26: C12 | B26: Third-party and supply-chain security | C26: Developing | D26: Managed | E26: 1308717.6 | F26: 1291144.9 | G26: 17572.631 | H26: 0.013427367 | I26: One-level uplift | J26: Prudent
A27: C09 | B27: Application and API security | C27: Developing | D27: Managed | E27: 1308717.6 | F27: 1291447.4 | G27: 17270.134 | H27: 0.013196227 | I27: One-level uplift | J27: Prudent
... A30: C01 | B30: Asset and vulnerability management | C30: Developing | D30: Managed | E30: 1308717.6 | F30: 1307519.3 | G30: 1198.275 | H30: 0.00091561011 | I30: One-level uplift | J30: Prudent

Sheet 17 Aggregate LECs
A1: 17 — Aggregate Loss-Exceedance Curves
A2: AEP and OEP points for best-estimate and prudent annual loss.
A5: ENGINE OUTPUT — do not edit. Run the Python engine after changing inputs or sector packs.
A15: Return period | B15: Exceedance probability | C15: Best AEP | D15: Best OEP | E15: Prudent AEP | F15: Prudent OEP
A16: 2 | B16: 0.5 | C16: 0 | D16: 0 | E16: 0 | F16: 0
A17: 5 | B17: 0.2 | C17: 0 | D17: 0 | E17: 0 | F17: 0
A18: 10 | B18: 0.1 | C18: 1129968.6 | D18: 1125096.3 | E18: 2334831.3 | F18: 2302523.3
A19: 20 | B19: 0.05 | C19: 5487402.5 | D19: 5365555.6 | E19: 7125948 | F19: 6877809
A20: 25 | B20: 0.04 | C20: 7219261.1 | D20: 7013988.3 | E20: 9033417 | F20: 8724690.7
A21: 50 | B21: 0.02 | C21: 13910287 | D21: 13453879 | E21: 16402002 | F21: 15693036
A22: 100 | B22: 0.01 | C22: 22824448 | D22: 22150406 | E22: 26218159 | F22: 25214416
A23: 200 | B23: 0.005 | C23: 34164820 | D23: 33340556 | E23: 39100630 | F23: 37983893
A24: 250 | B24: 0.004 | C24: 38734254 | D24: 37843498 | E24: 44082084 | F24: 42528113
A25: 500 | B25: 0.002 | C25: 56099057 | D25: 54762579 | E25: 61587868 | F25: 60373105

Sheet 18 Scenario LECs
A1: 18 — Scenario Loss-Exceedance Curves
A2: Scenario-specific AEP points for the selected reporting basis.
A5: ENGINE OUTPUT — do not edit. Run the Python engine after changing inputs or sector packs.
A15: Return period | B15: Exceedance probability | C15: Critical business-service disruption | D15: Sensitive-data compromise | E15: Data or transaction-integrity compromise | F15: Cyber-enabled theft or fraud
A16: 2 | B16: 0.5 | C16: 0 | D16: 0 | E16: 0 | F16: 0
A17: 5 | B17: 0.2 | C17: 0 | D17: 0 | E17: 0 | F17: 0
A18: 10 | B18: 0.1 | C18: 0 | D18: 0 | E18: 0 | F18: 0
A19: 20 | B19: 0.05 | C19: 421378.54 | D19: 0 | E19: 0 | F19: 355893.83
A20: 25 | B20: 0.04 | C20: 2339461.3 | D20: 0 | E20: 0 | F20: 1028185.8
A21: 50 | B21: 0.02 | C21: 7600857.9 | D21: 2813518.2 | E21: 0 | F21: 3408565.4
A22: 100 | B22: 0.01 | C22: 15039969 | D22: 8461016.1 | E22: 5108821.5 | F22: 6844977.2
A23: 200 | B23: 0.005 | C23: 25192120 | D23: 15650432 | E23: 10508730 | F23: 11530859
A24: 250 | B24: 0.004 | C24: 29232497 | D24: 18573322 | E24: 12521024 | F24: 13369947
A25: 500 | B25: 0.002 | C25: 44605621 | D25: 29439196 | E25: 20150316 | F25: 20118216

Sheet 19 Actor LECs
A1: 19 — Actor Loss-Exceedance Curves
A2: Actor-specific AEP points for the selected reporting basis.
A5: ENGINE OUTPUT — do not edit. Run the Python engine after changing inputs or sector packs.
A15: Return period | B15: Exceedance probability | C15: Nation-state | D15: Cybercriminal | E15: Malicious insider | F15: Hacktivist
A16: 2 | B16: 0.5 | C16: 0 | D16: 0 | E16: 0 | F16: 0
A17: 5 | B17: 0.2 | C17: 0 | D17: 0 | E17: 0 | F17: 0
A18: 10 | B18: 0.1 | C18: 0 | D18: 0 | E18: 0 | F18: 0
A19: 20 | B19: 0.05 | C19: 0 | D19: 2309382.9 | E19: 0 | F19: 0
A20: 25 | B20: 0.04 | C20: 0 | D20: 3598846 | E20: 0 | F20: 0
A21: 50 | B21: 0.02 | C21: 0 | D21: 8800838.2 | E21: 3554874.3 | F21: 1869379.2
A22: 100 | B22: 0.01 | C22: 2412035.6 | D22: 16138275 | E22: 8325961.9 | F22: 6353896.7
A23: 200 | B23: 0.005 | C23: 6678825.2 | D23: 26076029 | E23: 14709660 | F23: 12493850
A24: 250 | B24: 0.004 | C24: 8291438.2 | D24: 29616977 | E24: 17204672 | F24: 15039969
A25: 500 | B25: 0.002 | C25: 14614692 | D25: 43843924 | E25: 26816946 | F25: 24515311

Sheet 20 Risk Charts
A1: 20 — Risk Charts
A2: Legacy helper ranges retained for engine compatibility. Interactive presentation moved to the 00 Dashboard suite.
A4: Charts refresh when the Python engine rewrites the result workbook.
A15: Threat actor | B15: AAL
A16: Nation-state | B16: 119201.14
A17: Cybercriminal | B17: 651035.53
A18: Malicious insider | B18: 301385.84
A19: Hacktivist | B19: 240056.84
A22: Scenario | B22: AAL
A23: Critical business-service disruption | B23: 575998.21
A24: Sensitive-data compromise | B24: 292163.99
A25: Data or transaction-integrity compromise | B25: 183681.88
A26: Cyber-enabled theft or fraud | B26: 259835.28
A29: Return period | B29: Best AEP | C29: Prudent AEP
A30: 2 | B30: 0 | C30: 0
A31: 5 | B31: 0 | C31: 0
A32: 10 | B32: 1129968.6 | C32: 2334831.3
A33: 20 | B33: 5487402.5 | C33: 7125948
A34: 25 | B34: 7219261.1 | C34: 9033417
A35: 50 | B35: 13910287 | C35: 16402002
A36: 100 | B36: 22824448 | C36: 26218159
A37: 200 | B37: 34164820 | C37: 39100630
A38: 250 | B38: 38734254 | C38: 44082084
A39: 500 | B39: 56099057 | C39: 61587868

Sheet 21 Sources and Evidence
A1: 21 — Sources and Evidence
A2: Core methodology sources and important limitations. Pack-specific sources remain in the separate sector workbook.
A15: Source ID | B15: Source | C15: URL / file | D15: How used | E15: Limitation
A16: CORE-01 | B16: MITRE Enterprise ATT&CK | C16: https://attack.mitre.org/matrices/enterprise/ | D16: Technique taxonomy | E16: Not a probability dataset
A17: CORE-02 | B17: MITRE Enterprise mitigations | C17: https://attack.mitre.org/mitigations/enterprise/ | D17: Control-mitigation mapping | E17: Does not quantify efficacy
A18: CORE-03 | B18: NIST CSF 2.0 | C18: https://nvlpubs.nist.gov/nistpubs/CSWP/NIST.CSWP.29.pdf | D18: Control-family governance | E18: Outcome framework
A19: CORE-04 | B19: CISA KEV | C19: https://www.cisa.gov/known-exploited-vulnerabilities-catalog | D19: Future exposure-model evidence | E19: Not annual organisation frequency
A20: CORE-05 | B20: FIRST EPSS | C20: https://www.first.org/epss/ | D20: Future exposure-model evidence | E20: 30-day population probability only
A21: CORE-06 | B21: Guided OT CRQ v1.7 | C21: Guided_OT_CRQ_Model_v1_7.xlsx | D21: Reference-relative controls, composite stages, Monte Carlo and reporting architecture | E21: OT content not reused as IT calibration
A22: CORE-07 | B22: Balbix Breach Impact Model | C22: Balbix Breach Impact Model.xlsx | D22: Impact-driver structure and identifiable rate assumptions | E22: Taxonomy and formulas rebuilt for this model

Sheet 22 Validation Tests
A1: 22 — Validation Tests
A2: Python-populated structural, numerical, monotonicity and pack-interface checks.
A15: Test | B15: Status | C15: Actual | D15: Expected | E15: Location / remediation
A16: Sector-pack schema | B16: PASS | C16: CRQ-PACK-1.1 | D16: CRQ-PACK-1.1 | E16: Update pack or engine.
A17: Evidence grades valid | B17: PASS | C17: Valid | D17: A-D | E17: Correct pack grade.
A18: Exposure switch neutralisation | B18: PASS | C18: Neutral | D18: Neutral when No | E18: Review exposure interface.
A19: Baseline attempt frequency preserved | B19: PASS | C19: 1 | D19: 1 | E19: Review route renormalisation.
A20: Positive actor-scenario cells have valid paths | B20: PASS | C20: Covered | D20: Covered | E20: Review stage and ATT&CK applicability.
A21: No dead route-technique mappings | B21: PASS | C21: None | D21: None | E21: Correct mapping.
A22: All-zero stage masks inactive | B22: PASS | C22: None | D22: None with non-zero pooled route propensity | E22: Set at least one required stage or zero the route propensity.
A23: Loss-block P99 >= P50 | B23: PASS | C23: Ordered | D23: Ordered | E23: Review impact assumptions.
A24: Control ratios bounded | B24: PASS | C24: Bounded | D24: Within pack bounds | E24: Review aggregation.
A25: Common random numbers reproducible | B25: PASS | C25: Exact match | D25: Exact match | E25: Use same seed/order.
A26: Simulation AAL reconciles to analytic AAL | B26: PASS | C26: 1059877.3 | D26: 1046974.1 | E26: Increase years or review means.
A27: TVaR not below VaR | B27: PASS | C27: Valid | D27: TVaR >= VaR | E27: Review tail metrics.
A28: Sparse-loss exact TVaR | B28: PASS | C28: 20 | D28: 20 | E28: Restore fractional upper-tail expected shortfall.
A29: Diminishing-return control aggregation | B29: PASS | C29: 0.58050928 | D29: 0.58050928 | E29: Use remaining-gap OT recursion and barrier cap.
A30: Reporting-view resolution | B30: PASS | C30: Prudent | D30: Prudent | E30: Use one reporting-view resolver for outputs and what-ifs.
A31: AEP/OEP valid | B31: PASS | C31: Valid | D31: Monotonic; OEP <= AEP | E31: Review curves.
A32: Control what-ifs non-increasing | B32: PASS | C32: 1198.275 | D32: >= 0 | E32: Review control channels.
A33: Actor/scenario AAL reconcile | B33: PASS | C33: 2.3283064e-10 | D33: 0 | E33: Review decomposition.
A34: Simulation finite | B34: PASS | C34: Finite | D34: Finite | E34: Review inputs.

Sheet 00 Dashboard
A1: IT CYBER RISK QUANTIFICATION | EXECUTIVE DASHBOARD
A3: Decision view of financial risk, tail exposure, scenario/actor concentration and control opportunities. Engine output sheets remain the system of record.
A4: Sector | B4: ='02 Executive Summary'!B22 | E4: Pack | F4: ='02 Executive Summary'!B23 | I4: Detailed view | J4: ='08 Tail Risk Settings'!B16 | L4: Last run | M4: ='02 Executive Summary'!B26
A6: Reporting basis | B6: Prudent | D6: Loss curve | E6: AEP | G6: Return period | H6: 100 | J6: Selected loss | K6: =IFERROR(IF($B$6="Best Estimate",IF($E$6="AEP",INDEX('17 Aggregate LECs'!$C$16:$C$25,MATCH($H$6,'17 Aggregate LECs'!$A$16:$A$25,0)),INDEX('17 Aggregate LECs'!$D$16:$D$25,MATCH($H$6,'17 Aggregate LECs'!$A$16:$A$25,0))),IF($E$6="AEP",INDEX('17 Aggregate LECs'!$E$16:$E$25,MATCH($H$6,'17 Aggregate LECs'!$A$16:$A$25,0)),INDEX('17 Aggregate LECs'!$F$16:$F$25,MATCH($H$6,'17 Aggregate LECs'!$A$16:$A$25,0)))),"")
A8: ANNUAL AVERAGE LOSS | D8: TVaR 95% | G8: TVaR 99% | J8: P(ANY SUCCESSFUL EVENT) | M8: SUCCESSFUL EVENTS / YEAR
A9: =IF($B$6="Best Estimate",'02 Executive Summary'!B7,'02 Executive Summary'!C7) | D9: =IF($B$6="Best Estimate",'02 Executive Summary'!B9,'02 Executive Summary'!C9) | G9: =IF($B$6="Best Estimate",'02 Executive Summary'!B11,'02 Executive Summary'!C11) | J9: =IF($B$6="Best Estimate",'02 Executive Summary'!B18,'02 Executive Summary'!C18) | M9: =IF($B$6="Best Estimate",'02 Executive Summary'!B19,'02 Executive Summary'!C19)
A12: MATERIAL CAMPAIGNS / YEAR | D12: TAIL RISK CONTEXT | J12: CURRENT RISK-TRANSFER INPUT
A13: =IF($B$6="Best Estimate",'02 Executive Summary'!B20,'02 Executive Summary'!C20) | D13: ="1-in-20: "&TEXT(IF($B$6="Best Estimate",'02 Executive Summary'!B8,'02 Executive Summary'!C8),"$#,##0")&" | 1-in-100: "&TEXT(IF($B$6="Best Estimate",'02 Executive Summary'!B10,'02 Executive Summary'!C10),"$#,##0") | J13: ="Retention: "&TEXT('02 Executive Summary'!B13,"$#,##0")&" | Tail above retention: "&TEXT(IF($B$6="Best Estimate",'02 Executive Summary'!B14,'02 Executive Summary'!C14),"$#,##0")
A16: AGGREGATE LOSS EXCEEDANCE | J16: RISK CONCENTRATION
A36: TOP CONTROL OPPORTUNITIES — CURRENT ENGINE REPORTING VIEW
A37: Control | D37: Maturity uplift | F37: AAL reduction | H37: Reduction % | J37: Interpretation AAL = expected annual aggregate loss. TVaR = mean loss beyond the stated percentile. Scenario, actor and what-if decompositions use the engine-selected detailed reporting view shown above. Use the other dashboard tabs for route, loss-driver, control and risk-transfer drill-down.
A38: ='16 Control What-If'!B16 | D38: ='16 Control What-If'!C16&" → "&'16 Control What-If'!D16 | F38: ='16 Control What-If'!G16 | H38: ='16 Control What-If'!H16
A39: ='16 Control What-If'!B17 | D39: ='16 Control What-If'!C17&" → "&'16 Control What-If'!D17 | F39: ='16 Control What-If'!G17 | H39: ='16 Control What-If'!H17
A40: ='16 Control What-If'!B18 | D40: ='16 Control What-If'!C18&" → "&'16 Control What-If'!D18 | F40: ='16 Control What-If'!G18 | H40: ='16 Control What-If'!H18
A41: ='16 Control What-If'!B19 | D41: ='16 Control What-If'!C19&" → "&'16 Control What-If'!D19 | F41: ='16 Control What-If'!G19 | H41: ='16 Control What-If'!H19
A42: ='16 Control What-If'!B20 | D42: ='16 Control What-If'!C20&" → "&'16 Control What-If'!D20 | F42: ='16 Control What-If'!G20 | H42: ='16 Control What-If'!H20
A61: Return period | B61: Selected loss | D61: Scenario | E61: AAL | G61: Threat actor | H61: AAL
A62: ='17 Aggregate LECs'!A16 | B62: =IF($B$6="Best Estimate",IF($E$6="AEP",'17 Aggregate LECs'!C16,'17 Aggregate LECs'!D16),IF($E$6="AEP",'17 Aggregate LECs'!E16,'17 Aggregate LECs'!F16)) | D62: ='02 Executive Summary'!A37 | E62: ='02 Executive Summary'!B37 | G62: ='02 Executive Summary'!A30 | H62: ='02 Executive Summary'!B30
A63: ='17 Aggregate LECs'!A17 | B63: =IF($B$6="Best Estimate",IF($E$6="AEP",'17 Aggregate LECs'!C17,'17 Aggregate LECs'!D17),IF($E$6="AEP",'17 Aggregate LECs'!E17,'17 Aggregate LECs'!F17)) | D63: ='02 Executive Summary'!A38 | E63: ='02 Executive Summary'!B38 | G63: ='02 Executive Summary'!A31 | H63: ='02 Executive Summary'!B31
A64: ='17 Aggregate LECs'!A18 | B64: =IF($B$6="Best Estimate",IF($E$6="AEP",'17 Aggregate LECs'!C18,'17 Aggregate LECs'!D18),IF($E$6="AEP",'17 Aggregate LECs'!E18,'17 Aggregate LECs'!F18)) | D64: ='02 Executive Summary'!A39 | E64: ='02 Executive Summary'!B39 | G64: ='02 Executive Summary'!A32 | H64: ='02 Executive Summary'!B32
A65: ='17 Aggregate LECs'!A19 | B65: =IF($B$6="Best Estimate",IF($E$6="AEP",'17 Aggregate LECs'!C19,'17 Aggregate LECs'!D19),IF($E$6="AEP",'17 Aggregate LECs'!E19,'17 Aggregate LECs'!F19)) | D65: ='02 Executive Summary'!A40 | E65: ='02 Executive Summary'!B40 | G65: ='02 Executive Summary'!A33 | H65: ='02 Executive Summary'!B33
A66: ='17 Aggregate LECs'!A20 | B66: =IF($B$6="Best Estimate",IF($E$6="AEP",'17 Aggregate LECs'!C20,'17 Aggregate LECs'!D20),IF($E$6="AEP",'17 Aggregate LECs'!E20,'17 Aggregate LECs'!F20))
A67: ='17 Aggregate LECs'!A21 | B67: =IF($B$6="Best Estimate",IF($E$6="AEP",'17 Aggregate LECs'!C21,'17 Aggregate LECs'!D21),IF($E$6="AEP",'17 Aggregate LECs'!E21,'17 Aggregate LECs'!F21))
A68: ='17 Aggregate LECs'!A22 | B68: =IF($B$6="Best Estimate",IF($E$6="AEP",'17 Aggregate LECs'!C22,'17 Aggregate LECs'!D22),IF($E$6="AEP",'17 Aggregate LECs'!E22,'17 Aggregate LECs'!F22))
A69: ='17 Aggregate LECs'!A23 | B69: =IF($B$6="Best Estimate",IF($E$6="AEP",'17 Aggregate LECs'!C23,'17 Aggregate LECs'!D23),IF($E$6="AEP",'17 Aggregate LECs'!E23,'17 Aggregate LECs'!F23))
A70: ='17 Aggregate LECs'!A24 | B70: =IF($B$6="Best Estimate",IF($E$6="AEP",'17 Aggregate LECs'!C24,'17 Aggregate LECs'!D24),IF($E$6="AEP",'17 Aggregate LECs'!E24,'17 Aggregate LECs'!F24))
A71: ='17 Aggregate LECs'!A25 | B71: =IF($B$6="Best Estimate",IF($E$6="AEP",'17 Aggregate LECs'!C25,'17 Aggregate LECs'!D25),IF($E$6="AEP",'17 Aggregate LECs'!E25,'17 Aggregate LECs'!F25))

Sheet 00 Risk Drivers
A1: IT CYBER RISK QUANTIFICATION | RISK DRIVERS
A3: Drill from threat actor and scenario into attack routes, frequency, conditional success and AAL. All figures use the engine-selected detailed reporting view.
A4: Detailed reporting view | B4: ='08 Tail Risk Settings'!B16 | E4: Sector | F4: ='02 Executive Summary'!B22 | I4: Pack | J4: ='02 Executive Summary'!B23 | M4: ="Run: "&'02 Executive Summary'!B26
A6: Threat actor | B6: ='02 Executive Summary'!A30 | D6: Scenario | F6: ='02 Executive Summary'!A37 | J6: Risk equation: Attempts / year × P(success) × Expected event loss = AAL
A8: ATTEMPTS / YEAR | D8: P(SUCCESS) | G8: SUCCESSFUL EVENTS / YEAR | J8: EXPECTED EVENT LOSS | M8: AAL
A9: =SUMIFS('12 Frequency and Success'!$D$16:$D$111,'12 Frequency and Success'!$A$16:$A$111,$B$6,'12 Frequency and Success'!$B$16:$B$111,$F$6) | D9: =IFERROR(G9/A9,0) | G9: =SUMIFS('12 Frequency and Success'!$F$16:$F$111,'12 Frequency and Success'!$A$16:$A$111,$B$6,'12 Frequency and Success'!$B$16:$B$111,$F$6) | J9: =IFERROR(M9/G9,0) | M9: =SUMIFS('12 Frequency and Success'!$J$16:$J$111,'12 Frequency and Success'!$A$16:$A$111,$B$6,'12 Frequency and Success'!$B$16:$B$111,$F$6)
A13: ATTACK ROUTE BREAKDOWN | J13: AAL BY ATTACK ROUTE
A14: Attack route | B14: Attempts / yr | C14: P(success) | D14: Events / yr | E14: Expected event loss | F14: AAL
A15: ='04 Exposure Adjustments'!B16 | B15: =SUMIFS('12 Frequency and Success'!$D$16:$D$111,'12 Frequency and Success'!$A$16:$A$111,$B$6,'12 Frequency and Success'!$B$16:$B$111,$F$6,'12 Frequency and Success'!$C$16:$C$111,$A15) | C15: =IFERROR(D15/B15,0) | D15: =SUMIFS('12 Frequency and Success'!$F$16:$F$111,'12 Frequency and Success'!$A$16:$A$111,$B$6,'12 Frequency and Success'!$B$16:$B$111,$F$6,'12 Frequency and Success'!$C$16:$C$111,$A15) | E15: =IFERROR(F15/D15,0) | F15: =SUMIFS('12 Frequency and Success'!$J$16:$J$111,'12 Frequency and Success'!$A$16:$A$111,$B$6,'12 Frequency and Success'!$B$16:$B$111,$F$6,'12 Frequency and Success'!$C$16:$C$111,$A15)
A16: ='04 Exposure Adjustments'!B17 | B16: =SUMIFS('12 Frequency and Success'!$D$16:$D$111,'12 Frequency and Success'!$A$16:$A$111,$B$6,'12 Frequency and Success'!$B$16:$B$111,$F$6,'12 Frequency and Success'!$C$16:$C$111,$A16) | C16: =IFERROR(D16/B16,0) | D16: =SUMIFS('12 Frequency and Success'!$F$16:$F$111,'12 Frequency and Success'!$A$16:$A$111,$B$6,'12 Frequency and Success'!$B$16:$B$111,$F$6,'12 Frequency and Success'!$C$16:$C$111,$A16) | E16: =IFERROR(F16/D16,0) | F16: =SUMIFS('12 Frequency and Success'!$J$16:$J$111,'12 Frequency and Success'!$A$16:$A$111,$B$6,'12 Frequency and Success'!$B$16:$B$111,$F$6,'12 Frequency and Success'!$C$16:$C$111,$A16)
A17: ='04 Exposure Adjustments'!B18 | B17: =SUMIFS('12 Frequency and Success'!$D$16:$D$111,'12 Frequency and Success'!$A$16:$A$111,$B$6,'12 Frequency and Success'!$B$16:$B$111,$F$6,'12 Frequency and Success'!$C$16:$C$111,$A17) | C17: =IFERROR(D17/B17,0) | D17: =SUMIFS('12 Frequency and Success'!$F$16:$F$111,'12 Frequency and Success'!$A$16:$A$111,$B$6,'12 Frequency and Success'!$B$16:$B$111,$F$6,'12 Frequency and Success'!$C$16:$C$111,$A17) | E17: =IFERROR(F17/D17,0) | F17: =SUMIFS('12 Frequency and Success'!$J$16:$J$111,'12 Frequency and Success'!$A$16:$A$111,$B$6,'12 Frequency and Success'!$B$16:$B$111,$F$6,'12 Frequency and Success'!$C$16:$C$111,$A17)
A18: ='04 Exposure Adjustments'!B19 | B18: =SUMIFS('12 Frequency and Success'!$D$16:$D$111,'12 Frequency and Success'!$A$16:$A$111,$B$6,'12 Frequency and Success'!$B$16:$B$111,$F$6,'12 Frequency and Success'!$C$16:$C$111,$A18) | C18: =IFERROR(D18/B18,0) | D18: =SUMIFS('12 Frequency and Success'!$F$16:$F$111,'12 Frequency and Success'!$A$16:$A$111,$B$6,'12 Frequency and Success'!$B$16:$B$111,$F$6,'12 Frequency and Success'!$C$16:$C$111,$A18) | E18: =IFERROR(F18/D18,0) | F18: =SUMIFS('12 Frequency and Success'!$J$16:$J$111,'12 Frequency and Success'!$A$16:$A$111,$B$6,'12 Frequency and Success'!$B$16:$B$111,$F$6,'12 Frequency and Success'!$C$16:$C$111,$A18)
A19: ='04 Exposure Adjustments'!B20 | B19: =SUMIFS('12 Frequency and Success'!$D$16:$D$111,'12 Frequency and Success'!$A$16:$A$111,$B$6,'12 Frequency and Success'!$B$16:$B$111,$F$6,'12 Frequency and Success'!$C$16:$C$111,$A19) | C19: =IFERROR(D19/B19,0) | D19: =SUMIFS('12 Frequency and Success'!$F$16:$F$111,'12 Frequency and Success'!$A$16:$A$111,$B$6,'12 Frequency and Success'!$B$16:$B$111,$F$6,'12 Frequency and Success'!$C$16:$C$111,$A19) | E19: =IFERROR(F19/D19,0) | F19: =SUMIFS('12 Frequency and Success'!$J$16:$J$111,'12 Frequency and Success'!$A$16:$A$111,$B$6,'12 Frequency and Success'!$B$16:$B$111,$F$6,'12 Frequency and Success'!$C$16:$C$111,$A19)
A20: ='04 Exposure Adjustments'!B21 | B20: =SUMIFS('12 Frequency and Success'!$D$16:$D$111,'12 Frequency and Success'!$A$16:$A$111,$B$6,'12 Frequency and Success'!$B$16:$B$111,$F$6,'12 Frequency and Success'!$C$16:$C$111,$A20) | C20: =IFERROR(D20/B20,0) | D20: =SUMIFS('12 Frequency and Success'!$F$16:$F$111,'12 Frequency and Success'!$A$16:$A$111,$B$6,'12 Frequency and Success'!$B$16:$B$111,$F$6,'12 Frequency and Success'!$C$16:$C$111,$A20) | E20: =IFERROR(F20/D20,0) | F20: =SUMIFS('12 Frequency and Success'!$J$16:$J$111,'12 Frequency and Success'!$A$16:$A$111,$B$6,'12 Frequency and Success'!$B$16:$B$111,$F$6,'12 Frequency and Success'!$C$16:$C$111,$A20)
A23: ACTOR × SCENARIO AAL MATRIX
A24: AAL — Prudent | B24: Critical business-service disruption | C24: Sensitive-data compromise | D24: Data or transaction-integrity compromise | E24: Cyber-enabled theft or fraud
A25: Nation-state | B25: 34187.697 | C25: 42614.95 | D25: 39497.047 | E25: 7587.3365
A26: Cybercriminal | B26: 251325.1 | C26: 143618.54 | D26: 59240.441 | E26: 185707.97
A27: Malicious insider | B27: 58482.762 | C27: 94468.793 | D27: 81826.093 | E27: 63923.536 | J27: How to read this view Attempts / year is allocated campaign frequency. P(success) is the conditional probability that a material route succeeds. Events / year is their product. Expected event loss comes from the consequence model. AAL is therefore traceable to both likelihood and consequence rather than a standalone score.
A28: Hacktivist | B28: 229475.94 | C28: 9152.9954 | D28: 6470.7715 | E28: 1137.5952
J61: Route | K61: AAL
J62: =A15 | K62: =F15
J63: =A16 | K63: =F16
J64: =A17 | K64: =F17
J65: =A18 | K65: =F18
J66: =A19 | K66: =F19
J67: =A20 | K67: =F20

Sheet 00 Loss Analysis
A1: IT CYBER RISK QUANTIFICATION | LOSS ANALYSIS
A3: Bottom-up event consequence profile. Select an actor, scenario and quantile to see which impact drivers create the modeled loss.
A4: Sector | B4: ='02 Executive Summary'!B22 | E4: Pack | F4: ='02 Executive Summary'!B23 | I4: Event-loss drivers are not annualized here; they feed the consequence distribution used by the Monte Carlo engine.
A6: Threat actor | B6: ='02 Executive Summary'!A30 | D6: Scenario | F6: ='02 Executive Summary'!A37 | J6: Quantile | K6: P50 | M6: ="Source: 13 Consequence Calc"
A8: TOTAL EVENT LOSS | D8: BUSINESS INTERRUPTION | G8: BI SHARE | J8: IR / LEGAL / RESTORE | M8: FRAUD / EXTORTION
A9: =$N$61 | D9: =B15 | G9: =C15 | J9: =SUM(B21:B26) | M9: =SUM(B27:B28)
A13: DETAILED LOSS DRIVERS
A14: Driver | B14: Amount | C14: Share of event loss
A15: Business interruption | B15: =SUMIFS('13 Consequence Calc'!$G$16:$G$463,'13 Consequence Calc'!$A$16:$A$463,$B$6,'13 Consequence Calc'!$C$16:$C$463,$F$6,'13 Consequence Calc'!$E$16:$E$463,"BUSINESS_INTERRUPTION",'13 Consequence Calc'!$F$16:$F$463,$K$6) | C15: =IFERROR(B15/$N$61,0)
A16: Customer attrition | B16: =SUMIFS('13 Consequence Calc'!$G$16:$G$463,'13 Consequence Calc'!$A$16:$A$463,$B$6,'13 Consequence Calc'!$C$16:$C$463,$F$6,'13 Consequence Calc'!$E$16:$E$463,"CUSTOMER_ATTRITION",'13 Consequence Calc'!$F$16:$F$463,$K$6) | C16: =IFERROR(B16/$N$61,0)
A17: Post-event uplift | B17: =SUMIFS('13 Consequence Calc'!$G$16:$G$463,'13 Consequence Calc'!$A$16:$A$463,$B$6,'13 Consequence Calc'!$C$16:$C$463,$F$6,'13 Consequence Calc'!$E$16:$E$463,"POST_EVENT_UPLIFT",'13 Consequence Calc'!$F$16:$F$463,$K$6) | C17: =IFERROR(B17/$N$61,0)
A18: Notification | B18: =SUMIFS('13 Consequence Calc'!$G$16:$G$463,'13 Consequence Calc'!$A$16:$A$463,$B$6,'13 Consequence Calc'!$C$16:$C$463,$F$6,'13 Consequence Calc'!$E$16:$E$463,"NOTIFICATION",'13 Consequence Calc'!$F$16:$F$463,$K$6) | C18: =IFERROR(B18/$N$61,0)
A19: Credit monitoring | B19: =SUMIFS('13 Consequence Calc'!$G$16:$G$463,'13 Consequence Calc'!$A$16:$A$463,$B$6,'13 Consequence Calc'!$C$16:$C$463,$F$6,'13 Consequence Calc'!$E$16:$E$463,"CREDIT_MONITORING",'13 Consequence Calc'!$F$16:$F$463,$K$6) | C19: =IFERROR(B19/$N$61,0)
A20: Regulatory | B20: =SUMIFS('13 Consequence Calc'!$G$16:$G$463,'13 Consequence Calc'!$A$16:$A$463,$B$6,'13 Consequence Calc'!$C$16:$C$463,$F$6,'13 Consequence Calc'!$E$16:$E$463,"REGULATORY",'13 Consequence Calc'!$F$16:$F$463,$K$6) | C20: =IFERROR(B20/$N$61,0)
A21: IR / forensics | B21: =SUMIFS('13 Consequence Calc'!$G$16:$G$463,'13 Consequence Calc'!$A$16:$A$463,$B$6,'13 Consequence Calc'!$C$16:$C$463,$F$6,'13 Consequence Calc'!$E$16:$E$463,"IR_FORENSICS",'13 Consequence Calc'!$F$16:$F$463,$K$6) | C21: =IFERROR(B21/$N$61,0)
A22: External response | B22: =SUMIFS('13 Consequence Calc'!$G$16:$G$463,'13 Consequence Calc'!$A$16:$A$463,$B$6,'13 Consequence Calc'!$C$16:$C$463,$F$6,'13 Consequence Calc'!$E$16:$E$463,"EXTERNAL_RESPONSE",'13 Consequence Calc'!$F$16:$F$463,$K$6) | C22: =IFERROR(B22/$N$61,0)
A23: Legal response | B23: =SUMIFS('13 Consequence Calc'!$G$16:$G$463,'13 Consequence Calc'!$A$16:$A$463,$B$6,'13 Consequence Calc'!$C$16:$C$463,$F$6,'13 Consequence Calc'!$E$16:$E$463,"LEGAL_RESPONSE",'13 Consequence Calc'!$F$16:$F$463,$K$6) | C23: =IFERROR(B23/$N$61,0)
A24: Restoration | B24: =SUMIFS('13 Consequence Calc'!$G$16:$G$463,'13 Consequence Calc'!$A$16:$A$463,$B$6,'13 Consequence Calc'!$C$16:$C$463,$F$6,'13 Consequence Calc'!$E$16:$E$463,"RESTORATION",'13 Consequence Calc'!$F$16:$F$463,$K$6) | C24: =IFERROR(B24/$N$61,0)
A25: Endpoint recovery | B25: =SUMIFS('13 Consequence Calc'!$G$16:$G$463,'13 Consequence Calc'!$A$16:$A$463,$B$6,'13 Consequence Calc'!$C$16:$C$463,$F$6,'13 Consequence Calc'!$E$16:$E$463,"ENDPOINT_RECOVERY",'13 Consequence Calc'!$F$16:$F$463,$K$6) | C25: =IFERROR(B25/$N$61,0)
A26: Server recovery | B26: =SUMIFS('13 Consequence Calc'!$G$16:$G$463,'13 Consequence Calc'!$A$16:$A$463,$B$6,'13 Consequence Calc'!$C$16:$C$463,$F$6,'13 Consequence Calc'!$E$16:$E$463,"SERVER_RECOVERY",'13 Consequence Calc'!$F$16:$F$463,$K$6) | C26: =IFERROR(B26/$N$61,0)
A27: Fraud net of recovery | B27: =SUMIFS('13 Consequence Calc'!$G$16:$G$463,'13 Consequence Calc'!$A$16:$A$463,$B$6,'13 Consequence Calc'!$C$16:$C$463,$F$6,'13 Consequence Calc'!$E$16:$E$463,"FRAUD_NET_RECOVERY",'13 Consequence Calc'!$F$16:$F$463,$K$6) | C27: =IFERROR(B27/$N$61,0)
A28: Extortion | B28: =SUMIFS('13 Consequence Calc'!$G$16:$G$463,'13 Consequence Calc'!$A$16:$A$463,$B$6,'13 Consequence Calc'!$C$16:$C$463,$F$6,'13 Consequence Calc'!$E$16:$E$463,"EXTORTION",'13 Consequence Calc'!$F$16:$F$463,$K$6) | C28: =IFERROR(B28/$N$61,0)
A30: Interpretation This page is an event-level consequence explorer, not an annual-loss allocation. P50 and P99 values are built bottom-up from the BIA and scenario assumptions on sheet 06. The same actor/scenario event loss is then combined with route-level event frequency on sheet 12 and sampled in the annual Monte Carlo simulation.
J61: Loss category | K61: Amount | N61: =SUM(B15:B28)
J62: Business interruption | K62: =B15
J63: Customer / post-event | K63: =B16+B17
J64: Data / regulatory | K64: =B18+B19+B20
J65: Incident response / legal | K65: =B21+B22+B23
J66: Restoration / technology | K66: =B24+B25+B26
J67: Fraud / extortion | K67: =B27+B28

Sheet 00 What-If
A1: IT CYBER RISK QUANTIFICATION | CONTROL WHAT-IF
A3: Prioritise security investment by testing the one-level maturity uplift already calculated by the engine. Figures are analytic AAL, not a re-run Monte Carlo.
A4: Method | B4: ='16 Control What-If'!I16 | E4: View | F4: ='16 Control What-If'!J16 | I4: Use this page to rank marginal AAL reduction from the modelled one-level control maturity uplift.
A6: Control | B6: ='16 Control What-If'!B16 | J6: Maturity uplift | K6: =IFERROR(INDEX('16 Control What-If'!$C$16:$C$30,MATCH($B$6,'16 Control What-If'!$B$16:$B$30,0))&" → "&INDEX('16 Control What-If'!$D$16:$D$30,MATCH($B$6,'16 Control What-If'!$B$16:$B$30,0)),"")
A8: CURRENT ANALYTIC AAL | D8: WHAT-IF ANALYTIC AAL | G8: AAL REDUCTION | J8: REDUCTION % | M8: RANK
A9: =IFERROR(INDEX('16 Control What-If'!$E$16:$E$30,MATCH($B$6,'16 Control What-If'!$B$16:$B$30,0)),0) | D9: =IFERROR(INDEX('16 Control What-If'!$F$16:$F$30,MATCH($B$6,'16 Control What-If'!$B$16:$B$30,0)),0) | G9: =IFERROR(INDEX('16 Control What-If'!$G$16:$G$30,MATCH($B$6,'16 Control What-If'!$B$16:$B$30,0)),0) | J9: =IFERROR(INDEX('16 Control What-If'!$H$16:$H$30,MATCH($B$6,'16 Control What-If'!$B$16:$B$30,0)),0) | M9: =IFERROR(MATCH($B$6,'16 Control What-If'!$B$16:$B$30,0),0)
A13: CONTROL OPPORTUNITY RANKING | J13: TOP 10 AAL REDUCTION
A14: Rank | B14: Control family | C14: Current maturity | D14: What-if maturity | E14: AAL reduction | F14: Reduction %
A15: 1 | B15: ='16 Control What-If'!B16 | C15: ='16 Control What-If'!C16 | D15: ='16 Control What-If'!D16 | E15: ='16 Control What-If'!G16 | F15: ='16 Control What-If'!H16
A16: 2 | B16: ='16 Control What-If'!B17 | C16: ='16 Control What-If'!C17 | D16: ='16 Control What-If'!D17 | E16: ='16 Control What-If'!G17 | F16: ='16 Control What-If'!H17
A17: 3 | B17: ='16 Control What-If'!B18 | C17: ='16 Control What-If'!C18 | D17: ='16 Control What-If'!D18 | E17: ='16 Control What-If'!G18 | F17: ='16 Control What-If'!H18
A18: 4 | B18: ='16 Control What-If'!B19 | C18: ='16 Control What-If'!C19 | D18: ='16 Control What-If'!D19 | E18: ='16 Control What-If'!G19 | F18: ='16 Control What-If'!H19
A19: 5 | B19: ='16 Control What-If'!B20 | C19: ='16 Control What-If'!C20 | D19: ='16 Control What-If'!D20 | E19: ='16 Control What-If'!G20 | F19: ='16 Control What-If'!H20
A20: 6 | B20: ='16 Control What-If'!B21 | C20: ='16 Control What-If'!C21 | D20: ='16 Control What-If'!D21 | E20: ='16 Control What-If'!G21 | F20: ='16 Control What-If'!H21
A21: 7 | B21: ='16 Control What-If'!B22 | C21: ='16 Control What-If'!C22 | D21: ='16 Control What-If'!D22 | E21: ='16 Control What-If'!G22 | F21: ='16 Control What-If'!H22
A22: 8 | B22: ='16 Control What-If'!B23 | C22: ='16 Control What-If'!C23 | D22: ='16 Control What-If'!D23 | E22: ='16 Control What-If'!G23 | F22: ='16 Control What-If'!H23
A23: 9 | B23: ='16 Control What-If'!B24 | C23: ='16 Control What-If'!C24 | D23: ='16 Control What-If'!D24 | E23: ='16 Control What-If'!G24 | F23: ='16 Control What-If'!H24
A24: 10 | B24: ='16 Control What-If'!B25 | C24: ='16 Control What-If'!C25 | D24: ='16 Control What-If'!D25 | E24: ='16 Control What-If'!G25 | F24: ='16 Control What-If'!H25
A25: 11 | B25: ='16 Control What-If'!B26 | C25: ='16 Control What-If'!C26 | D25: ='16 Control What-If'!D26 | E25: ='16 Control What-If'!G26 | F25: ='16 Control What-If'!H26
A26: 12 | B26: ='16 Control What-If'!B27 | C26: ='16 Control What-If'!C27 | D26: ='16 Control What-If'!D27 | E26: ='16 Control What-If'!G27 | F26: ='16 Control What-If'!H27
... A29: 15 | B29: ='16 Control What-If'!B30 | C29: ='16 Control What-If'!C30 | D29: ='16 Control What-If'!D30 | E29: ='16 Control What-If'!G30 | F29: ='16 Control What-If'!H30
A31: Interpretation The what-if analysis changes one control family by one maturity level while holding other model inputs constant. The ranking is useful for prioritisation, but the displayed AAL is an analytic approximation rather than a second Monte Carlo distribution. A shortlisted control should therefore be validated against implementation feasibility, coverage, cost and any correlated control changes before being treated as an investment case.
J61: Control | K61: AAL reduction
J62: ='16 Control What-If'!B16 | K62: ='16 Control What-If'!G16
J63: ='16 Control What-If'!B17 | K63: ='16 Control What-If'!G17
J64: ='16 Control What-If'!B18 | K64: ='16 Control What-If'!G18
J65: ='16 Control What-If'!B19 | K65: ='16 Control What-If'!G19
J66: ='16 Control What-If'!B20 | K66: ='16 Control What-If'!G20
J67: ='16 Control What-If'!B21 | K67: ='16 Control What-If'!G21
J68: ='16 Control What-If'!B22 | K68: ='16 Control What-If'!G22
J69: ='16 Control What-If'!B23 | K69: ='16 Control What-If'!G23
J70: ='16 Control What-If'!B24 | K70: ='16 Control What-If'!G24
J71: ='16 Control What-If'!B25 | K71: ='16 Control What-If'!G25

Sheet 00 Risk Transfer
A1: IT CYBER RISK QUANTIFICATION | RISK TRANSFER
A3: Indicative limit diagnostic using the aggregate loss distribution. This page does not simulate policy terms, coverage or claims recoveries.
A4: Model retention | B4: ='08 Tail Risk Settings'!B18 | E4: Selected tail metric | F4: ='08 Tail Risk Settings'!B17 | I4: Use the dashboard-only limit below to test whether a proposed limit sits inside or outside modeled tail-loss levels.
A6: Reporting basis | B6: Prudent | D6: Loss curve | E6: AEP | G6: Illustrative insurance limit | H6: =IF($B$6="Best Estimate",'02 Executive Summary'!B11,'02 Executive Summary'!C11) | M6: Blue cell = dashboard input
A8: VaR 95% | D8: TVaR 95% | G8: VaR 99% | J8: TVaR 99% | M8: TVaR99 GAP ABOVE LIMIT
A9: =IF($B$6="Best Estimate",'02 Executive Summary'!B8,'02 Executive Summary'!C8) | D9: =IF($B$6="Best Estimate",'02 Executive Summary'!B9,'02 Executive Summary'!C9) | G9: =IF($B$6="Best Estimate",'02 Executive Summary'!B10,'02 Executive Summary'!C10) | J9: =IF($B$6="Best Estimate",'02 Executive Summary'!B11,'02 Executive Summary'!C11) | M9: =MAX(J9-$B$4-$H$6,0)
A12: ="Limit / TVaR95: "&TEXT(IFERROR($H$6/D9,0),"0%") | G12: ="Limit / TVaR99: "&TEXT(IFERROR($H$6/J9,0),"0%") | M12: ="Retention: "&TEXT($B$4,"$#,##0")
A14: RETURN-PERIOD DIAGNOSTIC | F14: LOSS CURVE VS ILLUSTRATIVE LIMIT
A15: Return period | B15: Exceedance probability | C15: Selected loss | D15: Amount above retention + limit
A16: ='17 Aggregate LECs'!A16 | B16: ='17 Aggregate LECs'!B16 | C16: =IF($B$6="Best Estimate",IF($E$6="AEP",'17 Aggregate LECs'!C16,'17 Aggregate LECs'!D16),IF($E$6="AEP",'17 Aggregate LECs'!E16,'17 Aggregate LECs'!F16)) | D16: =MAX(C16-$B$4-$H$6,0)
A17: ='17 Aggregate LECs'!A17 | B17: ='17 Aggregate LECs'!B17 | C17: =IF($B$6="Best Estimate",IF($E$6="AEP",'17 Aggregate LECs'!C17,'17 Aggregate LECs'!D17),IF($E$6="AEP",'17 Aggregate LECs'!E17,'17 Aggregate LECs'!F17)) | D17: =MAX(C17-$B$4-$H$6,0)
A18: ='17 Aggregate LECs'!A18 | B18: ='17 Aggregate LECs'!B18 | C18: =IF($B$6="Best Estimate",IF($E$6="AEP",'17 Aggregate LECs'!C18,'17 Aggregate LECs'!D18),IF($E$6="AEP",'17 Aggregate LECs'!E18,'17 Aggregate LECs'!F18)) | D18: =MAX(C18-$B$4-$H$6,0)
A19: ='17 Aggregate LECs'!A19 | B19: ='17 Aggregate LECs'!B19 | C19: =IF($B$6="Best Estimate",IF($E$6="AEP",'17 Aggregate LECs'!C19,'17 Aggregate LECs'!D19),IF($E$6="AEP",'17 Aggregate LECs'!E19,'17 Aggregate LECs'!F19)) | D19: =MAX(C19-$B$4-$H$6,0)
A20: ='17 Aggregate LECs'!A20 | B20: ='17 Aggregate LECs'!B20 | C20: =IF($B$6="Best Estimate",IF($E$6="AEP",'17 Aggregate LECs'!C20,'17 Aggregate LECs'!D20),IF($E$6="AEP",'17 Aggregate LECs'!E20,'17 Aggregate LECs'!F20)) | D20: =MAX(C20-$B$4-$H$6,0)
A21: ='17 Aggregate LECs'!A21 | B21: ='17 Aggregate LECs'!B21 | C21: =IF($B$6="Best Estimate",IF($E$6="AEP",'17 Aggregate LECs'!C21,'17 Aggregate LECs'!D21),IF($E$6="AEP",'17 Aggregate LECs'!E21,'17 Aggregate LECs'!F21)) | D21: =MAX(C21-$B$4-$H$6,0)
A22: ='17 Aggregate LECs'!A22 | B22: ='17 Aggregate LECs'!B22 | C22: =IF($B$6="Best Estimate",IF($E$6="AEP",'17 Aggregate LECs'!C22,'17 Aggregate LECs'!D22),IF($E$6="AEP",'17 Aggregate LECs'!E22,'17 Aggregate LECs'!F22)) | D22: =MAX(C22-$B$4-$H$6,0)
A23: ='17 Aggregate LECs'!A23 | B23: ='17 Aggregate LECs'!B23 | C23: =IF($B$6="Best Estimate",IF($E$6="AEP",'17 Aggregate LECs'!C23,'17 Aggregate LECs'!D23),IF($E$6="AEP",'17 Aggregate LECs'!E23,'17 Aggregate LECs'!F23)) | D23: =MAX(C23-$B$4-$H$6,0)
A24: ='17 Aggregate LECs'!A24 | B24: ='17 Aggregate LECs'!B24 | C24: =IF($B$6="Best Estimate",IF($E$6="AEP",'17 Aggregate LECs'!C24,'17 Aggregate LECs'!D24),IF($E$6="AEP",'17 Aggregate LECs'!E24,'17 Aggregate LECs'!F24)) | D24: =MAX(C24-$B$4-$H$6,0)
A25: ='17 Aggregate LECs'!A25 | B25: ='17 Aggregate LECs'!B25 | C25: =IF($B$6="Best Estimate",IF($E$6="AEP",'17 Aggregate LECs'!C25,'17 Aggregate LECs'!D25),IF($E$6="AEP",'17 Aggregate LECs'!E25,'17 Aggregate LECs'!F25)) | D25: =MAX(C25-$B$4-$H$6,0)
A27: Important The 'amount above retention + limit' is a simple tail diagnostic. It is not the expected uninsured loss under a policy. A true insurance view would need policy attachment, limit, sub-limits, exclusions/coverage, reinstatements and claim-level recovery logic applied inside the simulation.
F31: Use case This view is designed to support a limit discussion: compare a proposed limit against the modeled annual and occurrence loss curve and the 95%/99% tail metrics. It should inform, not replace, insurance structuring and broker/underwriter judgement.
J61: Return period | K61: Selected loss | L61: Illustrative limit
J62: =A16 | K62: =C16 | L62: =$H$6
J63: =A17 | K63: =C17 | L63: =$H$6
J64: =A18 | K64: =C18 | L64: =$H$6
J65: =A19 | K65: =C19 | L65: =$H$6
J66: =A20 | K66: =C20 | L66: =$H$6
J67: =A21 | K67: =C21 | L67: =$H$6
J68: =A22 | K68: =C22 | L68: =$H$6
J69: =A23 | K69: =C23 | L69: =$H$6
J70: =A24 | K70: =C24 | L70: =$H$6
J71: =A25 | K71: =C25 | L71: =$H$6
